Workbook

Sheet Lisez-moi
B2: Export CRM - Orvane Solutions (données de démonstration)
B3: Jeu de données pivot commun aux démonstrateurs « Préparation des visites commerciales » (Claude, Gemini, Copilot).
B5: Contexte
B6: Société | C6: Orvane Solutions, société fictive : fabricant français de solutions d'emballage (étuis, étiquettes, coffrets, caisses) et d'équipements de conditionnement.
B7: Format | C7: Export simulé d'un CRM de type HubSpot ou Salesforce : un onglet par objet, une ligne d'en-tête, des identifiants stables reliant les onglets.
B8: Date de l'export | C8: =DateExport
B9: Historique | C9: Activités depuis janvier 2025, commandes depuis octobre 2024, rendez-vous planifiés jusqu'à mi-novembre 2026.
B11: Avertissement
B12: Entreprises réelles | C12: Les 30 entreprises clientes sont réelles. Leurs données publiques (adresse, site web, activité, tranche de chiffre d'affaires, groupe, code bourse) sont issues de sources publiques et vérifiées en octobre 2026, pour que l'agent puisse les enrichir avec leur actualité et leur cours de bourse.
B13: Données fictives | C13: Le fournisseur Orvane Solutions, les contacts, les échanges, les montants, les commandes, les tickets et les rendez-vous sont entièrement inventés : aucune ligne ne reflète une relation commerciale existante.
B14: Coordonnées | C14: Les e-mails utilisent le domaine réservé .example et ne peuvent pas être délivrés. Les numéros de téléphone sont fictifs.
B16: Modèle de données
B17: Onglet | C17: Contenu | D17: Lignes | E17: Clé et liens
B18: Commerciaux | C18: Équipe commerciale (propriétaires des comptes) et indicateurs de portefeuille. | D18: =COUNTA(Commerciaux!$A$2:$A$3000) | E18: ID commercial (U...)
B19: Entreprises | C19: Comptes clients, opportunités et prospects, avec contexte et enjeux. | D19: =COUNTA(Entreprises!$A$2:$A$3000) | E19: ID entreprise (E...) ; ID propriétaire → Commerciaux
B20: Contacts | C20: Interlocuteurs chez les comptes (50 contacts). | D20: =COUNTA(Contacts!$A$2:$A$3000) | E20: ID contact (C...) ; ID entreprise → Entreprises
B21: Transactions | C21: Opportunités ouvertes, gagnées et perdues du pipeline « Ventes terrain ». | D21: =COUNTA(Transactions!$A$2:$A$3000) | E21: ID transaction (T...) ; → Entreprises, Contacts, Produits
B22: Activités | C22: Historique des visites, appels, e-mails, visios et notes, avec comptes rendus. | D22: =COUNTA(Activités!$A$2:$A$3000) | E22: ID activité (A...) ; → Entreprises, Contacts, Transactions
B23: Rendez-vous | C23: Rendez-vous à venir, avec colonnes à compléter par l'assistant. | D23: =COUNTA('Rendez-vous'!$A$2:$A$3000) | E23: ID rendez-vous (R...) ; → Entreprises, Contacts, Transactions
B24: Tickets | C24: Demandes et réclamations du service client. | D24: =COUNTA(Tickets!$A$2:$A$3000) | E24: ID ticket (K...) ; → Entreprises, Contacts
B25: Commandes | C25: Historique des commandes et des livraisons. | D25: =COUNTA(Commandes!$A$2:$A$3000) | E25: ID commande (CMD-...) ; → Entreprises, Produits
B26: Produits | C26: Catalogue et prix de vente. | D26: =COUNTA(Produits!$A$2:$A$3000) | E26: ID produit (P...)
B27: Paramètres | C27: Date de l'export et listes de valeurs (phases, statuts, types). | E27: Champ nommé DateExport
B29: Lecture des en-têtes
B30: Bleu foncé | C30: Donnée saisie dans le CRM.
B31: Gris | C31: Colonne calculée par formule (ne pas saisir).
B32: Orange | C32: Colonne à compléter par l'assistant (brief préparé, compte rendu).
B34: Scénario de démonstration
B35: Commercial | C35: Julien Morel (U002), commercial terrain Hauts-de-France et Île-de-France.
B36: Lundi 12/10/2026 | C36: Trois rendez-vous : R001 Bonduelle (9h30, sur site), R002 Lesaffre (14h00, sur site), R003 Guerbet (17h00, visio).
B37: Après la visite | C37: Le compte rendu validé par le commercial peut être saisi dans Rendez-vous (colonne Compte rendu de visite) et ajouté comme nouvelle ligne de type « Visite terrain » dans Activités.

Sheet Paramètres
A1: Paramètres et listes de référence
A3: Date de l'export | B3: 46304 | C3: Date de référence de toutes les formules (champ nommé DateExport). La modifier recalcule les indicateurs.
A6: Phase de la transaction | B6: Probabilité | C6: Statut | E6: Secteur d'activité | F6: Segment | G6: Phase du cycle de vie | H6: Statut du compte | I6: Type d'activité | J6: Résultat | K6: Type de rendez-vous | L6: Statut du rendez-vous | M6: Catégorie de ticket | N6: Priorité | O6: Statut du ticket | P6: Statut de commande | Q6: Type de transaction | R6: Niveau de décision | S6: Canal préféré | T6: Source d'origine | U6: Statut du lead | V6: Oui / Non | W6: Famille de produit | X6: Tranche d'effectif | Y6: Civilité | Z6: Tranche de CA
A7: Rendez-vous programmé | B7: 0.2 | C7: Ouverte | E7: Pharmaceutique et santé | F7: Grand compte | G7: Lead | H7: Nouveau | I7: Visite terrain | J7: Positif | K7: Visite sur site | L7: Planifié | M7: Livraison | N7: Basse | O7: Nouveau | P7: En cours de livraison | Q7: Nouvelle affaire | R7: Décideur | S7: Visite | T7: Salon professionnel | U7: Nouveau | V7: Oui | W7: Consommables | X7: 1 - 49 | Y7: M. | Z7: Moins de 10 M€
A8: Qualifié pour achat | B8: 0.4 | C8: Ouverte | E8: Vins et spiritueux | F8: ETI | G8: Prospect | H8: En développement | I8: Appel | J8: Neutre | K8: Visio | L8: Confirmé | M8: Qualité produit | N8: Normale | O8: En cours | P8: Livrée | Q8: Affaire existante | R8: Influenceur | S8: Téléphone | T8: Recommandation | U8: Ouvert | V8: Non | W8: Équipements | X8: 50 - 249 | Y8: Mme | Z8: 10 - 100 M€
A9: Présentation planifiée | B9: 0.6 | C9: Ouverte | E9: Grande consommation | F9: PME | G9: Opportunité | H9: Actif | I9: E-mail | J9: À relancer | K9: Déjeuner d'affaires | L9: À reprogrammer | M9: Facturation | N9: Haute | O9: En attente client | P9: Facturée | Q9: Renouvellement | R9: Prescripteur | S9: E-mail | T9: Prospection terrain | U9: Tentative de contact | W9: Services | X9: 250 - 999 | Z9: 100 M€ - 1 Md€
A10: Décideur impliqué | B10: 0.8 | C10: Ouverte | E10: Équipements et matériaux | G10: Client | H10: À surveiller | I10: Réunion visio | J10: Négatif | L10: Annulé | M10: Technique équipement | N10: Critique | O10: Fermé | R10: Utilisateur | S10: Visio | T10: Prospection téléphonique | U10: Connecté | X10: 1 000 - 4 999 | Z10: 1 - 10 Md€
A11: Contrat envoyé | B11: 0.9 | C11: Ouverte | H11: À risque | I11: Note | L11: Réalisé | M11: Documentation | T11: Site web | U11: Affaire ouverte | X11: 5 000 - 9 999 | Z11: Plus de 10 Md€
A12: Conclu gagné | B12: 1 | C12: Gagnée | T12: Événement / webinaire | U12: Non qualifié | X12: 10 000 et plus | Z12: Non publié
A13: Conclu perdu | B13: 0 | C13: Perdue | Z13: Non publié (filiale)

Sheet Commerciaux
A1: ID commercial | B1: Prénom | C1: Nom | D1: Nom complet | E1: E-mail | F1: Téléphone mobile | G1: Profil métier | H1: Équipe | I1: Territoire | J1: Manager | K1: Date d'arrivée | L1: Objectif CA annuel (€) | M1: Comptes en portefeuille | N1: CA 12 derniers mois du portefeuille (€) | O1: Pipeline pondéré ouvert (€) | P1: Rendez-vous à venir
A2: U001 | B2: Camille | C2: Laurent | D2: =B2&" "&C2 | E2: camille.laurent@orvane-solutions.example | F2: +33 6 39 98 10 20 | G2: Directrice commerciale | H2: Direction commerciale | I2: France | K2: 43528 | M2: =COUNTIF(Entreprises!$S$2:$S$3000,A2) | N2: =SUMIFS(Entreprises!$AA$2:$AA$3000,Entreprises!$S$2:$S$3000,A2) | O2: =SUMIFS(Transactions!$M$2:$M$3000,Transactions!$G$2:$G$3000,A2,Transactions!$N$2:$N$3000,"Ouverte") | P2: =COUNTIFS('Rendez-vous'!$K$2:$K$3000,A2,'Rendez-vous'!$B$2:$B$3000,">="&DateExport)
A3: U002 | B3: Julien | C3: Morel | D3: =B3&" "&C3 | E3: julien.morel@orvane-solutions.example | F3: +33 6 39 98 17 31 | G3: Commercial terrain | H3: Ventes terrain | I3: Hauts-de-France et Île-de-France | J3: Camille Laurent | K3: 44440 | L3: 1400000 | M3: =COUNTIF(Entreprises!$S$2:$S$3000,A3) | N3: =SUMIFS(Entreprises!$AA$2:$AA$3000,Entreprises!$S$2:$S$3000,A3) | O3: =SUMIFS(Transactions!$M$2:$M$3000,Transactions!$G$2:$G$3000,A3,Transactions!$N$2:$N$3000,"Ouverte") | P3: =COUNTIFS('Rendez-vous'!$K$2:$K$3000,A3,'Rendez-vous'!$B$2:$B$3000,">="&DateExport)
A4: U003 | B4: Sarah | C4: Benali | D4: =B4&" "&C4 | E4: sarah.benali@orvane-solutions.example | F4: +33 6 39 98 24 42 | G4: Commerciale terrain | H4: Ventes terrain | I4: Champagne et Grand Est | J4: Camille Laurent | K4: 44571 | L4: 1100000 | M4: =COUNTIF(Entreprises!$S$2:$S$3000,A4) | N4: =SUMIFS(Entreprises!$AA$2:$AA$3000,Entreprises!$S$2:$S$3000,A4) | O4: =SUMIFS(Transactions!$M$2:$M$3000,Transactions!$G$2:$G$3000,A4,Transactions!$N$2:$N$3000,"Ouverte") | P4: =COUNTIFS('Rendez-vous'!$K$2:$K$3000,A4,'Rendez-vous'!$B$2:$B$3000,">="&DateExport)
A5: U004 | B5: Maxime | C5: Garnier | D5: =B5&" "&C5 | E5: maxime.garnier@orvane-solutions.example | F5: +33 6 39 98 31 53 | G5: Commercial terrain | H5: Ventes terrain | I5: Auvergne-Rhône-Alpes et Sud-Est | J5: Camille Laurent | K5: 43969 | L5: 1300000 | M5: =COUNTIF(Entreprises!$S$2:$S$3000,A5) | N5: =SUMIFS(Entreprises!$AA$2:$AA$3000,Entreprises!$S$2:$S$3000,A5) | O5: =SUMIFS(Transactions!$M$2:$M$3000,Transactions!$G$2:$G$3000,A5,Transactions!$N$2:$N$3000,"Ouverte") | P5: =COUNTIFS('Rendez-vous'!$K$2:$K$3000,A5,'Rendez-vous'!$B$2:$B$3000,">="&DateExport)
A6: U005 | B6: Élodie | C6: Fabre | D6: =B6&" "&C6 | E6: elodie.fabre@orvane-solutions.example | F6: +33 6 39 98 38 64 | G6: Commerciale terrain | H6: Ventes terrain | I6: Nouvelle-Aquitaine et Occitanie | J6: Camille Laurent | K6: 44963 | L6: 1000000 | M6: =COUNTIF(Entreprises!$S$2:$S$3000,A6) | N6: =SUMIFS(Entreprises!$AA$2:$AA$3000,Entreprises!$S$2:$S$3000,A6) | O6: =SUMIFS(Transactions!$M$2:$M$3000,Transactions!$G$2:$G$3000,A6,Transactions!$N$2:$N$3000,"Ouverte") | P6: =COUNTIFS('Rendez-vous'!$K$2:$K$3000,A6,'Rendez-vous'!$B$2:$B$3000,">="&DateExport)
A7: U006 | B7: Thomas | C7: Roussel | D7: =B7&" "&C7 | E7: thomas.roussel@orvane-solutions.example | F7: +33 6 39 98 45 75 | G7: Key Account Manager | H7: Grands comptes | I7: National - Santé | J7: Camille Laurent | K7: 43409 | L7: 2500000 | M7: =COUNTIF(Entreprises!$S$2:$S$3000,A7) | N7: =SUMIFS(Entreprises!$AA$2:$AA$3000,Entreprises!$S$2:$S$3000,A7) | O7: =SUMIFS(Transactions!$M$2:$M$3000,Transactions!$G$2:$G$3000,A7,Transactions!$N$2:$N$3000,"Ouverte") | P7: =COUNTIFS('Rendez-vous'!$K$2:$K$3000,A7,'Rendez-vous'!$B$2:$B$3000,">="&DateExport)
A8: U007 | B8: Inès | C8: Caron | D8: =B8&" "&C8 | E8: ines.caron@orvane-solutions.example | F8: +33 6 39 98 52 86 | G8: Key Account Manager | H8: Grands comptes | I8: National - Grande consommation et Industrie | J8: Camille Laurent | K8: 43633 | L8: 2800000 | M8: =COUNTIF(Entreprises!$S$2:$S$3000,A8) | N8: =SUMIFS(Entreprises!$AA$2:$AA$3000,Entreprises!$S$2:$S$3000,A8) | O8: =SUMIFS(Transactions!$M$2:$M$3000,Transactions!$G$2:$G$3000,A8,Transactions!$N$2:$N$3000,"Ouverte") | P8: =COUNTIFS('Rendez-vous'!$K$2:$K$3000,A8,'Rendez-vous'!$B$2:$B$3000,">="&DateExport)

Sheet Produits
A1: ID produit | B1: Référence | C1: Nom du produit | D1: Famille | E1: Description | F1: Unité de vente | G1: Prix unitaire HT (€) | H1: Marchés cibles | I1: Actif
A2: P001 | B2: ETU-PH-100 | C2: Étuis carton pharmaceutiques imprimés | D2: Consommables | E2: Étuis pliants en carton compact, impression offset, compatibles encartonneuses pharmaceutiques. | F2: Lot de 1 000 étuis | G2: 185 | H2: Pharmaceutique et santé | I2: Oui
A3: P002 | B3: NOT-PH-200 | C3: Notices pharmaceutiques pliées | D3: Consommables | E3: Notices papier bible pliées, multilingues, conformes aux exigences réglementaires. | F3: Lot de 1 000 notices | G3: 95 | H3: Pharmaceutique et santé | I3: Oui
A4: P003 | B4: ETQ-HR-300 | C4: Étiquettes adhésives haute définition | D4: Consommables | E4: Étiquettes papier ou synthétiques, impression numérique, résistance humidité et froid. | F4: Rouleau de 5 000 étiquettes | G4: 240 | H4: Tous marchés | I4: Oui
A5: P004 | B5: ETQ-TE-310 | C5: Étiquettes d'inviolabilité | D5: Consommables | E5: Étiquettes de première ouverture (tamper-evident) avec découpe de sécurité. | F5: Rouleau de 5 000 étiquettes | G5: 310 | H5: Pharmaceutique et santé ; Vins et spiritueux | I5: Oui
A6: P005 | B6: COF-PR-400 | C6: Coffrets rigides premium | D6: Consommables | E6: Coffrets carton rigide habillés, calage carton, finitions dorure et gaufrage. | F6: Lot de 100 coffrets | G6: 1450 | H6: Vins et spiritueux ; Grande consommation | I6: Oui
A7: P006 | B7: ETU-SP-410 | C7: Étuis spiritueux luxe | D7: Consommables | E7: Étuis carton luxe avec dorure à chaud et vernis sélectif. | F7: Lot de 500 étuis | G7: 1150 | H7: Vins et spiritueux | I7: Oui
A8: P007 | B8: CAI-OND-500 | C8: Caisses carton ondulé personnalisées | D8: Consommables | E8: Caisses américaines et wrap-around, impression flexo, cannelures adaptées au transport. | F8: Palette de 500 caisses | G8: 620 | H8: Tous marchés | I8: Oui
A9: P008 | B9: ECO-MM-520 | C9: Emballages éco-conçus mono-matériau | D9: Consommables | E9: Étuis et calages 100 % carton, fibres certifiées, sans plastique. | F9: Lot de 1 000 unités | G9: 410 | H9: Tous marchés | I9: Oui
A10: P009 | B10: SER-DM-600 | C10: Solution de sérialisation DataMatrix | D10: Équipements | E10: Module d'impression et de contrôle DataMatrix avec logiciel d'agrégation. | F10: Unité | G10: 68000 | H10: Pharmaceutique et santé | I10: Oui
A11: P010 | B11: ETQ-AUTO-400 | C11: Étiqueteuse automatique ETQ-400 | D11: Équipements | E11: Étiqueteuse automatique jusqu'à 200 produits par minute. | F11: Unité | G11: 42000 | H11: Tous marchés | I11: Oui
A12: P011 | B12: ENC-200 | C12: Encartonneuse automatique EC-200 | D12: Équipements | E12: Encartonneuse automatique jusqu'à 20 cartons par minute, changement de format rapide. | F12: Unité | G12: 125000 | H12: Tous marchés | I12: Oui
A13: P012 | B13: MNT-PREV-01 | C13: Contrat de maintenance préventive | D13: Services | E13: Deux visites préventives par an, assistance téléphonique et pièces d'usure. | F13: Contrat annuel | G13: 9600 | H13: Tous marchés | I13: Oui
... A15: P014 | B15: FOR-OPE-01 | C15: Formation opérateurs | D15: Services | E15: Formation sur site à la conduite et au réglage des équipements. | F15: Journée | G15: 1200 | H15: Tous marchés | I15: Oui

Sheet Entreprises
A1: ID entreprise | B1: Nom de l'entreprise | C1: Domaine du site web | D1: Site web | E1: Description de l'activité | F1: Secteur d'activité | G1: Sous-secteur | H1: Segment | I1: Tranche d'effectif | J1: Chiffre d'affaires annuel (tranche) | K1: Adresse | L1: Code postal | M1: Ville | N1: Région | O1: Pays | P1: Groupe / société mère | Q1: Cotée en bourse | R1: Code bourse (Yahoo Finance) | S1: ID propriétaire | T1: Propriétaire du compte | U1: Phase du cycle de vie | V1: Statut du compte | W1: Date de création | X1: Client depuis | Y1: Source d'origine | Z1: Potentiel annuel estimé (€) | AA1: CA 12 derniers mois (€) | AB1: Transactions ouvertes | AC1: Pipeline ouvert (€) | AD1: Tickets ouverts | AE1: Date de dernière activité | AF1: Prochain rendez-vous | AG1: Concurrent principal | AH1: Conditions de paiement | AI1: Contexte client | AJ1: Enjeux et projets en cours
A2: E001 | B2: Bonduelle | C2: bonduelle.com | D2: https://www.bonduelle.com | E2: Groupe agroalimentaire familial spécialisé dans les légumes transformés (conserve, surgelé, frais) ; marques Bonduelle et Cassegrain. | F2: Grande consommation | G2: Légumes transformés | H2: Grand compte | I2: 10 000 et plus | J2: 1 - 10 Md€ | K2: Rue Nicolas Appert | L2: 59650 | M2: Villeneuve-d'Ascq | N2: Hauts-de-France | O2: France | P2: Groupe Bonduelle | Q2: Oui | R2: BON.PA | S2: U002 | T2: =IFERROR(INDEX(Commerciaux!$D$2:$D$3000,MATCH(S2,Commerciaux!$A$2:$A$3000,0)),"") | U2: Client | V2: À surveiller | W2: 44481 | X2: 44621 | Y2: Salon professionnel | Z2: 420000 | AA2: =SUMIFS(Commandes!$K$2:$K$3000,Commandes!$D$2:$D$3000,A2,Commandes!$C$2:$C$3000,">"&(DateExport-365),Commandes!$C$2:$C$3000,"<="&DateExport) | AB2: =COUNTIFS(Transactions!$C$2:$C$3000,A2,Transactions!$N$2:$N$3000,"Ouverte") | AC2: =SUMIFS(Transactions!$L$2:$L$3000,Transactions!$C$2:$C$3000,A2,Transactions!$N$2:$N$3000,"Ouverte") | AD2: =COUNTIFS(Tickets!$C$2:$C$3000,A2,Tickets!$I$2:$I$3000,"<>Fermé") | AE2: =IF(COUNTIFS(Activités!$D$2:$D$3000,A2,Activités!$B$2:$B$3000,"<="&DateExport)=0,"",_xlfn.MAXIFS(Activités!$B$2:$B$3000,Activités!$D$2:$D$3000,A2,Activités!$B$2:$B$3000,"<="&DateExport)) | AF2: =IF(COUNTIFS('Rendez-vous'!$F$2:$F$3000,A2,'Rendez-vous'!$B$2:$B$3000,">="&DateExport)=0,"",_xlfn.MINIFS('Rendez-vous'!$B$2:$B$3000,'Rendez-vous'!$F$2:$F$3000,A2,'Rendez-vous'!$B$2:$B$3000,">="&DateExport)) | AG2: Labelis Group | AH2: 60 jours fin de mois | AI2: Client historique sur les étiquettes adhésives des gammes conserve. Les achats emballages sont pilotés depuis Villeneuve-d'Ascq, avec une validation qualité systématique de chaque nouvelle référence. Le groupe mène un plan de transformation centré sur la rentabilité et le désendettement : la direction achats a durci ses objectifs de réduction des coûts d'emballage. | AJ2: Renouvellement de l'accord-cadre étiquettes 2027 ; passage à des emballages mono-matériau sur deux gammes ; sécurisation des délais de livraison après le retard de septembre.
A3: E002 | B3: Lesaffre | C3: lesaffre.com | D3: https://www.lesaffre.com | E3: Groupe familial, leader mondial des levures et ferments pour la panification, la nutrition, la santé et les biotechnologies. | F3: Grande consommation | G3: Ingrédients et levures | H3: Grand compte | I3: 10 000 et plus | J3: 1 - 10 Md€ | K3: 137 rue Gabriel Péri | L3: 59700 | M3: Marcq-en-Barœul | N3: Hauts-de-France | O3: France | P3: Groupe Lesaffre | Q3: Non | S3: U002 | T3: =IFERROR(INDEX(Commerciaux!$D$2:$D$3000,MATCH(S3,Commerciaux!$A$2:$A$3000,0)),"") | U3: Client | V3: Actif | W3: 44684 | X3: 44880 | Y3: Prospection terrain | Z3: 380000 | AA3: =SUMIFS(Commandes!$K$2:$K$3000,Commandes!$D$2:$D$3000,A3,Commandes!$C$2:$C$3000,">"&(DateExport-365),Commandes!$C$2:$C$3000,"<="&DateExport) | AB3: =COUNTIFS(Transactions!$C$2:$C$3000,A3,Transactions!$N$2:$N$3000,"Ouverte") | AC3: =SUMIFS(Transactions!$L$2:$L$3000,Transactions!$C$2:$C$3000,A3,Transactions!$N$2:$N$3000,"Ouverte") | AD3: =COUNTIFS(Tickets!$C$2:$C$3000,A3,Tickets!$I$2:$I$3000,"<>Fermé") | AE3: =IF(COUNTIFS(Activités!$D$2:$D$3000,A3,Activités!$B$2:$B$3000,"<="&DateExport)=0,"",_xlfn.MAXIFS(Activités!$B$2:$B$3000,Activités!$D$2:$D$3000,A3,Activités!$B$2:$B$3000,"<="&DateExport)) | AF3: =IF(COUNTIFS('Rendez-vous'!$F$2:$F$3000,A3,'Rendez-vous'!$B$2:$B$3000,">="&DateExport)=0,"",_xlfn.MINIFS('Rendez-vous'!$B$2:$B$3000,'Rendez-vous'!$F$2:$F$3000,A3,'Rendez-vous'!$B$2:$B$3000,">="&DateExport)) | AG3: Emballor Industries | AH3: 45 jours fin de mois | AI3: Client sur les caisses carton et les étiquettes. Groupe familial en croissance qui investit dans de nouvelles capacités industrielles, en France comme à l'international. Relation construite avec le service achats ; l'arrivée d'un nouveau directeur industriel en 2026 ouvre la discussion sur l'automatisation des fins de ligne. | AJ3: Automatiser la mise en carton d'une ligne de levure sèche ; réduire la pénibilité au poste de palettisation ; décision d'investissement attendue avant la clôture budgétaire de fin d'année.
A4: E003 | B4: Guerbet | C4: guerbet.com | D4: https://www.guerbet.com | E4: Laboratoire pharmaceutique spécialiste des produits de contraste pour l'imagerie médicale et de la radiologie interventionnelle. | F4: Pharmaceutique et santé | G4: Imagerie médicale | H4: ETI | I4: 1 000 - 4 999 | J4: 100 M€ - 1 Md€ | K4: 15 rue des Vanesses | L4: 93420 | M4: Villepinte | N4: Île-de-France | O4: France | P4: Groupe Guerbet | Q4: Oui | R4: GBT.PA | S4: U002 | T4: =IFERROR(INDEX(Commerciaux!$D$2:$D$3000,MATCH(S4,Commerciaux!$A$2:$A$3000,0)),"") | U4: Client | V4: À risque | W4: 43871 | X4: 44075 | Y4: Recommandation | Z4: 260000 | AA4: =SUMIFS(Commandes!$K$2:$K$3000,Commandes!$D$2:$D$3000,A4,Commandes!$C$2:$C$3000,">"&(DateExport-365),Commandes!$C$2:$C$3000,"<="&DateExport) | AB4: =COUNTIFS(Transactions!$C$2:$C$3000,A4,Transactions!$N$2:$N$3000,"Ouverte") | AC4: =SUMIFS(Transactions!$L$2:$L$3000,Transactions!$C$2:$C$3000,A4,Transactions!$N$2:$N$3000,"Ouverte") | AD4: =COUNTIFS(Tickets!$C$2:$C$3000,A4,Tickets!$I$2:$I$3000,"<>Fermé") | AE4: =IF(COUNTIFS(Activités!$D$2:$D$3000,A4,Activités!$B$2:$B$3000,"<="&DateExport)=0,"",_xlfn.MAXIFS(Activités!$B$2:$B$3000,Activités!$D$2:$D$3000,A4,Activités!$B$2:$B$3000,"<="&DateExport)) | AF4: =IF(COUNTIFS('Rendez-vous'!$F$2:$F$3000,A4,'Rendez-vous'!$B$2:$B$3000,">="&DateExport)=0,"",_xlfn.MINIFS('Rendez-vous'!$B$2:$B$3000,'Rendez-vous'!$F$2:$F$3000,A4,'Rendez-vous'!$B$2:$B$3000,">="&DateExport)) | AG4: Kartéa Pharma Pack | AH4: 60 jours | AI4: Client sur les étuis et notices pharmaceutiques. Exigences qualité très élevées et audits fournisseurs annuels. Le groupe traverse une période difficile (plan de transformation, réduction des coûts, changement de direction générale) : les achats renégocient les contrats fournisseurs et la qualité est sous surveillance renforcée. Une non-conformité d'impression en juin 2026 a fragilisé la relation. | AJ4: Restaurer la confiance après l'incident qualité de juin ; réussir l'audit fournisseur de novembre ; projet de refonte des notices multilingues pour 2027.
A5: E004 | B5: Interparfums | C5: interparfums.fr | D5: https://www.interparfums.fr | E5: Créateur et distributeur de parfums sous licence et marques propres (Montblanc, Jimmy Choo, Coach, Lacoste, Lanvin). | F5: Grande consommation | G5: Parfums et cosmétiques | H5: ETI | I5: 250 - 999 | J5: 100 M€ - 1 Md€ | K5: 10 rue de Solférino | L5: 75007 | M5: Paris | N5: Île-de-France | O5: France | P5: Interparfums | Q5: Oui | R5: ITP.PA | S5: U002 | T5: =IFERROR(INDEX(Commerciaux!$D$2:$D$3000,MATCH(S5,Commerciaux!$A$2:$A$3000,0)),"") | U5: Client | V5: Actif | W5: 44942 | X5: 45082 | Y5: Salon professionnel | Z5: 210000 | AA5: =SUMIFS(Commandes!$K$2:$K$3000,Commandes!$D$2:$D$3000,A5,Commandes!$C$2:$C$3000,">"&(DateExport-365),Commandes!$C$2:$C$3000,"<="&DateExport) | AB5: =COUNTIFS(Transactions!$C$2:$C$3000,A5,Transactions!$N$2:$N$3000,"Ouverte") | AC5: =SUMIFS(Transactions!$L$2:$L$3000,Transactions!$C$2:$C$3000,A5,Transactions!$N$2:$N$3000,"Ouverte") | AD5: =COUNTIFS(Tickets!$C$2:$C$3000,A5,Tickets!$I$2:$I$3000,"<>Fermé") | AE5: =IF(COUNTIFS(Activités!$D$2:$D$3000,A5,Activités!$B$2:$B$3000,"<="&DateExport)=0,"",_xlfn.MAXIFS(Activités!$B$2:$B$3000,Activités!$D$2:$D$3000,A5,Activités!$B$2:$B$3000,"<="&DateExport)) | AF5: =IF(COUNTIFS('Rendez-vous'!$F$2:$F$3000,A5,'Rendez-vous'!$B$2:$B$3000,">="&DateExport)=0,"",_xlfn.MINIFS('Rendez-vous'!$B$2:$B$3000,'Rendez-vous'!$F$2:$F$3000,A5,'Rendez-vous'!$B$2:$B$3000,">="&DateExport)) | AG5: Cartonnages Vauclair | AH5: 60 jours | AI5: Client sur les coffrets rigides premium des éditions de fin d'année. Commandes très saisonnières, concentrées entre mai et septembre. | AJ5: Préparation des éditions limitées 2027 ; intérêt marqué pour des coffrets sans calage plastique.
A6: E005 | B6: Clarins | C6: clarins.com | D6: https://www.clarins.com | E6: Groupe familial de cosmétiques de soin et de maquillage. | F6: Grande consommation | G6: Cosmétiques de soin | H6: Grand compte | I6: 5 000 - 9 999 | J6: 1 - 10 Md€ | K6: 9 rue du Commandant Pilot | L6: 92200 | M6: Neuilly-sur-Seine | N6: Île-de-France | O6: France | P6: Groupe Clarins | Q6: Non | S6: U002 | T6: =IFERROR(INDEX(Commerciaux!$D$2:$D$3000,MATCH(S6,Commerciaux!$A$2:$A$3000,0)),"") | U6: Opportunité | V6: En développement | W6: 45981 | Y6: Site web | Z6: 300000 | AA6: =SUMIFS(Commandes!$K$2:$K$3000,Commandes!$D$2:$D$3000,A6,Commandes!$C$2:$C$3000,">"&(DateExport-365),Commandes!$C$2:$C$3000,"<="&DateExport) | AB6: =COUNTIFS(Transactions!$C$2:$C$3000,A6,Transactions!$N$2:$N$3000,"Ouverte") | AC6: =SUMIFS(Transactions!$L$2:$L$3000,Transactions!$C$2:$C$3000,A6,Transactions!$N$2:$N$3000,"Ouverte") | AD6: =COUNTIFS(Tickets!$C$2:$C$3000,A6,Tickets!$I$2:$I$3000,"<>Fermé") | AE6: =IF(COUNTIFS(Activités!$D$2:$D$3000,A6,Activités!$B$2:$B$3000,"<="&DateExport)=0,"",_xlfn.MAXIFS(Activités!$B$2:$B$3000,Activités!$D$2:$D$3000,A6,Activités!$B$2:$B$3000,"<="&DateExport)) | AF6: =IF(COUNTIFS('Rendez-vous'!$F$2:$F$3000,A6,'Rendez-vous'!$B$2:$B$3000,">="&DateExport)=0,"",_xlfn.MINIFS('Rendez-vous'!$B$2:$B$3000,'Rendez-vous'!$F$2:$F$3000,A6,'Rendez-vous'!$B$2:$B$3000,">="&DateExport)) | AG6: Cartonnages Vauclair | AH6: 60 jours | AI6: Demande entrante via le site web. Clarins cherche un second fournisseur d'étuis pour sécuriser ses approvisionnements. | AJ6: Référencement comme second fournisseur d'étuis ; exigences fortes sur l'éco-conception et la traçabilité des fibres.
A7: E006 | B7: Imerys | C7: imerys.com | D7: https://www.imerys.com | E7: Leader mondial des spécialités minérales pour l'industrie. | F7: Équipements et matériaux | G7: Minéraux industriels | H7: Grand compte | I7: 10 000 et plus | J7: 1 - 10 Md€ | K7: 43 quai de Grenelle | L7: 75015 | M7: Paris | N7: Île-de-France | O7: France | P7: Groupe Imerys | Q7: Oui | R7: NK.PA | S7: U002 | T7: =IFERROR(INDEX(Commerciaux!$D$2:$D$3000,MATCH(S7,Commerciaux!$A$2:$A$3000,0)),"") | U7: Prospect | V7: Nouveau | W7: 46262 | Y7: Prospection téléphonique | Z7: 150000 | AA7: =SUMIFS(Commandes!$K$2:$K$3000,Commandes!$D$2:$D$3000,A7,Commandes!$C$2:$C$3000,">"&(DateExport-365),Commandes!$C$2:$C$3000,"<="&DateExport) | AB7: =COUNTIFS(Transactions!$C$2:$C$3000,A7,Transactions!$N$2:$N$3000,"Ouverte") | AC7: =SUMIFS(Transactions!$L$2:$L$3000,Transactions!$C$2:$C$3000,A7,Transactions!$N$2:$N$3000,"Ouverte") | AD7: =COUNTIFS(Tickets!$C$2:$C$3000,A7,Tickets!$I$2:$I$3000,"<>Fermé") | AE7: =IF(COUNTIFS(Activités!$D$2:$D$3000,A7,Activités!$B$2:$B$3000,"<="&DateExport)=0,"",_xlfn.MAXIFS(Activités!$B$2:$B$3000,Activités!$D$2:$D$3000,A7,Activités!$B$2:$B$3000,"<="&DateExport)) | AF7: =IF(COUNTIFS('Rendez-vous'!$F$2:$F$3000,A7,'Rendez-vous'!$B$2:$B$3000,">="&DateExport)=0,"",_xlfn.MINIFS('Rendez-vous'!$B$2:$B$3000,'Rendez-vous'!$F$2:$F$3000,A7,'Rendez-vous'!$B$2:$B$3000,">="&DateExport)) | AH7: 60 jours | AI7: Prospect identifié par prospection téléphonique : besoin potentiel d'emballages de transport pour des minéraux en poudre. | AJ7: Qualifier le besoin, les volumes et le décideur achats.
A8: E007 | B8: Nexans | C8: nexans.com | D8: https://www.nexans.com | E8: Fabricant de câbles et de solutions de câblage pour l'électrification (réseaux, bâtiment, industrie). | F8: Équipements et matériaux | G8: Câbles et systèmes de câblage | H8: Grand compte | I8: 10 000 et plus | J8: 1 - 10 Md€ | K8: 4 allée de l'Arche | L8: 92400 | M8: Courbevoie | N8: Île-de-France | O8: France | P8: Groupe Nexans | Q8: Oui | R8: NEX.PA | S8: U002 | T8: =IFERROR(INDEX(Commerciaux!$D$2:$D$3000,MATCH(S8,Commerciaux!$A$2:$A$3000,0)),"") | U8: Client | V8: Actif | W8: 45027 | X8: 45201 | Y8: Recommandation | Z8: 180000 | AA8: =SUMIFS(Commandes!$K$2:$K$3000,Commandes!$D$2:$D$3000,A8,Commandes!$C$2:$C$3000,">"&(DateExport-365),Commandes!$C$2:$C$3000,"<="&DateExport) | AB8: =COUNTIFS(Transactions!$C$2:$C$3000,A8,Transactions!$N$2:$N$3000,"Ouverte") | AC8: =SUMIFS(Transactions!$L$2:$L$3000,Transactions!$C$2:$C$3000,A8,Transactions!$N$2:$N$3000,"Ouverte") | AD8: =COUNTIFS(Tickets!$C$2:$C$3000,A8,Tickets!$I$2:$I$3000,"<>Fermé") | AE8: =IF(COUNTIFS(Activités!$D$2:$D$3000,A8,Activités!$B$2:$B$3000,"<="&DateExport)=0,"",_xlfn.MAXIFS(Activités!$B$2:$B$3000,Activités!$D$2:$D$3000,A8,Activités!$B$2:$B$3000,"<="&DateExport)) | AF8: =IF(COUNTIFS('Rendez-vous'!$F$2:$F$3000,A8,'Rendez-vous'!$B$2:$B$3000,">="&DateExport)=0,"",_xlfn.MINIFS('Rendez-vous'!$B$2:$B$3000,'Rendez-vous'!$F$2:$F$3000,A8,'Rendez-vous'!$B$2:$B$3000,">="&DateExport)) | AG8: Emballor Industries | AH8: 60 jours | AI8: Client sur les caisses carton personnalisées et l'étiquetage logistique des accessoires de câblage. | AJ8: Réduction des emballages de transport ; harmonisation des étiquettes logistiques entre trois sites français.
A9: E008 | B9: Moët & Chandon | C9: moet.com | D9: https://www.moet.com | E9: Maison de champagne du groupe LVMH (Moët Hennessy). | F9: Vins et spiritueux | G9: Champagne | H9: Grand compte | I9: 1 000 - 4 999 | J9: Non publié (filiale) | K9: 20 avenue de Champagne | L9: 51200 | M9: Épernay | N9: Grand Est | O9: France | P9: LVMH (Moët Hennessy) | Q9: Oui (via le groupe) | R9: MC.PA | S9: U003 | T9: =IFERROR(INDEX(Commerciaux!$D$2:$D$3000,MATCH(S9,Commerciaux!$A$2:$A$3000,0)),"") | U9: Client | V9: Actif | W9: 43557 | X9: 43724 | Y9: Salon professionnel | Z9: 650000 | AA9: =SUMIFS(Commandes!$K$2:$K$3000,Commandes!$D$2:$D$3000,A9,Commandes!$C$2:$C$3000,">"&(DateExport-365),Commandes!$C$2:$C$3000,"<="&DateExport) | AB9: =COUNTIFS(Transactions!$C$2:$C$3000,A9,Transactions!$N$2:$N$3000,"Ouverte") | AC9: =SUMIFS(Transactions!$L$2:$L$3000,Transactions!$C$2:$C$3000,A9,Transactions!$N$2:$N$3000,"Ouverte") | AD9: =COUNTIFS(Tickets!$C$2:$C$3000,A9,Tickets!$I$2:$I$3000,"<>Fermé") | AE9: =IF(COUNTIFS(Activités!$D$2:$D$3000,A9,Activités!$B$2:$B$3000,"<="&DateExport)=0,"",_xlfn.MAXIFS(Activités!$B$2:$B$3000,Activités!$D$2:$D$3000,A9,Activités!$B$2:$B$3000,"<="&DateExport)) | AF9: =IF(COUNTIFS('Rendez-vous'!$F$2:$F$3000,A9,'Rendez-vous'!$B$2:$B$3000,">="&DateExport)=0,"",_xlfn.MINIFS('Rendez-vous'!$B$2:$B$3000,'Rendez-vous'!$F$2:$F$3000,A9,'Rendez-vous'!$B$2:$B$3000,">="&DateExport)) | AG9: Kartéa Luxe | AH9: 60 jours | AI9: Client stratégique sur les étuis luxe et les coffrets de fin d'année. Cycle de décision long impliquant marketing, achats et industriel. | AJ9: Production des coffrets de fin d'année 2026 ; consultation 2027 sur des étuis allégés ; exigences fortes de recyclabilité.
A10: E009 | B10: Laurent-Perrier | C10: laurent-perrier.com | D10: https://www.laurent-perrier.com | E10: Groupe familial de maisons de champagne (Laurent-Perrier, Salon, Delamotte, de Castellane). | F10: Vins et spiritueux | G10: Champagne | H10: ETI | I10: 250 - 999 | J10: 100 M€ - 1 Md€ | K10: 32 avenue de Champagne | L10: 51150 | M10: Tours-sur-Marne | N10: Grand Est | O10: France | P10: Groupe Laurent-Perrier | Q10: Oui | R10: LPE.PA | S10: U003 | T10: =IFERROR(INDEX(Commerciaux!$D$2:$D$3000,MATCH(S10,Commerciaux!$A$2:$A$3000,0)),"") | U10: Client | V10: Actif | W10: 44270 | X10: 44378 | Y10: Recommandation | Z10: 220000 | AA10: =SUMIFS(Commandes!$K$2:$K$3000,Commandes!$D$2:$D$3000,A10,Commandes!$C$2:$C$3000,">"&(DateExport-365),Commandes!$C$2:$C$3000,"<="&DateExport) | AB10: =COUNTIFS(Transactions!$C$2:$C$3000,A10,Transactions!$N$2:$N$3000,"Ouverte") | AC10: =SUMIFS(Transactions!$L$2:$L$3000,Transactions!$C$2:$C$3000,A10,Transactions!$N$2:$N$3000,"Ouverte") | AD10: =COUNTIFS(Tickets!$C$2:$C$3000,A10,Tickets!$I$2:$I$3000,"<>Fermé") | AE10: =IF(COUNTIFS(Activités!$D$2:$D$3000,A10,Activités!$B$2:$B$3000,"<="&DateExport)=0,"",_xlfn.MAXIFS(Activités!$B$2:$B$3000,Activités!$D$2:$D$3000,A10,Activités!$B$2:$B$3000,"<="&DateExport)) | AF10: =IF(COUNTIFS('Rendez-vous'!$F$2:$F$3000,A10,'Rendez-vous'!$B$2:$B$3000,">="&DateExport)=0,"",_xlfn.MINIFS('Rendez-vous'!$B$2:$B$3000,'Rendez-vous'!$F$2:$F$3000,A10,'Rendez-vous'!$B$2:$B$3000,">="&DateExport)) | AG10: Kartéa Luxe | AH10: 45 jours fin de mois | AI10: Client sur les étuis spiritueux et les caisses export. Interlocuteurs stables, relation de confiance. | AJ10: Renouvellement des étuis de la gamme rosé ; optimisation des caisses export.
A11: E010 | B11: Vranken-Pommery | C11: vrankenpommery.com | D11: https://www.vrankenpommery.com | E11: Groupe de vins et champagnes (Vranken, Pommery, Heidsieck & Co Monopole). | F11: Vins et spiritueux | G11: Champagne | H11: ETI | I11: 250 - 999 | J11: 100 M€ - 1 Md€ | K11: 5 place du Général Gouraud | L11: 51100 | M11: Reims | N11: Grand Est | O11: France | P11: Vranken-Pommery Monopole | Q11: Oui | R11: VRAP.PA | S11: U003 | T11: =IFERROR(INDEX(Commerciaux!$D$2:$D$3000,MATCH(S11,Commerciaux!$A$2:$A$3000,0)),"") | U11: Opportunité | V11: En développement | W11: 45908 | Y11: Salon professionnel | Z11: 240000 | AA11: =SUMIFS(Commandes!$K$2:$K$3000,Commandes!$D$2:$D$3000,A11,Commandes!$C$2:$C$3000,">"&(DateExport-365),Commandes!$C$2:$C$3000,"<="&DateExport) | AB11: =COUNTIFS(Transactions!$C$2:$C$3000,A11,Transactions!$N$2:$N$3000,"Ouverte") | AC11: =SUMIFS(Transactions!$L$2:$L$3000,Transactions!$C$2:$C$3000,A11,Transactions!$N$2:$N$3000,"Ouverte") | AD11: =COUNTIFS(Tickets!$C$2:$C$3000,A11,Tickets!$I$2:$I$3000,"<>Fermé") | AE11: =IF(COUNTIFS(Activités!$D$2:$D$3000,A11,Activités!$B$2:$B$3000,"<="&DateExport)=0,"",_xlfn.MAXIFS(Activités!$B$2:$B$3000,Activités!$D$2:$D$3000,A11,Activités!$B$2:$B$3000,"<="&DateExport)) | AF11: =IF(COUNTIFS('Rendez-vous'!$F$2:$F$3000,A11,'Rendez-vous'!$B$2:$B$3000,">="&DateExport)=0,"",_xlfn.MINIFS('Rendez-vous'!$B$2:$B$3000,'Rendez-vous'!$F$2:$F$3000,A11,'Rendez-vous'!$B$2:$B$3000,">="&DateExport)) | AG11: Kartéa Luxe | AH11: 60 jours | AI11: Opportunité ouverte après un salon professionnel : intérêt pour des coffrets premium et des étiquettes d'inviolabilité. | AJ11: Remplacement du fournisseur actuel de coffrets, jugé peu fiable sur les délais ; décision attendue en décembre.
A12: E011 | B12: Kronenbourg | C12: kronenbourg.com | D12: https://www.kronenbourg.com | E12: Premier brasseur français, filiale du groupe Carlsberg (Kronenbourg 1664, Grimbergen) ; principale brasserie à Obernai. | F12: Grande consommation | G12: Bière | H12: Grand compte | I12: 1 000 - 4 999 | J12: Non publié (filiale) | K12: 68 route d'Oberhausbergen | L12: 67000 | M12: Strasbourg | N12: Grand Est | O12: France | P12: Groupe Carlsberg | Q12: Oui (via le groupe) | R12: CARL-B.CO | S12: U003 | T12: =IFERROR(INDEX(Commerciaux!$D$2:$D$3000,MATCH(S12,Commerciaux!$A$2:$A$3000,0)),"") | U12: Client | V12: À risque | W12: 44004 | X12: 44207 | Y12: Prospection terrain | Z12: 320000 | AA12: =SUMIFS(Commandes!$K$2:$K$3000,Commandes!$D$2:$D$3000,A12,Commandes!$C$2:$C$3000,">"&(DateExport-365),Commandes!$C$2:$C$3000,"<="&DateExport) | AB12: =COUNTIFS(Transactions!$C$2:$C$3000,A12,Transactions!$N$2:$N$3000,"Ouverte") | AC12: =SUMIFS(Transactions!$L$2:$L$3000,Transactions!$C$2:$C$3000,A12,Transactions!$N$2:$N$3000,"Ouverte") | AD12: =COUNTIFS(Tickets!$C$2:$C$3000,A12,Tickets!$I$2:$I$3000,"<>Fermé") | AE12: =IF(COUNTIFS(Activités!$D$2:$D$3000,A12,Activités!$B$2:$B$3000,"<="&DateExport)=0,"",_xlfn.MAXIFS(Activités!$B$2:$B$3000,Activités!$D$2:$D$3000,A12,Activités!$B$2:$B$3000,"<="&DateExport)) | AF12: =IF(COUNTIFS('Rendez-vous'!$F$2:$F$3000,A12,'Rendez-vous'!$B$2:$B$3000,">="&DateExport)=0,"",_xlfn.MINIFS('Rendez-vous'!$B$2:$B$3000,'Rendez-vous'!$F$2:$F$3000,A12,'Rendez-vous'!$B$2:$B$3000,">="&DateExport)) | AG12: Emballor Industries | AH12: 60 jours | AI12: Client sur les caisses carton et les étiquettes promotionnelles. Les décisions d'achat se prennent au siège de Strasbourg ; la production est concentrée à la brasserie d'Obernai. Volume en baisse depuis début 2026 : une partie des caisses a été attribuée à un concurrent. | AJ12: Reconquérir le volume perdu sur les caisses ; valoriser le contrat de maintenance des étiqueteuses installées.
A13: E012 | B13: bioMérieux | C13: biomerieux.com | D13: https://www.biomerieux.com | E13: Acteur mondial du diagnostic in vitro (microbiologie, immunoessais, biologie moléculaire). | F13: Pharmaceutique et santé | G13: Diagnostic in vitro | H13: Grand compte | I13: 10 000 et plus | J13: 1 - 10 Md€ | K13: 376 chemin de l'Orme | L13: 69280 | M13: Marcy-l'Étoile | N13: Auvergne-Rhône-Alpes | O13: France | P13: bioMérieux | Q13: Oui | R13: BIM.PA | S13: U004 | T13: =IFERROR(INDEX(Commerciaux!$D$2:$D$3000,MATCH(S13,Commerciaux!$A$2:$A$3000,0)),"") | U13: Client | V13: Actif | W13: 44088 | X13: 44228 | Y13: Recommandation | Z13: 410000 | AA13: =SUMIFS(Commandes!$K$2:$K$3000,Commandes!$D$2:$D$3000,A13,Commandes!$C$2:$C$3000,">"&(DateExport-365),Commandes!$C$2:$C$3000,"<="&DateExport) | AB13: =COUNTIFS(Transactions!$C$2:$C$3000,A13,Transactions!$N$2:$N$3000,"Ouverte") | AC13: =SUMIFS(Transactions!$L$2:$L$3000,Transactions!$C$2:$C$3000,A13,Transactions!$N$2:$N$3000,"Ouverte") | AD13: =COUNTIFS(Tickets!$C$2:$C$3000,A13,Tickets!$I$2:$I$3000,"<>Fermé") | AE13: =IF(COUNTIFS(Activités!$D$2:$D$3000,A13,Activités!$B$2:$B$3000,"<="&DateExport)=0,"",_xlfn.MAXIFS(Activités!$B$2:$B$3000,Activités!$D$2:$D$3000,A13,Activités!$B$2:$B$3000,"<="&DateExport)) | AF13: =IF(COUNTIFS('Rendez-vous'!$F$2:$F$3000,A13,'Rendez-vous'!$B$2:$B$3000,">="&DateExport)=0,"",_xlfn.MINIFS('Rendez-vous'!$B$2:$B$3000,'Rendez-vous'!$F$2:$F$3000,A13,'Rendez-vous'!$B$2:$B$3000,">="&DateExport)) | AG13: Kartéa Pharma Pack | AH13: 60 jours | AI13: Client sur les étuis et étiquettes des kits de diagnostic. Forte exigence de traçabilité. | AJ13: Sérialisation des kits pour les marchés export ; évolution réglementaire de l'étiquetage.
A14: E013 | B14: Boiron | C14: boiron.com | D14: https://www.boiron.com | E14: Laboratoire pharmaceutique spécialiste de l'homéopathie et des médicaments sans ordonnance. | F14: Pharmaceutique et santé | G14: Homéopathie | H14: ETI | I14: 1 000 - 4 999 | J14: 100 M€ - 1 Md€ | K14: 2 avenue de l'Ouest Lyonnais | L14: 69510 | M14: Messimy | N14: Auvergne-Rhône-Alpes | O14: France | P14: Boiron | Q14: Oui | R14: BOI.PA | S14: U004 | T14: =IFERROR(INDEX(Commerciaux!$D$2:$D$3000,MATCH(S14,Commerciaux!$A$2:$A$3000,0)),"") | U14: Client | V14: Actif | W14: 43514 | X14: 43619 | Y14: Prospection terrain | Z14: 190000 | AA14: =SUMIFS(Commandes!$K$2:$K$3000,Commandes!$D$2:$D$3000,A14,Commandes!$C$2:$C$3000,">"&(DateExport-365),Commandes!$C$2:$C$3000,"<="&DateExport) | AB14: =COUNTIFS(Transactions!$C$2:$C$3000,A14,Transactions!$N$2:$N$3000,"Ouverte") | AC14: =SUMIFS(Transactions!$L$2:$L$3000,Transactions!$C$2:$C$3000,A14,Transactions!$N$2:$N$3000,"Ouverte") | AD14: =COUNTIFS(Tickets!$C$2:$C$3000,A14,Tickets!$I$2:$I$3000,"<>Fermé") | AE14: =IF(COUNTIFS(Activités!$D$2:$D$3000,A14,Activités!$B$2:$B$3000,"<="&DateExport)=0,"",_xlfn.MAXIFS(Activités!$B$2:$B$3000,Activités!$D$2:$D$3000,A14,Activités!$B$2:$B$3000,"<="&DateExport)) | AF14: =IF(COUNTIFS('Rendez-vous'!$F$2:$F$3000,A14,'Rendez-vous'!$B$2:$B$3000,">="&DateExport)=0,"",_xlfn.MINIFS('Rendez-vous'!$B$2:$B$3000,'Rendez-vous'!$F$2:$F$3000,A14,'Rendez-vous'!$B$2:$B$3000,">="&DateExport)) | AG14: Kartéa Pharma Pack | AH14: 60 jours | AI14: Client de longue date sur les étuis et notices, avec des volumes réguliers. | AJ14: Optimisation des coûts d'emballage ; passage à des étuis en carton recyclé.
A15: E014 | B15: SEB | C15: groupeseb.com | D15: https://www.groupeseb.com | E15: Leader mondial du petit équipement domestique (Tefal, Rowenta, Moulinex, Krups, Seb). | F15: Équipements et matériaux | G15: Petit électroménager | H15: Grand compte | I15: 10 000 et plus | J15: 1 - 10 Md€ | K15: 112 chemin du Moulin Carron | L15: 69130 | M15: Écully | N15: Auvergne-Rhône-Alpes | O15: France | P15: Groupe SEB | Q15: Oui | R15: SK.PA | S15: U004 | T15: =IFERROR(INDEX(Commerciaux!$D$2:$D$3000,MATCH(S15,Commerciaux!$A$2:$A$3000,0)),"") | U15: Client | V15: Actif | W15: 44221 | X15: 44326 | Y15: Salon professionnel | Z15: 520000 | AA15: =SUMIFS(Commandes!$K$2:$K$3000,Commandes!$D$2:$D$3000,A15,Commandes!$C$2:$C$3000,">"&(DateExport-365),Commandes!$C$2:$C$3000,"<="&DateExport) | AB15: =COUNTIFS(Transactions!$C$2:$C$3000,A15,Transactions!$N$2:$N$3000,"Ouverte") | AC15: =SUMIFS(Transactions!$L$2:$L$3000,Transactions!$C$2:$C$3000,A15,Transactions!$N$2:$N$3000,"Ouverte") | AD15: =COUNTIFS(Tickets!$C$2:$C$3000,A15,Tickets!$I$2:$I$3000,"<>Fermé") | AE15: =IF(COUNTIFS(Activités!$D$2:$D$3000,A15,Activités!$B$2:$B$3000,"<="&DateExport)=0,"",_xlfn.MAXIFS(Activités!$B$2:$B$3000,Activités!$D$2:$D$3000,A15,Activités!$B$2:$B$3000,"<="&DateExport)) | AF15: =IF(COUNTIFS('Rendez-vous'!$F$2:$F$3000,A15,'Rendez-vous'!$B$2:$B$3000,">="&DateExport)=0,"",_xlfn.MINIFS('Rendez-vous'!$B$2:$B$3000,'Rendez-vous'!$F$2:$F$3000,A15,'Rendez-vous'!$B$2:$B$3000,">="&DateExport)) | AG15: Emballor Industries | AH15: 60 jours | AI15: Client sur les caisses carton personnalisées et les emballages éco-conçus de plusieurs gammes. | AJ15: Suppression du polystyrène dans les calages ; harmonisation des emballages entre marques.
A16: E015 | B16: Vicat | C16: vicat.com | D16: https://www.vicat.com | E16: Groupe cimentier familial (ciment, béton prêt à l'emploi, granulats). | F16: Équipements et matériaux | G16: Ciment et matériaux de construction | H16: Grand compte | I16: 10 000 et plus | J16: 1 - 10 Md€ | K16: 4 rue Aristide Bergès | L16: 38080 | M16: L'Isle-d'Abeau | N16: Auvergne-Rhône-Alpes | O16: France | P16: Groupe Vicat | Q16: Oui | R16: VCT.PA | S16: U004 | T16: =IFERROR(INDEX(Commerciaux!$D$2:$D$3000,MATCH(S16,Commerciaux!$A$2:$A$3000,0)),"") | U16: Prospect | V16: Nouveau | W16: 46272 | Y16: Événement / webinaire | Z16: 120000 | AA16: =SUMIFS(Commandes!$K$2:$K$3000,Commandes!$D$2:$D$3000,A16,Commandes!$C$2:$C$3000,">"&(DateExport-365),Commandes!$C$2:$C$3000,"<="&DateExport) | AB16: =COUNTIFS(Transactions!$C$2:$C$3000,A16,Transactions!$N$2:$N$3000,"Ouverte") | AC16: =SUMIFS(Transactions!$L$2:$L$3000,Transactions!$C$2:$C$3000,A16,Transactions!$N$2:$N$3000,"Ouverte") | AD16: =COUNTIFS(Tickets!$C$2:$C$3000,A16,Tickets!$I$2:$I$3000,"<>Fermé") | AE16: =IF(COUNTIFS(Activités!$D$2:$D$3000,A16,Activités!$B$2:$B$3000,"<="&DateExport)=0,"",_xlfn.MAXIFS(Activités!$B$2:$B$3000,Activités!$D$2:$D$3000,A16,Activités!$B$2:$B$3000,"<="&DateExport)) | AF16: =IF(COUNTIFS('Rendez-vous'!$F$2:$F$3000,A16,'Rendez-vous'!$B$2:$B$3000,">="&DateExport)=0,"",_xlfn.MINIFS('Rendez-vous'!$B$2:$B$3000,'Rendez-vous'!$F$2:$F$3000,A16,'Rendez-vous'!$B$2:$B$3000,">="&DateExport)) | AH16: 60 jours | AI16: Prospect venu d'un webinaire sur l'étiquetage logistique : besoin potentiel d'étiquettes résistantes pour les sacs. | AJ16: Qualifier le besoin et identifier le décideur.
A17: E016 | B17: Virbac | C17: virbac.com | D17: https://www.virbac.com | E17: Laboratoire pharmaceutique dédié exclusivement à la santé animale. | F17: Pharmaceutique et santé | G17: Santé animale | H17: Grand compte | I17: 5 000 - 9 999 | J17: 1 - 10 Md€ | K17: 1ère avenue 2065 m LID | L17: 06510 | M17: Carros | N17: Provence-Alpes-Côte d'Azur | O17: France | P17: Virbac | Q17: Oui | R17: VIRP.PA | S17: U004 | T17: =IFERROR(INDEX(Commerciaux!$D$2:$D$3000,MATCH(S17,Commerciaux!$A$2:$A$3000,0)),"") | U17: Opportunité | V17: En développement | W17: 45994 | Y17: Recommandation | Z17: 280000 | AA17: =SUMIFS(Commandes!$K$2:$K$3000,Commandes!$D$2:$D$3000,A17,Commandes!$C$2:$C$3000,">"&(DateExport-365),Commandes!$C$2:$C$3000,"<="&DateExport) | AB17: =COUNTIFS(Transactions!$C$2:$C$3000,A17,Transactions!$N$2:$N$3000,"Ouverte") | AC17: =SUMIFS(Transactions!$L$2:$L$3000,Transactions!$C$2:$C$3000,A17,Transactions!$N$2:$N$3000,"Ouverte") | AD17: =COUNTIFS(Tickets!$C$2:$C$3000,A17,Tickets!$I$2:$I$3000,"<>Fermé") | AE17: =IF(COUNTIFS(Activités!$D$2:$D$3000,A17,Activités!$B$2:$B$3000,"<="&DateExport)=0,"",_xlfn.MAXIFS(Activités!$B$2:$B$3000,Activités!$D$2:$D$3000,A17,Activités!$B$2:$B$3000,"<="&DateExport)) | AF17: =IF(COUNTIFS('Rendez-vous'!$F$2:$F$3000,A17,'Rendez-vous'!$B$2:$B$3000,">="&DateExport)=0,"",_xlfn.MINIFS('Rendez-vous'!$B$2:$B$3000,'Rendez-vous'!$F$2:$F$3000,A17,'Rendez-vous'!$B$2:$B$3000,">="&DateExport)) | AG17: Kartéa Pharma Pack | AH17: 60 jours | AI17: Opportunité sur les étuis et la sérialisation d'une nouvelle ligne de produits vétérinaires. | AJ17: Choix d'un fournisseur de sérialisation pour une ligne prévue mi-2027 ; calendrier serré.
A18: E017 | B18: Rémy Cointreau | C18: remy-cointreau.com | D18: https://www.remy-cointreau.com | E18: Groupe de spiritueux premium (Rémy Martin, Louis XIII, Cointreau, The Botanist). | F18: Vins et spiritueux | G18: Cognac et liqueurs | H18: Grand compte | I18: 1 000 - 4 999 | J18: 100 M€ - 1 Md€ | K18: 20 rue de la Société Vinicole | L18: 16100 | M18: Cognac | N18: Nouvelle-Aquitaine | O18: France | P18: Rémy Cointreau | Q18: Oui | R18: RCO.PA | S18: U005 | T18: =IFERROR(INDEX(Commerciaux!$D$2:$D$3000,MATCH(S18,Commerciaux!$A$2:$A$3000,0)),"") | U18: Client | V18: Actif | W18: 44109 | X18: 44270 | Y18: Salon professionnel | Z18: 480000 | AA18: =SUMIFS(Commandes!$K$2:$K$3000,Commandes!$D$2:$D$3000,A18,Commandes!$C$2:$C$3000,">"&(DateExport-365),Commandes!$C$2:$C$3000,"<="&DateExport) | AB18: =COUNTIFS(Transactions!$C$2:$C$3000,A18,Transactions!$N$2:$N$3000,"Ouverte") | AC18: =SUMIFS(Transactions!$L$2:$L$3000,Transactions!$C$2:$C$3000,A18,Transactions!$N$2:$N$3000,"Ouverte") | AD18: =COUNTIFS(Tickets!$C$2:$C$3000,A18,Tickets!$I$2:$I$3000,"<>Fermé") | AE18: =IF(COUNTIFS(Activités!$D$2:$D$3000,A18,Activités!$B$2:$B$3000,"<="&DateExport)=0,"",_xlfn.MAXIFS(Activités!$B$2:$B$3000,Activités!$D$2:$D$3000,A18,Activités!$B$2:$B$3000,"<="&DateExport)) | AF18: =IF(COUNTIFS('Rendez-vous'!$F$2:$F$3000,A18,'Rendez-vous'!$B$2:$B$3000,">="&DateExport)=0,"",_xlfn.MINIFS('Rendez-vous'!$B$2:$B$3000,'Rendez-vous'!$F$2:$F$3000,A18,'Rendez-vous'!$B$2:$B$3000,">="&DateExport)) | AG18: Kartéa Luxe | AH18: 60 jours | AI18: Client sur les étuis spiritueux et les coffrets premium. Forte saisonnalité liée aux fêtes de fin d'année. | AJ18: Sécuriser les capacités pour la saison 2027 ; projet de coffret réutilisable pour la gamme premium.
A19: E018 | B19: Maison Ferrand | C19: maisonferrand.com | D19: https://www.maisonferrand.com | E19: Maison de spiritueux (Cognac Ferrand, rhums Planteray, gin Citadelle). | F19: Vins et spiritueux | G19: Cognac et rhums | H19: PME | I19: 50 - 249 | J19: Non publié | K19: Château de Bonbonnet | L19: 16130 | M19: Ars | N19: Nouvelle-Aquitaine | O19: France | P19: Maison Ferrand | Q19: Non | S19: U005 | T19: =IFERROR(INDEX(Commerciaux!$D$2:$D$3000,MATCH(S19,Commerciaux!$A$2:$A$3000,0)),"") | U19: Client | V19: Actif | W19: 44655 | X19: 44816 | Y19: Recommandation | Z19: 90000 | AA19: =SUMIFS(Commandes!$K$2:$K$3000,Commandes!$D$2:$D$3000,A19,Commandes!$C$2:$C$3000,">"&(DateExport-365),Commandes!$C$2:$C$3000,"<="&DateExport) | AB19: =COUNTIFS(Transactions!$C$2:$C$3000,A19,Transactions!$N$2:$N$3000,"Ouverte") | AC19: =SUMIFS(Transactions!$L$2:$L$3000,Transactions!$C$2:$C$3000,A19,Transactions!$N$2:$N$3000,"Ouverte") | AD19: =COUNTIFS(Tickets!$C$2:$C$3000,A19,Tickets!$I$2:$I$3000,"<>Fermé") | AE19: =IF(COUNTIFS(Activités!$D$2:$D$3000,A19,Activités!$B$2:$B$3000,"<="&DateExport)=0,"",_xlfn.MAXIFS(Activités!$B$2:$B$3000,Activités!$D$2:$D$3000,A19,Activités!$B$2:$B$3000,"<="&DateExport)) | AF19: =IF(COUNTIFS('Rendez-vous'!$F$2:$F$3000,A19,'Rendez-vous'!$B$2:$B$3000,">="&DateExport)=0,"",_xlfn.MINIFS('Rendez-vous'!$B$2:$B$3000,'Rendez-vous'!$F$2:$F$3000,A19,'Rendez-vous'!$B$2:$B$3000,">="&DateExport)) | AH19: 30 jours | AI19: Petit client très exigeant sur le design, commandes en petites séries. | AJ19: Étuis d'une édition limitée de fin d'année ; souplesse attendue sur les minimums de commande.
A20: E019 | B20: Pierre Fabre | C20: pierre-fabre.com | D20: https://www.pierre-fabre.com | E20: Groupe pharmaceutique et dermo-cosmétique (Avène, Ducray, Klorane, René Furterer). | F20: Pharmaceutique et santé | G20: Dermo-cosmétique et médicament | H20: Grand compte | I20: 5 000 - 9 999 | J20: 1 - 10 Md€ | K20: Parc industriel de la Chartreuse, 40 rue Albert Calmette | L20: 81100 | M20: Castres | N20: Occitanie | O20: France | P20: Groupe Pierre Fabre | Q20: Non | S20: U005 | T20: =IFERROR(INDEX(Commerciaux!$D$2:$D$3000,MATCH(S20,Commerciaux!$A$2:$A$3000,0)),"") | U20: Client | V20: À surveiller | W20: 44361 | X20: 44502 | Y20: Prospection terrain | Z20: 360000 | AA20: =SUMIFS(Commandes!$K$2:$K$3000,Commandes!$D$2:$D$3000,A20,Commandes!$C$2:$C$3000,">"&(DateExport-365),Commandes!$C$2:$C$3000,"<="&DateExport) | AB20: =COUNTIFS(Transactions!$C$2:$C$3000,A20,Transactions!$N$2:$N$3000,"Ouverte") | AC20: =SUMIFS(Transactions!$L$2:$L$3000,Transactions!$C$2:$C$3000,A20,Transactions!$N$2:$N$3000,"Ouverte") | AD20: =COUNTIFS(Tickets!$C$2:$C$3000,A20,Tickets!$I$2:$I$3000,"<>Fermé") | AE20: =IF(COUNTIFS(Activités!$D$2:$D$3000,A20,Activités!$B$2:$B$3000,"<="&DateExport)=0,"",_xlfn.MAXIFS(Activités!$B$2:$B$3000,Activités!$D$2:$D$3000,A20,Activités!$B$2:$B$3000,"<="&DateExport)) | AF20: =IF(COUNTIFS('Rendez-vous'!$F$2:$F$3000,A20,'Rendez-vous'!$B$2:$B$3000,">="&DateExport)=0,"",_xlfn.MINIFS('Rendez-vous'!$B$2:$B$3000,'Rendez-vous'!$F$2:$F$3000,A20,'Rendez-vous'!$B$2:$B$3000,">="&DateExport)) | AG20: Kartéa Pharma Pack | AH20: 60 jours | AI20: Client sur les étuis dermo-cosmétiques et les notices. Un ticket qualité est ouvert sur un défaut de pliage. | AJ20: Résoudre le défaut de pliage ; renouvellement du contrat étuis en janvier 2027.
A21: E020 | B21: Andros | C21: andros.fr | D21: https://www.andros.fr | E21: Groupe familial agroalimentaire (confitures, compotes, desserts, jus de fruits ; marques Andros et Bonne Maman). | F21: Grande consommation | G21: Fruits transformés et desserts | H21: Grand compte | I21: 5 000 - 9 999 | J21: 1 - 10 Md€ | K21: Zone industrielle | L21: 46130 | M21: Biars-sur-Cère | N21: Occitanie | O21: France | P21: Groupe Andros | Q21: Non | S21: U005 | T21: =IFERROR(INDEX(Commerciaux!$D$2:$D$3000,MATCH(S21,Commerciaux!$A$2:$A$3000,0)),"") | U21: Opportunité | V21: En développement | W21: 46083 | Y21: Salon professionnel | Z21: 260000 | AA21: =SUMIFS(Commandes!$K$2:$K$3000,Commandes!$D$2:$D$3000,A21,Commandes!$C$2:$C$3000,">"&(DateExport-365),Commandes!$C$2:$C$3000,"<="&DateExport) | AB21: =COUNTIFS(Transactions!$C$2:$C$3000,A21,Transactions!$N$2:$N$3000,"Ouverte") | AC21: =SUMIFS(Transactions!$L$2:$L$3000,Transactions!$C$2:$C$3000,A21,Transactions!$N$2:$N$3000,"Ouverte") | AD21: =COUNTIFS(Tickets!$C$2:$C$3000,A21,Tickets!$I$2:$I$3000,"<>Fermé") | AE21: =IF(COUNTIFS(Activités!$D$2:$D$3000,A21,Activités!$B$2:$B$3000,"<="&DateExport)=0,"",_xlfn.MAXIFS(Activités!$B$2:$B$3000,Activités!$D$2:$D$3000,A21,Activités!$B$2:$B$3000,"<="&DateExport)) | AF21: =IF(COUNTIFS('Rendez-vous'!$F$2:$F$3000,A21,'Rendez-vous'!$B$2:$B$3000,">="&DateExport)=0,"",_xlfn.MINIFS('Rendez-vous'!$B$2:$B$3000,'Rendez-vous'!$F$2:$F$3000,A21,'Rendez-vous'!$B$2:$B$3000,">="&DateExport)) | AG21: Emballor Industries | AH21: 60 jours | AI21: Opportunité sur les caisses carton et l'étiquetage d'une nouvelle gamme lancée en 2027. | AJ21: Trouver un fournisseur capable de suivre une montée en volume rapide, avec de la souplesse la première année.
A22: E021 | B22: Volterra | C22: volterra.example | D22: https://www.volterra.example | E22: Spécialiste mondial des infrastructures électriques et numériques du bâtiment. | F22: Équipements et matériaux | G22: Matériel électrique | H22: Grand compte | I22: 10 000 et plus | J22: 1 - 10 Md€ | K22: 12 rue des Isolants | L22: 86000 | M22: Poitiers | N22: Nouvelle-Aquitaine | O22: France | P22: Groupe Volterra | Q22: Oui | S22: U005 | T22: =IFERROR(INDEX(Commerciaux!$D$2:$D$3000,MATCH(S22,Commerciaux!$A$2:$A$3000,0)),"") | U22: Client | V22: Actif | W22: 43850 | X22: 43990 | Y22: Recommandation | Z22: 450000 | AA22: =SUMIFS(Commandes!$K$2:$K$3000,Commandes!$D$2:$D$3000,A22,Commandes!$C$2:$C$3000,">"&(DateExport-365),Commandes!$C$2:$C$3000,"<="&DateExport) | AB22: =COUNTIFS(Transactions!$C$2:$C$3000,A22,Transactions!$N$2:$N$3000,"Ouverte") | AC22: =SUMIFS(Transactions!$L$2:$L$3000,Transactions!$C$2:$C$3000,A22,Transactions!$N$2:$N$3000,"Ouverte") | AD22: =COUNTIFS(Tickets!$C$2:$C$3000,A22,Tickets!$I$2:$I$3000,"<>Fermé") | AE22: =IF(COUNTIFS(Activités!$D$2:$D$3000,A22,Activités!$B$2:$B$3000,"<="&DateExport)=0,"",_xlfn.MAXIFS(Activités!$B$2:$B$3000,Activités!$D$2:$D$3000,A22,Activités!$B$2:$B$3000,"<="&DateExport)) | AF22: =IF(COUNTIFS('Rendez-vous'!$F$2:$F$3000,A22,'Rendez-vous'!$B$2:$B$3000,">="&DateExport)=0,"",_xlfn.MINIFS('Rendez-vous'!$B$2:$B$3000,'Rendez-vous'!$F$2:$F$3000,A22,'Rendez-vous'!$B$2:$B$3000,">="&DateExport)) | AG22: Emballor Industries | AH22: 60 jours | AI22: Client sur les caisses carton et les emballages éco-conçus de l'appareillage électrique. Une étiqueteuse ETQ-400 est installée sur le site de Poitiers. | AJ22: Réduction du plastique dans les emballages de vente ; déploiement sur deux usines supplémentaires.
A23: E022 | B23: Sanofi | C23: sanofi.com | D23: https://www.sanofi.com | E23: Groupe biopharmaceutique mondial (médicaments de spécialité, vaccins, médicaments généraux). | F23: Pharmaceutique et santé | G23: Médicaments de prescription et vaccins | H23: Grand compte | I23: 10 000 et plus | J23: Plus de 10 Md€ | K23: 46 avenue de la Grande Armée | L23: 75017 | M23: Paris | N23: Île-de-France | O23: France | P23: Groupe Sanofi | Q23: Oui | R23: SAN.PA | S23: U006 | T23: =IFERROR(INDEX(Commerciaux!$D$2:$D$3000,MATCH(S23,Commerciaux!$A$2:$A$3000,0)),"") | U23: Client | V23: Actif | W23: 43437 | X23: 43605 | Y23: Prospection terrain | Z23: 1200000 | AA23: =SUMIFS(Commandes!$K$2:$K$3000,Commandes!$D$2:$D$3000,A23,Commandes!$C$2:$C$3000,">"&(DateExport-365),Commandes!$C$2:$C$3000,"<="&DateExport) | AB23: =COUNTIFS(Transactions!$C$2:$C$3000,A23,Transactions!$N$2:$N$3000,"Ouverte") | AC23: =SUMIFS(Transactions!$L$2:$L$3000,Transactions!$C$2:$C$3000,A23,Transactions!$N$2:$N$3000,"Ouverte") | AD23: =COUNTIFS(Tickets!$C$2:$C$3000,A23,Tickets!$I$2:$I$3000,"<>Fermé") | AE23: =IF(COUNTIFS(Activités!$D$2:$D$3000,A23,Activités!$B$2:$B$3000,"<="&DateExport)=0,"",_xlfn.MAXIFS(Activités!$B$2:$B$3000,Activités!$D$2:$D$3000,A23,Activités!$B$2:$B$3000,"<="&DateExport)) | AF23: =IF(COUNTIFS('Rendez-vous'!$F$2:$F$3000,A23,'Rendez-vous'!$B$2:$B$3000,">="&DateExport)=0,"",_xlfn.MINIFS('Rendez-vous'!$B$2:$B$3000,'Rendez-vous'!$F$2:$F$3000,A23,'Rendez-vous'!$B$2:$B$3000,">="&DateExport)) | AG23: Kartéa Pharma Pack | AH23: 60 jours | AI23: Grand compte stratégique. Accord-cadre national sur les étuis et notices, décliné par site de production. Plusieurs interlocuteurs achats et industriels. | AJ23: Renouvellement de l'accord-cadre en 2027 ; déploiement de la sérialisation sur un site supplémentaire.
A24: E023 | B24: Ipsen | C24: ipsen.com | D24: https://www.ipsen.com | E24: Groupe biopharmaceutique spécialisé en oncologie, maladies rares et neurosciences. | F24: Pharmaceutique et santé | G24: Médicaments de spécialité | H24: Grand compte | I24: 5 000 - 9 999 | J24: 1 - 10 Md€ | K24: 65 quai Georges Gorse | L24: 92100 | M24: Boulogne-Billancourt | N24: Île-de-France | O24: France | P24: Ipsen | Q24: Oui | R24: IPN.PA | S24: U006 | T24: =IFERROR(INDEX(Commerciaux!$D$2:$D$3000,MATCH(S24,Commerciaux!$A$2:$A$3000,0)),"") | U24: Client | V24: Actif | W24: 43899 | X24: 44116 | Y24: Recommandation | Z24: 380000 | AA24: =SUMIFS(Commandes!$K$2:$K$3000,Commandes!$D$2:$D$3000,A24,Commandes!$C$2:$C$3000,">"&(DateExport-365),Commandes!$C$2:$C$3000,"<="&DateExport) | AB24: =COUNTIFS(Transactions!$C$2:$C$3000,A24,Transactions!$N$2:$N$3000,"Ouverte") | AC24: =SUMIFS(Transactions!$L$2:$L$3000,Transactions!$C$2:$C$3000,A24,Transactions!$N$2:$N$3000,"Ouverte") | AD24: =COUNTIFS(Tickets!$C$2:$C$3000,A24,Tickets!$I$2:$I$3000,"<>Fermé") | AE24: =IF(COUNTIFS(Activités!$D$2:$D$3000,A24,Activités!$B$2:$B$3000,"<="&DateExport)=0,"",_xlfn.MAXIFS(Activités!$B$2:$B$3000,Activités!$D$2:$D$3000,A24,Activités!$B$2:$B$3000,"<="&DateExport)) | AF24: =IF(COUNTIFS('Rendez-vous'!$F$2:$F$3000,A24,'Rendez-vous'!$B$2:$B$3000,">="&DateExport)=0,"",_xlfn.MINIFS('Rendez-vous'!$B$2:$B$3000,'Rendez-vous'!$F$2:$F$3000,A24,'Rendez-vous'!$B$2:$B$3000,">="&DateExport)) | AG24: Kartéa Pharma Pack | AH24: 60 jours | AI24: Client sur les étuis et étiquettes de médicaments de spécialité. | AJ24: Généralisation des étiquettes d'inviolabilité sur toute la gamme ; clause de révision annuelle des prix demandée.
A25: E024 | B25: Servier | C25: servier.com | D25: https://www.servier.com | E25: Groupe pharmaceutique indépendant gouverné par une fondation, spécialisé notamment en oncologie et cardiologie. | F25: Pharmaceutique et santé | G25: Médicaments de prescription | H25: Grand compte | I25: 10 000 et plus | J25: 1 - 10 Md€ | K25: 50 rue Carnot | L25: 92150 | M25: Suresnes | N25: Île-de-France | O25: France | P25: Groupe Servier | Q25: Non | S25: U006 | T25: =IFERROR(INDEX(Commerciaux!$D$2:$D$3000,MATCH(S25,Commerciaux!$A$2:$A$3000,0)),"") | U25: Opportunité | V25: En développement | W25: 45944 | Y25: Événement / webinaire | Z25: 500000 | AA25: =SUMIFS(Commandes!$K$2:$K$3000,Commandes!$D$2:$D$3000,A25,Commandes!$C$2:$C$3000,">"&(DateExport-365),Commandes!$C$2:$C$3000,"<="&DateExport) | AB25: =COUNTIFS(Transactions!$C$2:$C$3000,A25,Transactions!$N$2:$N$3000,"Ouverte") | AC25: =SUMIFS(Transactions!$L$2:$L$3000,Transactions!$C$2:$C$3000,A25,Transactions!$N$2:$N$3000,"Ouverte") | AD25: =COUNTIFS(Tickets!$C$2:$C$3000,A25,Tickets!$I$2:$I$3000,"<>Fermé") | AE25: =IF(COUNTIFS(Activités!$D$2:$D$3000,A25,Activités!$B$2:$B$3000,"<="&DateExport)=0,"",_xlfn.MAXIFS(Activités!$B$2:$B$3000,Activités!$D$2:$D$3000,A25,Activités!$B$2:$B$3000,"<="&DateExport)) | AF25: =IF(COUNTIFS('Rendez-vous'!$F$2:$F$3000,A25,'Rendez-vous'!$B$2:$B$3000,">="&DateExport)=0,"",_xlfn.MINIFS('Rendez-vous'!$B$2:$B$3000,'Rendez-vous'!$F$2:$F$3000,A25,'Rendez-vous'!$B$2:$B$3000,">="&DateExport)) | AG25: Kartéa Pharma Pack | AH25: 60 jours | AI25: Opportunité de référencement sur les notices et étuis d'un site de production. | AJ25: Appel d'offres en cours, trois fournisseurs retenus ; décision attendue au premier trimestre 2027.
A26: E025 | B26: Pernod Ricard | C26: pernod-ricard.com | D26: https://www.pernod-ricard.com | E26: Numéro deux mondial des vins et spiritueux (Absolut, Jameson, Ricard, Martell, Chivas Regal). | F26: Vins et spiritueux | G26: Spiritueux | H26: Grand compte | I26: 10 000 et plus | J26: 1 - 10 Md€ | K26: 5 cours Paul Ricard | L26: 75008 | M26: Paris | N26: Île-de-France | O26: France | P26: Groupe Pernod Ricard | Q26: Oui | R26: RI.PA | S26: U007 | T26: =IFERROR(INDEX(Commerciaux!$D$2:$D$3000,MATCH(S26,Commerciaux!$A$2:$A$3000,0)),"") | U26: Client | V26: Actif | W26: 43479 | X26: 43647 | Y26: Salon professionnel | Z26: 950000 | AA26: =SUMIFS(Commandes!$K$2:$K$3000,Commandes!$D$2:$D$3000,A26,Commandes!$C$2:$C$3000,">"&(DateExport-365),Commandes!$C$2:$C$3000,"<="&DateExport) | AB26: =COUNTIFS(Transactions!$C$2:$C$3000,A26,Transactions!$N$2:$N$3000,"Ouverte") | AC26: =SUMIFS(Transactions!$L$2:$L$3000,Transactions!$C$2:$C$3000,A26,Transactions!$N$2:$N$3000,"Ouverte") | AD26: =COUNTIFS(Tickets!$C$2:$C$3000,A26,Tickets!$I$2:$I$3000,"<>Fermé") | AE26: =IF(COUNTIFS(Activités!$D$2:$D$3000,A26,Activités!$B$2:$B$3000,"<="&DateExport)=0,"",_xlfn.MAXIFS(Activités!$B$2:$B$3000,Activités!$D$2:$D$3000,A26,Activités!$B$2:$B$3000,"<="&DateExport)) | AF26: =IF(COUNTIFS('Rendez-vous'!$F$2:$F$3000,A26,'Rendez-vous'!$B$2:$B$3000,">="&DateExport)=0,"",_xlfn.MINIFS('Rendez-vous'!$B$2:$B$3000,'Rendez-vous'!$F$2:$F$3000,A26,'Rendez-vous'!$B$2:$B$3000,">="&DateExport)) | AG26: Kartéa Luxe | AH26: 60 jours | AI26: Grand compte sur les étuis et coffrets de plusieurs marques. Achats centralisés, déclinés par filiale. | AJ26: Programme d'éco-conception des coffrets ; révision du panel fournisseurs en 2027.
A27: E026 | B27: Danone | C27: danone.com | D27: https://www.danone.com | E27: Groupe alimentaire mondial (produits laitiers et d'origine végétale, nutrition spécialisée, eaux). | F27: Grande consommation | G27: Produits laitiers et nutrition | H27: Grand compte | I27: 10 000 et plus | J27: Plus de 10 Md€ | K27: 17 boulevard Haussmann | L27: 75009 | M27: Paris | N27: Île-de-France | O27: France | P27: Groupe Danone | Q27: Oui | R27: BN.PA | S27: U007 | T27: =IFERROR(INDEX(Commerciaux!$D$2:$D$3000,MATCH(S27,Commerciaux!$A$2:$A$3000,0)),"") | U27: Client | V27: Actif | W27: 43717 | X27: 43878 | Y27: Prospection terrain | Z27: 880000 | AA27: =SUMIFS(Commandes!$K$2:$K$3000,Commandes!$D$2:$D$3000,A27,Commandes!$C$2:$C$3000,">"&(DateExport-365),Commandes!$C$2:$C$3000,"<="&DateExport) | AB27: =COUNTIFS(Transactions!$C$2:$C$3000,A27,Transactions!$N$2:$N$3000,"Ouverte") | AC27: =SUMIFS(Transactions!$L$2:$L$3000,Transactions!$C$2:$C$3000,A27,Transactions!$N$2:$N$3000,"Ouverte") | AD27: =COUNTIFS(Tickets!$C$2:$C$3000,A27,Tickets!$I$2:$I$3000,"<>Fermé") | AE27: =IF(COUNTIFS(Activités!$D$2:$D$3000,A27,Activités!$B$2:$B$3000,"<="&DateExport)=0,"",_xlfn.MAXIFS(Activités!$B$2:$B$3000,Activités!$D$2:$D$3000,A27,Activités!$B$2:$B$3000,"<="&DateExport)) | AF27: =IF(COUNTIFS('Rendez-vous'!$F$2:$F$3000,A27,'Rendez-vous'!$B$2:$B$3000,">="&DateExport)=0,"",_xlfn.MINIFS('Rendez-vous'!$B$2:$B$3000,'Rendez-vous'!$F$2:$F$3000,A27,'Rendez-vous'!$B$2:$B$3000,">="&DateExport)) | AG27: Emballor Industries | AH27: 60 jours | AI27: Grand compte sur les caisses carton et les étiquettes de plusieurs usines. | AJ27: Réduction des emballages secondaires ; essais de caisses en carton recyclé.
A28: E027 | B28: L'Oréal | C28: loreal.com | D28: https://www.loreal.com | E28: Numéro un mondial de la beauté (L'Oréal Paris, Lancôme, La Roche-Posay, Garnier). | F28: Grande consommation | G28: Cosmétiques | H28: Grand compte | I28: 10 000 et plus | J28: Plus de 10 Md€ | K28: 41 rue Martre | L28: 92110 | M28: Clichy | N28: Île-de-France | O28: France | P28: Groupe L'Oréal | Q28: Oui | R28: OR.PA | S28: U007 | T28: =IFERROR(INDEX(Commerciaux!$D$2:$D$3000,MATCH(S28,Commerciaux!$A$2:$A$3000,0)),"") | U28: Client | V28: Actif | W28: 44151 | X28: 44292 | Y28: Recommandation | Z28: 1000000 | AA28: =SUMIFS(Commandes!$K$2:$K$3000,Commandes!$D$2:$D$3000,A28,Commandes!$C$2:$C$3000,">"&(DateExport-365),Commandes!$C$2:$C$3000,"<="&DateExport) | AB28: =COUNTIFS(Transactions!$C$2:$C$3000,A28,Transactions!$N$2:$N$3000,"Ouverte") | AC28: =SUMIFS(Transactions!$L$2:$L$3000,Transactions!$C$2:$C$3000,A28,Transactions!$N$2:$N$3000,"Ouverte") | AD28: =COUNTIFS(Tickets!$C$2:$C$3000,A28,Tickets!$I$2:$I$3000,"<>Fermé") | AE28: =IF(COUNTIFS(Activités!$D$2:$D$3000,A28,Activités!$B$2:$B$3000,"<="&DateExport)=0,"",_xlfn.MAXIFS(Activités!$B$2:$B$3000,Activités!$D$2:$D$3000,A28,Activités!$B$2:$B$3000,"<="&DateExport)) | AF28: =IF(COUNTIFS('Rendez-vous'!$F$2:$F$3000,A28,'Rendez-vous'!$B$2:$B$3000,">="&DateExport)=0,"",_xlfn.MINIFS('Rendez-vous'!$B$2:$B$3000,'Rendez-vous'!$F$2:$F$3000,A28,'Rendez-vous'!$B$2:$B$3000,">="&DateExport)) | AG28: Cartonnages Vauclair | AH28: 60 jours | AI28: Grand compte sur les coffrets de fêtes et les étuis éco-conçus. | AJ28: Coffrets de fêtes 2027 : réduction du poids, absence de plastique et maîtrise des coûts.
A29: E028 | B29: Savencia | C29: savencia-fromagedairy.com | D29: https://www.savencia-fromagedairy.com | E29: Groupe familial de produits laitiers et fromagers (Caprice des Dieux, Saint Agur, Elle & Vire). | F29: Grande consommation | G29: Produits laitiers et fromages | H29: Grand compte | I29: 10 000 et plus | J29: 1 - 10 Md€ | K29: 42 rue Rieussec | L29: 78220 | M29: Viroflay | N29: Île-de-France | O29: France | P29: Savencia Fromage & Dairy | Q29: Oui | R29: SAVE.PA | S29: U007 | T29: =IFERROR(INDEX(Commerciaux!$D$2:$D$3000,MATCH(S29,Commerciaux!$A$2:$A$3000,0)),"") | U29: Client | V29: Actif | W29: 44438 | X29: 44578 | Y29: Salon professionnel | Z29: 340000 | AA29: =SUMIFS(Commandes!$K$2:$K$3000,Commandes!$D$2:$D$3000,A29,Commandes!$C$2:$C$3000,">"&(DateExport-365),Commandes!$C$2:$C$3000,"<="&DateExport) | AB29: =COUNTIFS(Transactions!$C$2:$C$3000,A29,Transactions!$N$2:$N$3000,"Ouverte") | AC29: =SUMIFS(Transactions!$L$2:$L$3000,Transactions!$C$2:$C$3000,A29,Transactions!$N$2:$N$3000,"Ouverte") | AD29: =COUNTIFS(Tickets!$C$2:$C$3000,A29,Tickets!$I$2:$I$3000,"<>Fermé") | AE29: =IF(COUNTIFS(Activités!$D$2:$D$3000,A29,Activités!$B$2:$B$3000,"<="&DateExport)=0,"",_xlfn.MAXIFS(Activités!$B$2:$B$3000,Activités!$D$2:$D$3000,A29,Activités!$B$2:$B$3000,"<="&DateExport)) | AF29: =IF(COUNTIFS('Rendez-vous'!$F$2:$F$3000,A29,'Rendez-vous'!$B$2:$B$3000,">="&DateExport)=0,"",_xlfn.MINIFS('Rendez-vous'!$B$2:$B$3000,'Rendez-vous'!$F$2:$F$3000,A29,'Rendez-vous'!$B$2:$B$3000,">="&DateExport)) | AG29: Emballor Industries | AH29: 60 jours | AI29: Client sur les étiquettes et caisses carton de plusieurs marques fromagères. | AJ29: Étiquettes multilingues pour une gamme export ; optimisation des caisses.
A30: E029 | B30: Saint-Gobain | C30: saint-gobain.com | D30: https://www.saint-gobain.com | E30: Leader mondial des matériaux de construction légère et durable. | F30: Équipements et matériaux | G30: Matériaux de construction | H30: Grand compte | I30: 10 000 et plus | J30: Plus de 10 Md€ | K30: Tour Saint-Gobain, 12 place de l'Iris | L30: 92400 | M30: Courbevoie | N30: Île-de-France | O30: France | P30: Groupe Saint-Gobain | Q30: Oui | R30: SGO.PA | S30: U007 | T30: =IFERROR(INDEX(Commerciaux!$D$2:$D$3000,MATCH(S30,Commerciaux!$A$2:$A$3000,0)),"") | U30: Prospect | V30: Nouveau | W30: 46209 | Y30: Recommandation | Z30: 600000 | AA30: =SUMIFS(Commandes!$K$2:$K$3000,Commandes!$D$2:$D$3000,A30,Commandes!$C$2:$C$3000,">"&(DateExport-365),Commandes!$C$2:$C$3000,"<="&DateExport) | AB30: =COUNTIFS(Transactions!$C$2:$C$3000,A30,Transactions!$N$2:$N$3000,"Ouverte") | AC30: =SUMIFS(Transactions!$L$2:$L$3000,Transactions!$C$2:$C$3000,A30,Transactions!$N$2:$N$3000,"Ouverte") | AD30: =COUNTIFS(Tickets!$C$2:$C$3000,A30,Tickets!$I$2:$I$3000,"<>Fermé") | AE30: =IF(COUNTIFS(Activités!$D$2:$D$3000,A30,Activités!$B$2:$B$3000,"<="&DateExport)=0,"",_xlfn.MAXIFS(Activités!$B$2:$B$3000,Activités!$D$2:$D$3000,A30,Activités!$B$2:$B$3000,"<="&DateExport)) | AF30: =IF(COUNTIFS('Rendez-vous'!$F$2:$F$3000,A30,'Rendez-vous'!$B$2:$B$3000,">="&DateExport)=0,"",_xlfn.MINIFS('Rendez-vous'!$B$2:$B$3000,'Rendez-vous'!$F$2:$F$3000,A30,'Rendez-vous'!$B$2:$B$3000,">="&DateExport)) | AH30: 60 jours | AI30: Prospect introduit par un contact chez un client. Besoin potentiel d'emballages de transport pour une activité de distribution. | AJ30: Comprendre l'organisation achats et le périmètre du besoin.
A31: E030 | B31: Schneider Electric | C31: se.com | D31: https://www.se.com | E31: Spécialiste mondial de la gestion de l'énergie et des automatismes industriels. | F31: Équipements et matériaux | G31: Matériel électrique et automatismes | H31: Grand compte | I31: 10 000 et plus | J31: Plus de 10 Md€ | K31: 35 rue Joseph Monier | L31: 92500 | M31: Rueil-Malmaison | N31: Île-de-France | O31: France | P31: Schneider Electric | Q31: Oui | R31: SU.PA | S31: U007 | T31: =IFERROR(INDEX(Commerciaux!$D$2:$D$3000,MATCH(S31,Commerciaux!$A$2:$A$3000,0)),"") | U31: Client | V31: Actif | W31: 44606 | X31: 44746 | Y31: Recommandation | Z31: 560000 | AA31: =SUMIFS(Commandes!$K$2:$K$3000,Commandes!$D$2:$D$3000,A31,Commandes!$C$2:$C$3000,">"&(DateExport-365),Commandes!$C$2:$C$3000,"<="&DateExport) | AB31: =COUNTIFS(Transactions!$C$2:$C$3000,A31,Transactions!$N$2:$N$3000,"Ouverte") | AC31: =SUMIFS(Transactions!$L$2:$L$3000,Transactions!$C$2:$C$3000,A31,Transactions!$N$2:$N$3000,"Ouverte") | AD31: =COUNTIFS(Tickets!$C$2:$C$3000,A31,Tickets!$I$2:$I$3000,"<>Fermé") | AE31: =IF(COUNTIFS(Activités!$D$2:$D$3000,A31,Activités!$B$2:$B$3000,"<="&DateExport)=0,"",_xlfn.MAXIFS(Activités!$B$2:$B$3000,Activités!$D$2:$D$3000,A31,Activités!$B$2:$B$3000,"<="&DateExport)) | AF31: =IF(COUNTIFS('Rendez-vous'!$F$2:$F$3000,A31,'Rendez-vous'!$B$2:$B$3000,">="&DateExport)=0,"",_xlfn.MINIFS('Rendez-vous'!$B$2:$B$3000,'Rendez-vous'!$F$2:$F$3000,A31,'Rendez-vous'!$B$2:$B$3000,">="&DateExport)) | AG31: Emballor Industries | AH31: 60 jours | AI31: Client sur les caisses carton et les emballages de produits de distribution électrique. | AJ31: Emballages sans plastique pour la distribution électrique ; deux fournisseurs en lice.

Sheet Contacts
A1: ID contact | B1: Civilité | C1: Prénom | D1: Nom | E1: Nom complet | F1: E-mail | G1: Téléphone fixe | H1: Téléphone mobile | I1: Intitulé du poste | J1: Service | K1: Niveau de décision | L1: Contact clé | M1: ID entreprise | N1: Entreprise | O1: ID propriétaire | P1: Propriétaire du contact | Q1: Phase du cycle de vie | R1: Statut du lead | S1: Source d'origine | T1: Canal préféré | U1: Langue | V1: Date de création | W1: Date du dernier contact | X1: Interactions 12 derniers mois | Y1: Consentement e-mail marketing | Z1: Notes
A2: C001 | B2: Mme | C2: Nathalie | D2: Dubreuil | E2: =C2&" "&D2 | F2: nathalie.dubreuil@bonduelle.example | G2: +33 1 99 00 10 11 | H2: +33 6 39 98 12 13 | I2: Responsable achats emballages | J2: Achats | K2: Décideur | L2: Oui | M2: E001 | N2: =IFERROR(INDEX(Entreprises!$B$2:$B$3000,MATCH(M2,Entreprises!$A$2:$A$3000,0)),"") | O2: U002 | P2: =IFERROR(INDEX(Commerciaux!$D$2:$D$3000,MATCH(O2,Commerciaux!$A$2:$A$3000,0)),"") | Q2: Client | R2: Connecté | S2: Salon professionnel | T2: Visite | U2: Français | V2: 44566 | W2: =IF(COUNTIFS(Activités!$F$2:$F$3000,A2,Activités!$B$2:$B$3000,"<="&DateExport)=0,"",_xlfn.MAXIFS(Activités!$B$2:$B$3000,Activités!$F$2:$F$3000,A2,Activités!$B$2:$B$3000,"<="&DateExport)) | X2: =COUNTIFS(Activités!$F$2:$F$3000,A2,Activités!$B$2:$B$3000,">"&(DateExport-365),Activités!$B$2:$B$3000,"<="&DateExport) | Y2: Oui | Z2: Interlocutrice principale. Très attentive au respect des délais et aux indexations matières.
A3: C002 | B3: M. | C3: Kevin | D3: Lemaire | E3: =C3&" "&D3 | F3: kevin.lemaire@bonduelle.example | G3: +33 1 99 00 13 18 | H3: +33 6 39 98 17 22 | I3: Chef de projet packaging | J3: R&D packaging | K3: Prescripteur | L3: Non | M3: E001 | N3: =IFERROR(INDEX(Entreprises!$B$2:$B$3000,MATCH(M3,Entreprises!$A$2:$A$3000,0)),"") | O3: U002 | P3: =IFERROR(INDEX(Commerciaux!$D$2:$D$3000,MATCH(O3,Commerciaux!$A$2:$A$3000,0)),"") | Q3: Client | R3: Connecté | S3: Salon professionnel | T3: E-mail | U3: Français | V3: 44508 | W3: =IF(COUNTIFS(Activités!$F$2:$F$3000,A3,Activités!$B$2:$B$3000,"<="&DateExport)=0,"",_xlfn.MAXIFS(Activités!$B$2:$B$3000,Activités!$F$2:$F$3000,A3,Activités!$B$2:$B$3000,"<="&DateExport)) | X3: =COUNTIFS(Activités!$F$2:$F$3000,A3,Activités!$B$2:$B$3000,">"&(DateExport-365),Activités!$B$2:$B$3000,"<="&DateExport) | Y3: Oui | Z3: Porte le projet d'emballages mono-matériau. Apprécie les échantillons physiques.
A4: C003 | B4: Mme | C4: Aurélie | D4: Vasseur | E4: =C4&" "&D4 | F4: aurelie.vasseur@lesaffre.example | G4: +33 1 99 00 16 25 | H4: +33 6 39 98 22 31 | I4: Acheteuse emballages et indirects | J4: Achats | K4: Influenceur | L4: Oui | M4: E002 | N4: =IFERROR(INDEX(Entreprises!$B$2:$B$3000,MATCH(M4,Entreprises!$A$2:$A$3000,0)),"") | O4: U002 | P4: =IFERROR(INDEX(Commerciaux!$D$2:$D$3000,MATCH(O4,Commerciaux!$A$2:$A$3000,0)),"") | Q4: Client | R4: Connecté | S4: Prospection terrain | T4: Téléphone | U4: Français | V4: 44743 | W4: =IF(COUNTIFS(Activités!$F$2:$F$3000,A4,Activités!$B$2:$B$3000,"<="&DateExport)=0,"",_xlfn.MAXIFS(Activités!$B$2:$B$3000,Activités!$F$2:$F$3000,A4,Activités!$B$2:$B$3000,"<="&DateExport)) | X4: =COUNTIFS(Activités!$F$2:$F$3000,A4,Activités!$B$2:$B$3000,">"&(DateExport-365),Activités!$B$2:$B$3000,"<="&DateExport) | Y4: Oui | Z4: Gère les commandes récurrentes de caisses et d'étiquettes.
A5: C004 | B5: M. | C5: Philippe | D5: Delattre | E5: =C5&" "&D5 | F5: philippe.delattre@lesaffre.example | G5: +33 1 99 00 19 32 | H5: +33 6 39 98 27 40 | I5: Directeur industriel | J5: Industrie | K5: Décideur | L5: Oui | M5: E002 | N5: =IFERROR(INDEX(Entreprises!$B$2:$B$3000,MATCH(M5,Entreprises!$A$2:$A$3000,0)),"") | O5: U002 | P5: =IFERROR(INDEX(Commerciaux!$D$2:$D$3000,MATCH(O5,Commerciaux!$A$2:$A$3000,0)),"") | Q5: Client | R5: Connecté | S5: Prospection terrain | T5: Visite | U5: Français | V5: 46041 | W5: =IF(COUNTIFS(Activités!$F$2:$F$3000,A5,Activités!$B$2:$B$3000,"<="&DateExport)=0,"",_xlfn.MAXIFS(Activités!$B$2:$B$3000,Activités!$F$2:$F$3000,A5,Activités!$B$2:$B$3000,"<="&DateExport)) | X5: =COUNTIFS(Activités!$F$2:$F$3000,A5,Activités!$B$2:$B$3000,">"&(DateExport-365),Activités!$B$2:$B$3000,"<="&DateExport) | Y5: Non | Z5: Arrivé en janvier 2026. Raisonne en coût total de possession et en sécurité des opérateurs.
A6: C005 | B6: Mme | C6: Sophie | D6: Marchand | E6: =C6&" "&D6 | F6: sophie.marchand@guerbet.example | G6: +33 1 99 00 22 39 | H6: +33 6 39 98 32 49 | I6: Responsable assurance qualité fournisseurs | J6: Qualité | K6: Décideur | L6: Oui | M6: E003 | N6: =IFERROR(INDEX(Entreprises!$B$2:$B$3000,MATCH(M6,Entreprises!$A$2:$A$3000,0)),"") | O6: U002 | P6: =IFERROR(INDEX(Commerciaux!$D$2:$D$3000,MATCH(O6,Commerciaux!$A$2:$A$3000,0)),"") | Q6: Client | R6: Connecté | S6: Recommandation | T6: E-mail | U6: Français | V6: 43888 | W6: =IF(COUNTIFS(Activités!$F$2:$F$3000,A6,Activités!$B$2:$B$3000,"<="&DateExport)=0,"",_xlfn.MAXIFS(Activités!$B$2:$B$3000,Activités!$F$2:$F$3000,A6,Activités!$B$2:$B$3000,"<="&DateExport)) | X6: =COUNTIFS(Activités!$F$2:$F$3000,A6,Activités!$B$2:$B$3000,">"&(DateExport-365),Activités!$B$2:$B$3000,"<="&DateExport) | Y6: Non | Z6: Pilote les audits fournisseurs. Exige des réponses écrites et documentées.
A7: C006 | B7: M. | C7: Olivier | D7: Chen | E7: =C7&" "&D7 | F7: olivier.chen@guerbet.example | G7: +33 1 99 00 25 46 | H7: +33 6 39 98 37 58 | I7: Responsable conditionnement | J7: Production | K7: Prescripteur | L7: Non | M7: E003 | N7: =IFERROR(INDEX(Entreprises!$B$2:$B$3000,MATCH(M7,Entreprises!$A$2:$A$3000,0)),"") | O7: U002 | P7: =IFERROR(INDEX(Commerciaux!$D$2:$D$3000,MATCH(O7,Commerciaux!$A$2:$A$3000,0)),"") | Q7: Client | R7: Connecté | S7: Recommandation | T7: Téléphone | U7: Français | V7: 43913 | W7: =IF(COUNTIFS(Activités!$F$2:$F$3000,A7,Activités!$B$2:$B$3000,"<="&DateExport)=0,"",_xlfn.MAXIFS(Activités!$B$2:$B$3000,Activités!$F$2:$F$3000,A7,Activités!$B$2:$B$3000,"<="&DateExport)) | X7: =COUNTIFS(Activités!$F$2:$F$3000,A7,Activités!$B$2:$B$3000,">"&(DateExport-365),Activités!$B$2:$B$3000,"<="&DateExport) | Y7: Oui | Z7: Porte le projet de refonte des notices multilingues.
A8: C007 | B8: Mme | C8: Claire | D8: Fontaine | E8: =C8&" "&D8 | F8: claire.fontaine@interparfums.example | G8: +33 1 99 00 28 53 | H8: +33 6 39 98 42 67 | I8: Responsable développement packaging | J8: Packaging | K8: Décideur | L8: Oui | M8: E004 | N8: =IFERROR(INDEX(Entreprises!$B$2:$B$3000,MATCH(M8,Entreprises!$A$2:$A$3000,0)),"") | O8: U002 | P8: =IFERROR(INDEX(Commerciaux!$D$2:$D$3000,MATCH(O8,Commerciaux!$A$2:$A$3000,0)),"") | Q8: Client | R8: Connecté | S8: Salon professionnel | T8: Visite | U8: Français | V8: 44952 | W8: =IF(COUNTIFS(Activités!$F$2:$F$3000,A8,Activités!$B$2:$B$3000,"<="&DateExport)=0,"",_xlfn.MAXIFS(Activités!$B$2:$B$3000,Activités!$F$2:$F$3000,A8,Activités!$B$2:$B$3000,"<="&DateExport)) | X8: =COUNTIFS(Activités!$F$2:$F$3000,A8,Activités!$B$2:$B$3000,">"&(DateExport-365),Activités!$B$2:$B$3000,"<="&DateExport) | Y8: Oui | Z8: Sensible au design et à l'éco-conception.
A9: C008 | B9: M. | C9: Hugo | D9: Perrin | E9: =C9&" "&D9 | F9: hugo.perrin@interparfums.example | G9: +33 1 99 00 31 60 | H9: +33 6 39 98 47 76 | I9: Acheteur | J9: Achats | K9: Influenceur | L9: Non | M9: E004 | N9: =IFERROR(INDEX(Entreprises!$B$2:$B$3000,MATCH(M9,Entreprises!$A$2:$A$3000,0)),"") | O9: U002 | P9: =IFERROR(INDEX(Commerciaux!$D$2:$D$3000,MATCH(O9,Commerciaux!$A$2:$A$3000,0)),"") | Q9: Client | R9: Connecté | S9: Salon professionnel | T9: E-mail | U9: Français | V9: 44966 | W9: =IF(COUNTIFS(Activités!$F$2:$F$3000,A9,Activités!$B$2:$B$3000,"<="&DateExport)=0,"",_xlfn.MAXIFS(Activités!$B$2:$B$3000,Activités!$F$2:$F$3000,A9,Activités!$B$2:$B$3000,"<="&DateExport)) | X9: =COUNTIFS(Activités!$F$2:$F$3000,A9,Activités!$B$2:$B$3000,">"&(DateExport-365),Activités!$B$2:$B$3000,"<="&DateExport) | Y9: Oui | Z9: Suit les délais et la facturation.
A10: C009 | B10: Mme | C10: Léa | D10: Moreau | E10: =C10&" "&D10 | F10: lea.moreau@clarins.example | G10: +33 1 99 00 34 67 | H10: +33 6 39 98 52 85 | I10: Responsable achats packaging | J10: Achats | K10: Décideur | L10: Oui | M10: E005 | N10: =IFERROR(INDEX(Entreprises!$B$2:$B$3000,MATCH(M10,Entreprises!$A$2:$A$3000,0)),"") | O10: U002 | P10: =IFERROR(INDEX(Commerciaux!$D$2:$D$3000,MATCH(O10,Commerciaux!$A$2:$A$3000,0)),"") | Q10: Opportunité | R10: Affaire ouverte | S10: Site web | T10: Visio | U10: Français | V10: 45981 | W10: =IF(COUNTIFS(Activités!$F$2:$F$3000,A10,Activités!$B$2:$B$3000,"<="&DateExport)=0,"",_xlfn.MAXIFS(Activités!$B$2:$B$3000,Activités!$F$2:$F$3000,A10,Activités!$B$2:$B$3000,"<="&DateExport)) | X10: =COUNTIFS(Activités!$F$2:$F$3000,A10,Activités!$B$2:$B$3000,">"&(DateExport-365),Activités!$B$2:$B$3000,"<="&DateExport) | Y10: Oui | Z10: Contact entrant via le site web. Cherche un second fournisseur d'étuis.
A11: C010 | B11: M. | C11: Rachid | D11: Bensaïd | E11: =C11&" "&D11 | F11: rachid.bensaid@imerys.example | G11: +33 1 99 00 37 74 | H11: +33 6 39 98 57 94 | I11: Responsable supply chain | J11: Supply chain | K11: Influenceur | L11: Oui | M11: E006 | N11: =IFERROR(INDEX(Entreprises!$B$2:$B$3000,MATCH(M11,Entreprises!$A$2:$A$3000,0)),"") | O11: U002 | P11: =IFERROR(INDEX(Commerciaux!$D$2:$D$3000,MATCH(O11,Commerciaux!$A$2:$A$3000,0)),"") | Q11: Prospect | R11: Tentative de contact | S11: Prospection téléphonique | T11: Téléphone | U11: Français | V11: 46262 | W11: =IF(COUNTIFS(Activités!$F$2:$F$3000,A11,Activités!$B$2:$B$3000,"<="&DateExport)=0,"",_xlfn.MAXIFS(Activités!$B$2:$B$3000,Activités!$F$2:$F$3000,A11,Activités!$B$2:$B$3000,"<="&DateExport)) | X11: =COUNTIFS(Activités!$F$2:$F$3000,A11,Activités!$B$2:$B$3000,">"&(DateExport-365),Activités!$B$2:$B$3000,"<="&DateExport) | Y11: Non | Z11: Premier contact chez Imerys, oriente vers les achats si le besoin se confirme.
A12: C011 | B12: M. | C12: François | D12: Girard | E12: =C12&" "&D12 | F12: francois.girard@nexans.example | G12: +33 1 99 00 40 81 | H12: +33 6 39 98 62 20 | I12: Responsable logistique France | J12: Logistique | K12: Décideur | L12: Oui | M12: E007 | N12: =IFERROR(INDEX(Entreprises!$B$2:$B$3000,MATCH(M12,Entreprises!$A$2:$A$3000,0)),"") | O12: U002 | P12: =IFERROR(INDEX(Commerciaux!$D$2:$D$3000,MATCH(O12,Commerciaux!$A$2:$A$3000,0)),"") | Q12: Client | R12: Connecté | S12: Recommandation | T12: Visite | U12: Français | V12: 45112 | W12: =IF(COUNTIFS(Activités!$F$2:$F$3000,A12,Activités!$B$2:$B$3000,"<="&DateExport)=0,"",_xlfn.MAXIFS(Activités!$B$2:$B$3000,Activités!$F$2:$F$3000,A12,Activités!$B$2:$B$3000,"<="&DateExport)) | X12: =COUNTIFS(Activités!$F$2:$F$3000,A12,Activités!$B$2:$B$3000,">"&(DateExport-365),Activités!$B$2:$B$3000,"<="&DateExport) | Y12: Oui | Z12: Porte l'harmonisation des étiquettes logistiques entre sites.
A13: C012 | B13: Mme | C13: Marie-Laure | D13: Rivière | E13: =C13&" "&D13 | F13: marie-laure.riviere@moet.example | G13: +33 1 99 00 43 88 | H13: +33 6 39 98 67 29 | I13: Directrice achats matières sèches | J13: Achats | K13: Décideur | L13: Oui | M13: E008 | N13: =IFERROR(INDEX(Entreprises!$B$2:$B$3000,MATCH(M13,Entreprises!$A$2:$A$3000,0)),"") | O13: U003 | P13: =IFERROR(INDEX(Commerciaux!$D$2:$D$3000,MATCH(O13,Commerciaux!$A$2:$A$3000,0)),"") | Q13: Client | R13: Connecté | S13: Salon professionnel | T13: Visite | U13: Français | V13: 43640 | W13: =IF(COUNTIFS(Activités!$F$2:$F$3000,A13,Activités!$B$2:$B$3000,"<="&DateExport)=0,"",_xlfn.MAXIFS(Activités!$B$2:$B$3000,Activités!$F$2:$F$3000,A13,Activités!$B$2:$B$3000,"<="&DateExport)) | X13: =COUNTIFS(Activités!$F$2:$F$3000,A13,Activités!$B$2:$B$3000,">"&(DateExport-365),Activités!$B$2:$B$3000,"<="&DateExport) | Y13: Non | Z13: Décide avec le marketing sur les projets premium.
... A51: C050 | B51: M. | C51: Pierre-Yves | D51: Guérin | E51: =C51&" "&D51 | F51: pierre-yves.guerin@se.example | G51: +33 1 99 00 68 93 | H51: +33 6 39 98 87 39 | I51: Ingénieur packaging durable | J51: R&D | K51: Prescripteur | L51: Non | M51: E030 | N51: =IFERROR(INDEX(Entreprises!$B$2:$B$3000,MATCH(M51,Entreprises!$A$2:$A$3000,0)),"") | O51: U007 | P51: =IFERROR(INDEX(Commerciaux!$D$2:$D$3000,MATCH(O51,Commerciaux!$A$2:$A$3000,0)),"") | Q51: Client | R51: Connecté | S51: Recommandation | T51: Visio | U51: Français | V51: 44652 | W51: =IF(COUNTIFS(Activités!$F$2:$F$3000,A51,Activités!$B$2:$B$3000,"<="&DateExport)=0,"",_xlfn.MAXIFS(Activités!$B$2:$B$3000,Activités!$F$2:$F$3000,A51,Activités!$B$2:$B$3000,"<="&DateExport)) | X51: =COUNTIFS(Activités!$F$2:$F$3000,A51,Activités!$B$2:$B$3000,">"&(DateExport-365),Activités!$B$2:$B$3000,"<="&DateExport) | Y51: Oui | Z51: A validé nos tests de résistance.

Sheet Transactions
A1: ID transaction | B1: Nom de la transaction | C1: ID entreprise | D1: Entreprise | E1: ID contact principal | F1: Contact principal | G1: ID propriétaire | H1: Propriétaire | I1: Pipeline | J1: Phase de la transaction | K1: Probabilité | L1: Montant (€) | M1: Montant pondéré (€) | N1: Statut | O1: Type de transaction | P1: ID produit principal | Q1: Produit principal | R1: Date de création | S1: Date de clôture prévue | T1: Date de clôture effective | U1: Prochaine étape | V1: Concurrent en lice | W1: Motif de perte
A2: T001 | B2: Bonduelle - Renouvellement accord-cadre étiquettes 2027 | C2: E001 | D2: =IFERROR(INDEX(Entreprises!$B$2:$B$3000,MATCH(C2,Entreprises!$A$2:$A$3000,0)),"") | E2: C001 | F2: =IFERROR(INDEX(Contacts!$E$2:$E$3000,MATCH(E2,Contacts!$A$2:$A$3000,0)),"") | G2: U002 | H2: =IFERROR(INDEX(Commerciaux!$D$2:$D$3000,MATCH(G2,Commerciaux!$A$2:$A$3000,0)),"") | I2: Ventes terrain | J2: Contrat envoyé | K2: =IFERROR(INDEX(Paramètres!$B$7:$B$13,MATCH(J2,Paramètres!$A$7:$A$13,0)),"") | L2: 186000 | M2: =IF(OR(L2="",K2=""),"",L2*K2) | N2: =IFERROR(INDEX(Paramètres!$C$7:$C$13,MATCH(J2,Paramètres!$A$7:$A$13,0)),"") | O2: Renouvellement | P2: P003 | Q2: =IFERROR(INDEX(Produits!$C$2:$C$3000,MATCH(P2,Produits!$A$2:$A$3000,0)),"") | R2: 46197 | S2: 46356 | U2: Défendre la proposition et l'engagement sur les délais lors de la revue du 12/10 | V2: Labelis Group
A3: T002 | B3: Bonduelle - Emballages mono-matériau gamme bio | C3: E001 | D3: =IFERROR(INDEX(Entreprises!$B$2:$B$3000,MATCH(C3,Entreprises!$A$2:$A$3000,0)),"") | E3: C002 | F3: =IFERROR(INDEX(Contacts!$E$2:$E$3000,MATCH(E3,Contacts!$A$2:$A$3000,0)),"") | G3: U002 | H3: =IFERROR(INDEX(Commerciaux!$D$2:$D$3000,MATCH(G3,Commerciaux!$A$2:$A$3000,0)),"") | I3: Ventes terrain | J3: Qualifié pour achat | K3: =IFERROR(INDEX(Paramètres!$B$7:$B$13,MATCH(J3,Paramètres!$A$7:$A$13,0)),"") | L3: 64000 | M3: =IF(OR(L3="",K3=""),"",L3*K3) | N3: =IFERROR(INDEX(Paramètres!$C$7:$C$13,MATCH(J3,Paramètres!$A$7:$A$13,0)),"") | O3: Nouvelle affaire | P3: P008 | Q3: =IFERROR(INDEX(Produits!$C$2:$C$3000,MATCH(P3,Produits!$A$2:$A$3000,0)),"") | R3: 46197 | S3: 46444 | U3: Faire valider les échantillons papier certifié
A4: T003 | B4: Bonduelle - Caisses carton 2025 | C4: E001 | D4: =IFERROR(INDEX(Entreprises!$B$2:$B$3000,MATCH(C4,Entreprises!$A$2:$A$3000,0)),"") | E4: C001 | F4: =IFERROR(INDEX(Contacts!$E$2:$E$3000,MATCH(E4,Contacts!$A$2:$A$3000,0)),"") | G4: U002 | H4: =IFERROR(INDEX(Commerciaux!$D$2:$D$3000,MATCH(G4,Commerciaux!$A$2:$A$3000,0)),"") | I4: Ventes terrain | J4: Conclu gagné | K4: =IFERROR(INDEX(Paramètres!$B$7:$B$13,MATCH(J4,Paramètres!$A$7:$A$13,0)),"") | L4: 92000 | M4: =IF(OR(L4="",K4=""),"",L4*K4) | N4: =IFERROR(INDEX(Paramètres!$C$7:$C$13,MATCH(J4,Paramètres!$A$7:$A$13,0)),"") | O4: Affaire existante | P4: P007 | Q4: =IFERROR(INDEX(Produits!$C$2:$C$3000,MATCH(P4,Produits!$A$2:$A$3000,0)),"") | R4: 45600 | S4: 45672 | T4: 45672
A5: T004 | B5: Lesaffre - Encartonneuse ligne levure sèche | C5: E002 | D5: =IFERROR(INDEX(Entreprises!$B$2:$B$3000,MATCH(C5,Entreprises!$A$2:$A$3000,0)),"") | E5: C004 | F5: =IFERROR(INDEX(Contacts!$E$2:$E$3000,MATCH(E5,Contacts!$A$2:$A$3000,0)),"") | G5: U002 | H5: =IFERROR(INDEX(Commerciaux!$D$2:$D$3000,MATCH(G5,Commerciaux!$A$2:$A$3000,0)),"") | I5: Ventes terrain | J5: Présentation planifiée | K5: =IFERROR(INDEX(Paramètres!$B$7:$B$13,MATCH(J5,Paramètres!$A$7:$A$13,0)),"") | L5: 148000 | M5: =IF(OR(L5="",K5=""),"",L5*K5) | N5: =IFERROR(INDEX(Paramètres!$C$7:$C$13,MATCH(J5,Paramètres!$A$7:$A$13,0)),"") | O5: Nouvelle affaire | P5: P011 | Q5: =IFERROR(INDEX(Produits!$C$2:$C$3000,MATCH(P5,Produits!$A$2:$A$3000,0)),"") | R5: 46282 | S5: 46371 | U5: Démonstration de l'EC-200 le 12/10, puis chiffrage avec maintenance | V5: Emballor Industries
A6: T005 | B6: Lesaffre - Étiquettes logistiques 2026 | C6: E002 | D6: =IFERROR(INDEX(Entreprises!$B$2:$B$3000,MATCH(C6,Entreprises!$A$2:$A$3000,0)),"") | E6: C003 | F6: =IFERROR(INDEX(Contacts!$E$2:$E$3000,MATCH(E6,Contacts!$A$2:$A$3000,0)),"") | G6: U002 | H6: =IFERROR(INDEX(Commerciaux!$D$2:$D$3000,MATCH(G6,Commerciaux!$A$2:$A$3000,0)),"") | I6: Ventes terrain | J6: Conclu gagné | K6: =IFERROR(INDEX(Paramètres!$B$7:$B$13,MATCH(J6,Paramètres!$A$7:$A$13,0)),"") | L6: 38000 | M6: =IF(OR(L6="",K6=""),"",L6*K6) | N6: =IFERROR(INDEX(Paramètres!$C$7:$C$13,MATCH(J6,Paramètres!$A$7:$A$13,0)),"") | O6: Affaire existante | P6: P003 | Q6: =IFERROR(INDEX(Produits!$C$2:$C$3000,MATCH(P6,Produits!$A$2:$A$3000,0)),"") | R6: 45964 | S6: 46042 | T6: 46042
A7: T006 | B7: Guerbet - Notices multilingues 2027 | C7: E003 | D7: =IFERROR(INDEX(Entreprises!$B$2:$B$3000,MATCH(C7,Entreprises!$A$2:$A$3000,0)),"") | E7: C006 | F7: =IFERROR(INDEX(Contacts!$E$2:$E$3000,MATCH(E7,Contacts!$A$2:$A$3000,0)),"") | G7: U002 | H7: =IFERROR(INDEX(Commerciaux!$D$2:$D$3000,MATCH(G7,Commerciaux!$A$2:$A$3000,0)),"") | I7: Ventes terrain | J7: Qualifié pour achat | K7: =IFERROR(INDEX(Paramètres!$B$7:$B$13,MATCH(J7,Paramètres!$A$7:$A$13,0)),"") | L7: 72000 | M7: =IF(OR(L7="",K7=""),"",L7*K7) | N7: =IFERROR(INDEX(Paramètres!$C$7:$C$13,MATCH(J7,Paramètres!$A$7:$A$13,0)),"") | O7: Nouvelle affaire | P7: P002 | Q7: =IFERROR(INDEX(Produits!$C$2:$C$3000,MATCH(P7,Produits!$A$2:$A$3000,0)),"") | R7: 46211 | S7: 46477 | U7: Rassurer sur la qualité avant l'audit fournisseur de novembre | V7: Kartéa Pharma Pack
A8: T007 | B8: Guerbet - Étiquettes d'inviolabilité | C8: E003 | D8: =IFERROR(INDEX(Entreprises!$B$2:$B$3000,MATCH(C8,Entreprises!$A$2:$A$3000,0)),"") | E8: C005 | F8: =IFERROR(INDEX(Contacts!$E$2:$E$3000,MATCH(E8,Contacts!$A$2:$A$3000,0)),"") | G8: U002 | H8: =IFERROR(INDEX(Commerciaux!$D$2:$D$3000,MATCH(G8,Commerciaux!$A$2:$A$3000,0)),"") | I8: Ventes terrain | J8: Conclu perdu | K8: =IFERROR(INDEX(Paramètres!$B$7:$B$13,MATCH(J8,Paramètres!$A$7:$A$13,0)),"") | L8: 45000 | M8: =IF(OR(L8="",K8=""),"",L8*K8) | N8: =IFERROR(INDEX(Paramètres!$C$7:$C$13,MATCH(J8,Paramètres!$A$7:$A$13,0)),"") | O8: Nouvelle affaire | P8: P004 | Q8: =IFERROR(INDEX(Produits!$C$2:$C$3000,MATCH(P8,Produits!$A$2:$A$3000,0)),"") | R8: 46083 | S8: 46223 | T8: 46223 | V8: Kartéa Pharma Pack | W8: Incident qualité sur un lot d'étuis en juin
A9: T008 | B9: Interparfums - Coffrets éditions limitées 2027 | C9: E004 | D9: =IFERROR(INDEX(Entreprises!$B$2:$B$3000,MATCH(C9,Entreprises!$A$2:$A$3000,0)),"") | E9: C007 | F9: =IFERROR(INDEX(Contacts!$E$2:$E$3000,MATCH(E9,Contacts!$A$2:$A$3000,0)),"") | G9: U002 | H9: =IFERROR(INDEX(Commerciaux!$D$2:$D$3000,MATCH(G9,Commerciaux!$A$2:$A$3000,0)),"") | I9: Ventes terrain | J9: Rendez-vous programmé | K9: =IFERROR(INDEX(Paramètres!$B$7:$B$13,MATCH(J9,Paramètres!$A$7:$A$13,0)),"") | L9: 95000 | M9: =IF(OR(L9="",K9=""),"",L9*K9) | N9: =IFERROR(INDEX(Paramètres!$C$7:$C$13,MATCH(J9,Paramètres!$A$7:$A$13,0)),"") | O9: Affaire existante | P9: P005 | Q9: =IFERROR(INDEX(Produits!$C$2:$C$3000,MATCH(P9,Produits!$A$2:$A$3000,0)),"") | R9: 46268 | S9: 46416 | U9: Présenter trois maquettes de coffrets éco-conçus | V9: Cartonnages Vauclair
A10: T009 | B10: Interparfums - Coffrets fin d'année 2026 | C10: E004 | D10: =IFERROR(INDEX(Entreprises!$B$2:$B$3000,MATCH(C10,Entreprises!$A$2:$A$3000,0)),"") | E10: C007 | F10: =IFERROR(INDEX(Contacts!$E$2:$E$3000,MATCH(E10,Contacts!$A$2:$A$3000,0)),"") | G10: U002 | H10: =IFERROR(INDEX(Commerciaux!$D$2:$D$3000,MATCH(G10,Commerciaux!$A$2:$A$3000,0)),"") | I10: Ventes terrain | J10: Conclu gagné | K10: =IFERROR(INDEX(Paramètres!$B$7:$B$13,MATCH(J10,Paramètres!$A$7:$A$13,0)),"") | L10: 118000 | M10: =IF(OR(L10="",K10=""),"",L10*K10) | N10: =IFERROR(INDEX(Paramètres!$C$7:$C$13,MATCH(J10,Paramètres!$A$7:$A$13,0)),"") | O10: Affaire existante | P10: P005 | Q10: =IFERROR(INDEX(Produits!$C$2:$C$3000,MATCH(P10,Produits!$A$2:$A$3000,0)),"") | R10: 46034 | S10: 46126 | T10: 46126
A11: T010 | B11: Clarins - Référencement second fournisseur étuis | C11: E005 | D11: =IFERROR(INDEX(Entreprises!$B$2:$B$3000,MATCH(C11,Entreprises!$A$2:$A$3000,0)),"") | E11: C009 | F11: =IFERROR(INDEX(Contacts!$E$2:$E$3000,MATCH(E11,Contacts!$A$2:$A$3000,0)),"") | G11: U002 | H11: =IFERROR(INDEX(Commerciaux!$D$2:$D$3000,MATCH(G11,Commerciaux!$A$2:$A$3000,0)),"") | I11: Ventes terrain | J11: Qualifié pour achat | K11: =IFERROR(INDEX(Paramètres!$B$7:$B$13,MATCH(J11,Paramètres!$A$7:$A$13,0)),"") | L11: 150000 | M11: =IF(OR(L11="",K11=""),"",L11*K11) | N11: =IFERROR(INDEX(Paramètres!$C$7:$C$13,MATCH(J11,Paramètres!$A$7:$A$13,0)),"") | O11: Nouvelle affaire | P11: P008 | Q11: =IFERROR(INDEX(Produits!$C$2:$C$3000,MATCH(P11,Produits!$A$2:$A$3000,0)),"") | R11: 46037 | S11: 46461 | U11: Envoyer les échantillons et la fiche RSE | V11: Cartonnages Vauclair
A12: T011 | B12: Imerys - Emballages de transport minéraux | C12: E006 | D12: =IFERROR(INDEX(Entreprises!$B$2:$B$3000,MATCH(C12,Entreprises!$A$2:$A$3000,0)),"") | E12: C010 | F12: =IFERROR(INDEX(Contacts!$E$2:$E$3000,MATCH(E12,Contacts!$A$2:$A$3000,0)),"") | G12: U002 | H12: =IFERROR(INDEX(Commerciaux!$D$2:$D$3000,MATCH(G12,Commerciaux!$A$2:$A$3000,0)),"") | I12: Ventes terrain | J12: Rendez-vous programmé | K12: =IFERROR(INDEX(Paramètres!$B$7:$B$13,MATCH(J12,Paramètres!$A$7:$A$13,0)),"") | L12: 60000 | M12: =IF(OR(L12="",K12=""),"",L12*K12) | N12: =IFERROR(INDEX(Paramètres!$C$7:$C$13,MATCH(J12,Paramètres!$A$7:$A$13,0)),"") | O12: Nouvelle affaire | P12: P007 | Q12: =IFERROR(INDEX(Produits!$C$2:$C$3000,MATCH(P12,Produits!$A$2:$A$3000,0)),"") | R12: 46267 | S12: 46507 | U12: Premier rendez-vous de qualification le 27/10
A13: T012 | B13: Nexans - Harmonisation des étiquettes logistiques | C13: E007 | D13: =IFERROR(INDEX(Entreprises!$B$2:$B$3000,MATCH(C13,Entreprises!$A$2:$A$3000,0)),"") | E13: C011 | F13: =IFERROR(INDEX(Contacts!$E$2:$E$3000,MATCH(E13,Contacts!$A$2:$A$3000,0)),"") | G13: U002 | H13: =IFERROR(INDEX(Commerciaux!$D$2:$D$3000,MATCH(G13,Commerciaux!$A$2:$A$3000,0)),"") | I13: Ventes terrain | J13: Décideur impliqué | K13: =IFERROR(INDEX(Paramètres!$B$7:$B$13,MATCH(J13,Paramètres!$A$7:$A$13,0)),"") | L13: 28000 | M13: =IF(OR(L13="",K13=""),"",L13*K13) | N13: =IFERROR(INDEX(Paramètres!$C$7:$C$13,MATCH(J13,Paramètres!$A$7:$A$13,0)),"") | O13: Affaire existante | P13: P013 | Q13: =IFERROR(INDEX(Produits!$C$2:$C$3000,MATCH(P13,Produits!$A$2:$A$3000,0)),"") | R13: 46161 | S13: 46346 | U13: Restituer l'étude d'harmonisation
A14: T013 | B14: Moët & Chandon - Étuis allégés 2027 | C14: E008 | D14: =IFERROR(INDEX(Entreprises!$B$2:$B$3000,MATCH(C14,Entreprises!$A$2:$A$3000,0)),"") | E14: C013 | F14: =IFERROR(INDEX(Contacts!$E$2:$E$3000,MATCH(E14,Contacts!$A$2:$A$3000,0)),"") | G14: U003 | H14: =IFERROR(INDEX(Commerciaux!$D$2:$D$3000,MATCH(G14,Commerciaux!$A$2:$A$3000,0)),"") | I14: Ventes terrain | J14: Qualifié pour achat | K14: =IFERROR(INDEX(Paramètres!$B$7:$B$13,MATCH(J14,Paramètres!$A$7:$A$13,0)),"") | L14: 240000 | M14: =IF(OR(L14="",K14=""),"",L14*K14) | N14: =IFERROR(INDEX(Paramètres!$C$7:$C$13,MATCH(J14,Paramètres!$A$7:$A$13,0)),"") | O14: Affaire existante | P14: P006 | Q14: =IFERROR(INDEX(Produits!$C$2:$C$3000,MATCH(P14,Produits!$A$2:$A$3000,0)),"") | R14: 46275 | S14: 46433 | U14: Présenter les prototypes sans film plastique | V14: Kartéa Luxe
A15: T014 | B15: Moët & Chandon - Coffrets fin d'année 2026 | C15: E008 | D15: =IFERROR(INDEX(Entreprises!$B$2:$B$3000,MATCH(C15,Entreprises!$A$2:$A$3000,0)),"") | E15: C012 | F15: =IFERROR(INDEX(Contacts!$E$2:$E$3000,MATCH(E15,Contacts!$A$2:$A$3000,0)),"") | G15: U003 | H15: =IFERROR(INDEX(Commerciaux!$D$2:$D$3000,MATCH(G15,Commerciaux!$A$2:$A$3000,0)),"") | I15: Ventes terrain | J15: Conclu gagné | K15: =IFERROR(INDEX(Paramètres!$B$7:$B$13,MATCH(J15,Paramètres!$A$7:$A$13,0)),"") | L15: 310000 | M15: =IF(OR(L15="",K15=""),"",L15*K15) | N15: =IFERROR(INDEX(Paramètres!$C$7:$C$13,MATCH(J15,Paramètres!$A$7:$A$13,0)),"") | O15: Affaire existante | P15: P005 | Q15: =IFERROR(INDEX(Produits!$C$2:$C$3000,MATCH(P15,Produits!$A$2:$A$3000,0)),"") | R15: 45992 | S15: 46101 | T15: 46101
A16: T015 | B16: Laurent-Perrier - Étuis gamme rosé | C16: E009 | D16: =IFERROR(INDEX(Entreprises!$B$2:$B$3000,MATCH(C16,Entreprises!$A$2:$A$3000,0)),"") | E16: C015 | F16: =IFERROR(INDEX(Contacts!$E$2:$E$3000,MATCH(E16,Contacts!$A$2:$A$3000,0)),"") | G16: U003 | H16: =IFERROR(INDEX(Commerciaux!$D$2:$D$3000,MATCH(G16,Commerciaux!$A$2:$A$3000,0)),"") | I16: Ventes terrain | J16: Rendez-vous programmé | K16: =IFERROR(INDEX(Paramètres!$B$7:$B$13,MATCH(J16,Paramètres!$A$7:$A$13,0)),"") | L16: 85000 | M16: =IF(OR(L16="",K16=""),"",L16*K16) | N16: =IFERROR(INDEX(Paramètres!$C$7:$C$13,MATCH(J16,Paramètres!$A$7:$A$13,0)),"") | O16: Affaire existante | P16: P006 | Q16: =IFERROR(INDEX(Produits!$C$2:$C$3000,MATCH(P16,Produits!$A$2:$A$3000,0)),"") | R16: 46184 | S16: 46402 | U16: Atelier brief créatif
A17: T016 | B17: Vranken-Pommery - Coffrets premium 2027 | C17: E010 | D17: =IFERROR(INDEX(Entreprises!$B$2:$B$3000,MATCH(C17,Entreprises!$A$2:$A$3000,0)),"") | E17: C016 | F17: =IFERROR(INDEX(Contacts!$E$2:$E$3000,MATCH(E17,Contacts!$A$2:$A$3000,0)),"") | G17: U003 | H17: =IFERROR(INDEX(Commerciaux!$D$2:$D$3000,MATCH(G17,Commerciaux!$A$2:$A$3000,0)),"") | I17: Ventes terrain | J17: Décideur impliqué | K17: =IFERROR(INDEX(Paramètres!$B$7:$B$13,MATCH(J17,Paramètres!$A$7:$A$13,0)),"") | L17: 130000 | M17: =IF(OR(L17="",K17=""),"",L17*K17) | N17: =IFERROR(INDEX(Paramètres!$C$7:$C$13,MATCH(J17,Paramètres!$A$7:$A$13,0)),"") | O17: Nouvelle affaire | P17: P005 | Q17: =IFERROR(INDEX(Produits!$C$2:$C$3000,MATCH(P17,Produits!$A$2:$A$3000,0)),"") | R17: 45931 | S17: 46374 | U17: Remettre la proposition chiffrée avant le 20/10 | V17: Kartéa Luxe
A18: T017 | B18: Kronenbourg - Caisses carton en flux tendu | C18: E011 | D18: =IFERROR(INDEX(Entreprises!$B$2:$B$3000,MATCH(C18,Entreprises!$A$2:$A$3000,0)),"") | E18: C017 | F18: =IFERROR(INDEX(Contacts!$E$2:$E$3000,MATCH(E18,Contacts!$A$2:$A$3000,0)),"") | G18: U003 | H18: =IFERROR(INDEX(Commerciaux!$D$2:$D$3000,MATCH(G18,Commerciaux!$A$2:$A$3000,0)),"") | I18: Ventes terrain | J18: Présentation planifiée | K18: =IFERROR(INDEX(Paramètres!$B$7:$B$13,MATCH(J18,Paramètres!$A$7:$A$13,0)),"") | L18: 110000 | M18: =IF(OR(L18="",K18=""),"",L18*K18) | N18: =IFERROR(INDEX(Paramètres!$C$7:$C$13,MATCH(J18,Paramètres!$A$7:$A$13,0)),"") | O18: Affaire existante | P18: P007 | Q18: =IFERROR(INDEX(Produits!$C$2:$C$3000,MATCH(P18,Produits!$A$2:$A$3000,0)),"") | R18: 46261 | S18: 46367 | U18: Présenter l'offre révisée avec livraison en flux tendu | V18: Emballor Industries
A19: T018 | B19: Kronenbourg - Caisses carton 2026 | C19: E011 | D19: =IFERROR(INDEX(Entreprises!$B$2:$B$3000,MATCH(C19,Entreprises!$A$2:$A$3000,0)),"") | E19: C017 | F19: =IFERROR(INDEX(Contacts!$E$2:$E$3000,MATCH(E19,Contacts!$A$2:$A$3000,0)),"") | G19: U003 | H19: =IFERROR(INDEX(Commerciaux!$D$2:$D$3000,MATCH(G19,Commerciaux!$A$2:$A$3000,0)),"") | I19: Ventes terrain | J19: Conclu perdu | K19: =IFERROR(INDEX(Paramètres!$B$7:$B$13,MATCH(J19,Paramètres!$A$7:$A$13,0)),"") | L19: 140000 | M19: =IF(OR(L19="",K19=""),"",L19*K19) | N19: =IFERROR(INDEX(Paramètres!$C$7:$C$13,MATCH(J19,Paramètres!$A$7:$A$13,0)),"") | O19: Renouvellement | P19: P007 | Q19: =IFERROR(INDEX(Produits!$C$2:$C$3000,MATCH(P19,Produits!$A$2:$A$3000,0)),"") | R19: 45936 | S19: 46052 | T19: 46052 | V19: Emballor Industries | W19: Prix (écart d'environ 7 %)
A20: T019 | B20: Kronenbourg - Contrat de maintenance étiqueteuses | C20: E011 | D20: =IFERROR(INDEX(Entreprises!$B$2:$B$3000,MATCH(C20,Entreprises!$A$2:$A$3000,0)),"") | E20: C018 | F20: =IFERROR(INDEX(Contacts!$E$2:$E$3000,MATCH(E20,Contacts!$A$2:$A$3000,0)),"") | G20: U003 | H20: =IFERROR(INDEX(Commerciaux!$D$2:$D$3000,MATCH(G20,Commerciaux!$A$2:$A$3000,0)),"") | I20: Ventes terrain | J20: Conclu gagné | K20: =IFERROR(INDEX(Paramètres!$B$7:$B$13,MATCH(J20,Paramètres!$A$7:$A$13,0)),"") | L20: 19200 | M20: =IF(OR(L20="",K20=""),"",L20*K20) | N20: =IFERROR(INDEX(Paramètres!$C$7:$C$13,MATCH(J20,Paramètres!$A$7:$A$13,0)),"") | O20: Affaire existante | P20: P012 | Q20: =IFERROR(INDEX(Produits!$C$2:$C$3000,MATCH(P20,Produits!$A$2:$A$3000,0)),"") | R20: 45915 | S20: 45966 | T20: 45966
A21: T020 | B21: bioMérieux - Sérialisation kits export | C21: E012 | D21: =IFERROR(INDEX(Entreprises!$B$2:$B$3000,MATCH(C21,Entreprises!$A$2:$A$3000,0)),"") | E21: C020 | F21: =IFERROR(INDEX(Contacts!$E$2:$E$3000,MATCH(E21,Contacts!$A$2:$A$3000,0)),"") | G21: U004 | H21: =IFERROR(INDEX(Commerciaux!$D$2:$D$3000,MATCH(G21,Commerciaux!$A$2:$A$3000,0)),"") | I21: Ventes terrain | J21: Décideur impliqué | K21: =IFERROR(INDEX(Paramètres!$B$7:$B$13,MATCH(J21,Paramètres!$A$7:$A$13,0)),"") | L21: 210000 | M21: =IF(OR(L21="",K21=""),"",L21*K21) | N21: =IFERROR(INDEX(Paramètres!$C$7:$C$13,MATCH(J21,Paramètres!$A$7:$A$13,0)),"") | O21: Nouvelle affaire | P21: P009 | Q21: =IFERROR(INDEX(Produits!$C$2:$C$3000,MATCH(P21,Produits!$A$2:$A$3000,0)),"") | R21: 46091 | S21: 46374 | U21: Démonstration DataMatrix sur ligne pilote | V21: Kartéa Pharma Pack
A22: T021 | B22: bioMérieux - Étuis kits diagnostic 2026 | C22: E012 | D22: =IFERROR(INDEX(Entreprises!$B$2:$B$3000,MATCH(C22,Entreprises!$A$2:$A$3000,0)),"") | E22: C019 | F22: =IFERROR(INDEX(Contacts!$E$2:$E$3000,MATCH(E22,Contacts!$A$2:$A$3000,0)),"") | G22: U004 | H22: =IFERROR(INDEX(Commerciaux!$D$2:$D$3000,MATCH(G22,Commerciaux!$A$2:$A$3000,0)),"") | I22: Ventes terrain | J22: Conclu gagné | K22: =IFERROR(INDEX(Paramètres!$B$7:$B$13,MATCH(J22,Paramètres!$A$7:$A$13,0)),"") | L22: 165000 | M22: =IF(OR(L22="",K22=""),"",L22*K22) | N22: =IFERROR(INDEX(Paramètres!$C$7:$C$13,MATCH(J22,Paramètres!$A$7:$A$13,0)),"") | O22: Renouvellement | P22: P001 | Q22: =IFERROR(INDEX(Produits!$C$2:$C$3000,MATCH(P22,Produits!$A$2:$A$3000,0)),"") | R22: 45922 | S22: 46001 | T22: 46001
A23: T022 | B23: Boiron - Étuis carton recyclé 2027-2028 | C23: E013 | D23: =IFERROR(INDEX(Entreprises!$B$2:$B$3000,MATCH(C23,Entreprises!$A$2:$A$3000,0)),"") | E23: C021 | F23: =IFERROR(INDEX(Contacts!$E$2:$E$3000,MATCH(E23,Contacts!$A$2:$A$3000,0)),"") | G23: U004 | H23: =IFERROR(INDEX(Commerciaux!$D$2:$D$3000,MATCH(G23,Commerciaux!$A$2:$A$3000,0)),"") | I23: Ventes terrain | J23: Contrat envoyé | K23: =IFERROR(INDEX(Paramètres!$B$7:$B$13,MATCH(J23,Paramètres!$A$7:$A$13,0)),"") | L23: 155000 | M23: =IF(OR(L23="",K23=""),"",L23*K23) | N23: =IFERROR(INDEX(Paramètres!$C$7:$C$13,MATCH(J23,Paramètres!$A$7:$A$13,0)),"") | O23: Renouvellement | P23: P008 | Q23: =IFERROR(INDEX(Produits!$C$2:$C$3000,MATCH(P23,Produits!$A$2:$A$3000,0)),"") | R23: 46203 | S23: 46332 | U23: Signature prévue le 26/10
A24: T023 | B24: SEB - Calages carton sans polystyrène | C24: E014 | D24: =IFERROR(INDEX(Entreprises!$B$2:$B$3000,MATCH(C24,Entreprises!$A$2:$A$3000,0)),"") | E24: C024 | F24: =IFERROR(INDEX(Contacts!$E$2:$E$3000,MATCH(E24,Contacts!$A$2:$A$3000,0)),"") | G24: U004 | H24: =IFERROR(INDEX(Commerciaux!$D$2:$D$3000,MATCH(G24,Commerciaux!$A$2:$A$3000,0)),"") | I24: Ventes terrain | J24: Contrat envoyé | K24: =IFERROR(INDEX(Paramètres!$B$7:$B$13,MATCH(J24,Paramètres!$A$7:$A$13,0)),"") | L24: 230000 | M24: =IF(OR(L24="",K24=""),"",L24*K24) | N24: =IFERROR(INDEX(Paramètres!$C$7:$C$13,MATCH(J24,Paramètres!$A$7:$A$13,0)),"") | O24: Nouvelle affaire | P24: P008 | Q24: =IFERROR(INDEX(Produits!$C$2:$C$3000,MATCH(P24,Produits!$A$2:$A$3000,0)),"") | R24: 46127 | S24: 46353 | U24: Négocier le devis d'industrialisation | V24: Emballor Industries
A25: T024 | B25: SEB - Caisses carton 2026 | C25: E014 | D25: =IFERROR(INDEX(Entreprises!$B$2:$B$3000,MATCH(C25,Entreprises!$A$2:$A$3000,0)),"") | E25: C024 | F25: =IFERROR(INDEX(Contacts!$E$2:$E$3000,MATCH(E25,Contacts!$A$2:$A$3000,0)),"") | G25: U004 | H25: =IFERROR(INDEX(Commerciaux!$D$2:$D$3000,MATCH(G25,Commerciaux!$A$2:$A$3000,0)),"") | I25: Ventes terrain | J25: Conclu gagné | K25: =IFERROR(INDEX(Paramètres!$B$7:$B$13,MATCH(J25,Paramètres!$A$7:$A$13,0)),"") | L25: 205000 | M25: =IF(OR(L25="",K25=""),"",L25*K25) | N25: =IFERROR(INDEX(Paramètres!$C$7:$C$13,MATCH(J25,Paramètres!$A$7:$A$13,0)),"") | O25: Renouvellement | P25: P007 | Q25: =IFERROR(INDEX(Produits!$C$2:$C$3000,MATCH(P25,Produits!$A$2:$A$3000,0)),"") | R25: 45931 | S25: 46009 | T25: 46009
A26: T025 | B26: Vicat - Étiquettes résistantes pour sacs | C26: E015 | D26: =IFERROR(INDEX(Entreprises!$B$2:$B$3000,MATCH(C26,Entreprises!$A$2:$A$3000,0)),"") | E26: C025 | F26: =IFERROR(INDEX(Contacts!$E$2:$E$3000,MATCH(E26,Contacts!$A$2:$A$3000,0)),"") | G26: U004 | H26: =IFERROR(INDEX(Commerciaux!$D$2:$D$3000,MATCH(G26,Commerciaux!$A$2:$A$3000,0)),"") | I26: Ventes terrain | J26: Rendez-vous programmé | K26: =IFERROR(INDEX(Paramètres!$B$7:$B$13,MATCH(J26,Paramètres!$A$7:$A$13,0)),"") | L26: 45000 | M26: =IF(OR(L26="",K26=""),"",L26*K26) | N26: =IFERROR(INDEX(Paramètres!$C$7:$C$13,MATCH(J26,Paramètres!$A$7:$A$13,0)),"") | O26: Nouvelle affaire | P26: P003 | Q26: =IFERROR(INDEX(Produits!$C$2:$C$3000,MATCH(P26,Produits!$A$2:$A$3000,0)),"") | R26: 46275 | S26: 46477 | U26: Visio de qualification le 29/10
A27: T026 | B27: Virbac - Sérialisation nouvelle ligne | C27: E016 | D27: =IFERROR(INDEX(Entreprises!$B$2:$B$3000,MATCH(C27,Entreprises!$A$2:$A$3000,0)),"") | E27: C026 | F27: =IFERROR(INDEX(Contacts!$E$2:$E$3000,MATCH(E27,Contacts!$A$2:$A$3000,0)),"") | G27: U004 | H27: =IFERROR(INDEX(Commerciaux!$D$2:$D$3000,MATCH(G27,Commerciaux!$A$2:$A$3000,0)),"") | I27: Ventes terrain | J27: Présentation planifiée | K27: =IFERROR(INDEX(Paramètres!$B$7:$B$13,MATCH(J27,Paramètres!$A$7:$A$13,0)),"") | L27: 185000 | M27: =IF(OR(L27="",K27=""),"",L27*K27) | N27: =IFERROR(INDEX(Paramètres!$C$7:$C$13,MATCH(J27,Paramètres!$A$7:$A$13,0)),"") | O27: Nouvelle affaire | P27: P009 | Q27: =IFERROR(INDEX(Produits!$C$2:$C$3000,MATCH(P27,Produits!$A$2:$A$3000,0)),"") | R27: 45994 | S27: 46416 | U27: Présenter l'organisation SAV Sud-Est et une référence client | V27: Kartéa Pharma Pack
A28: T027 | B28: Rémy Cointreau - Coffret réutilisable premium | C28: E017 | D28: =IFERROR(INDEX(Entreprises!$B$2:$B$3000,MATCH(C28,Entreprises!$A$2:$A$3000,0)),"") | E28: C028 | F28: =IFERROR(INDEX(Contacts!$E$2:$E$3000,MATCH(E28,Contacts!$A$2:$A$3000,0)),"") | G28: U005 | H28: =IFERROR(INDEX(Commerciaux!$D$2:$D$3000,MATCH(G28,Commerciaux!$A$2:$A$3000,0)),"") | I28: Ventes terrain | J28: Qualifié pour achat | K28: =IFERROR(INDEX(Paramètres!$B$7:$B$13,MATCH(J28,Paramètres!$A$7:$A$13,0)),"") | L28: 175000 | M28: =IF(OR(L28="",K28=""),"",L28*K28) | N28: =IFERROR(INDEX(Paramètres!$C$7:$C$13,MATCH(J28,Paramètres!$A$7:$A$13,0)),"") | O28: Nouvelle affaire | P28: P005 | Q28: =IFERROR(INDEX(Produits!$C$2:$C$3000,MATCH(P28,Produits!$A$2:$A$3000,0)),"") | R28: 46266 | S28: 46458 | U28: Présenter un concept de coffret réutilisable | V28: Kartéa Luxe
A29: T028 | B29: Rémy Cointreau - Étuis saison 2026 | C29: E017 | D29: =IFERROR(INDEX(Entreprises!$B$2:$B$3000,MATCH(C29,Entreprises!$A$2:$A$3000,0)),"") | E29: C027 | F29: =IFERROR(INDEX(Contacts!$E$2:$E$3000,MATCH(E29,Contacts!$A$2:$A$3000,0)),"") | G29: U005 | H29: =IFERROR(INDEX(Commerciaux!$D$2:$D$3000,MATCH(G29,Commerciaux!$A$2:$A$3000,0)),"") | I29: Ventes terrain | J29: Conclu gagné | K29: =IFERROR(INDEX(Paramètres!$B$7:$B$13,MATCH(J29,Paramètres!$A$7:$A$13,0)),"") | L29: 260000 | M29: =IF(OR(L29="",K29=""),"",L29*K29) | N29: =IFERROR(INDEX(Paramètres!$C$7:$C$13,MATCH(J29,Paramètres!$A$7:$A$13,0)),"") | O29: Renouvellement | P29: P006 | Q29: =IFERROR(INDEX(Produits!$C$2:$C$3000,MATCH(P29,Produits!$A$2:$A$3000,0)),"") | R29: 45978 | S29: 46080 | T29: 46080
A30: T029 | B30: Maison Ferrand - Étuis édition limitée | C30: E018 | D30: =IFERROR(INDEX(Entreprises!$B$2:$B$3000,MATCH(C30,Entreprises!$A$2:$A$3000,0)),"") | E30: C029 | F30: =IFERROR(INDEX(Contacts!$E$2:$E$3000,MATCH(E30,Contacts!$A$2:$A$3000,0)),"") | G30: U005 | H30: =IFERROR(INDEX(Commerciaux!$D$2:$D$3000,MATCH(G30,Commerciaux!$A$2:$A$3000,0)),"") | I30: Ventes terrain | J30: Contrat envoyé | K30: =IFERROR(INDEX(Paramètres!$B$7:$B$13,MATCH(J30,Paramètres!$A$7:$A$13,0)),"") | L30: 24000 | M30: =IF(OR(L30="",K30=""),"",L30*K30) | N30: =IFERROR(INDEX(Paramètres!$C$7:$C$13,MATCH(J30,Paramètres!$A$7:$A$13,0)),"") | O30: Affaire existante | P30: P006 | Q30: =IFERROR(INDEX(Produits!$C$2:$C$3000,MATCH(P30,Produits!$A$2:$A$3000,0)),"") | R30: 46254 | S30: 46318 | U30: Valider le BAT
A31: T030 | B31: Pierre Fabre - Renouvellement contrat étuis 2027 | C31: E019 | D31: =IFERROR(INDEX(Entreprises!$B$2:$B$3000,MATCH(C31,Entreprises!$A$2:$A$3000,0)),"") | E31: C030 | F31: =IFERROR(INDEX(Contacts!$E$2:$E$3000,MATCH(E31,Contacts!$A$2:$A$3000,0)),"") | G31: U005 | H31: =IFERROR(INDEX(Commerciaux!$D$2:$D$3000,MATCH(G31,Commerciaux!$A$2:$A$3000,0)),"") | I31: Ventes terrain | J31: Décideur impliqué | K31: =IFERROR(INDEX(Paramètres!$B$7:$B$13,MATCH(J31,Paramètres!$A$7:$A$13,0)),"") | L31: 290000 | M31: =IF(OR(L31="",K31=""),"",L31*K31) | N31: =IFERROR(INDEX(Paramètres!$C$7:$C$13,MATCH(J31,Paramètres!$A$7:$A$13,0)),"") | O31: Renouvellement | P31: P001 | Q31: =IFERROR(INDEX(Produits!$C$2:$C$3000,MATCH(P31,Produits!$A$2:$A$3000,0)),"") | R31: 46204 | S31: 46418 | U31: Clôturer le ticket qualité avant de présenter la proposition | V31: Kartéa Pharma Pack
A32: T031 | B32: Andros - Emballages nouvelle gamme | C32: E020 | D32: =IFERROR(INDEX(Entreprises!$B$2:$B$3000,MATCH(C32,Entreprises!$A$2:$A$3000,0)),"") | E32: C032 | F32: =IFERROR(INDEX(Contacts!$E$2:$E$3000,MATCH(E32,Contacts!$A$2:$A$3000,0)),"") | G32: U005 | H32: =IFERROR(INDEX(Commerciaux!$D$2:$D$3000,MATCH(G32,Commerciaux!$A$2:$A$3000,0)),"") | I32: Ventes terrain | J32: Présentation planifiée | K32: =IFERROR(INDEX(Paramètres!$B$7:$B$13,MATCH(J32,Paramètres!$A$7:$A$13,0)),"") | L32: 135000 | M32: =IF(OR(L32="",K32=""),"",L32*K32) | N32: =IFERROR(INDEX(Paramètres!$C$7:$C$13,MATCH(J32,Paramètres!$A$7:$A$13,0)),"") | O32: Nouvelle affaire | P32: P007 | Q32: =IFERROR(INDEX(Produits!$C$2:$C$3000,MATCH(P32,Produits!$A$2:$A$3000,0)),"") | R32: 46083 | S32: 46360 | U32: Présenter l'offre avec scénario de montée en charge | V32: Emballor Industries
A33: T032 | B33: Volterra - Emballages éco-conçus deux usines | C33: E021 | D33: =IFERROR(INDEX(Entreprises!$B$2:$B$3000,MATCH(C33,Entreprises!$A$2:$A$3000,0)),"") | E33: C033 | F33: =IFERROR(INDEX(Contacts!$E$2:$E$3000,MATCH(E33,Contacts!$A$2:$A$3000,0)),"") | G33: U005 | H33: =IFERROR(INDEX(Commerciaux!$D$2:$D$3000,MATCH(G33,Commerciaux!$A$2:$A$3000,0)),"") | I33: Ventes terrain | J33: Décideur impliqué | K33: =IFERROR(INDEX(Paramètres!$B$7:$B$13,MATCH(J33,Paramètres!$A$7:$A$13,0)),"") | L33: 260000 | M33: =IF(OR(L33="",K33=""),"",L33*K33) | N33: =IFERROR(INDEX(Paramètres!$C$7:$C$13,MATCH(J33,Paramètres!$A$7:$A$13,0)),"") | O33: Affaire existante | P33: P008 | Q33: =IFERROR(INDEX(Produits!$C$2:$C$3000,MATCH(P33,Produits!$A$2:$A$3000,0)),"") | R33: 46154 | S33: 46374 | U33: Préparer le dossier du comité de décision | V33: Emballor Industries
A34: T033 | B34: Volterra - Étiqueteuse automatique site de Poitiers | C34: E021 | D34: =IFERROR(INDEX(Entreprises!$B$2:$B$3000,MATCH(C34,Entreprises!$A$2:$A$3000,0)),"") | E34: C034 | F34: =IFERROR(INDEX(Contacts!$E$2:$E$3000,MATCH(E34,Contacts!$A$2:$A$3000,0)),"") | G34: U005 | H34: =IFERROR(INDEX(Commerciaux!$D$2:$D$3000,MATCH(G34,Commerciaux!$A$2:$A$3000,0)),"") | I34: Ventes terrain | J34: Conclu gagné | K34: =IFERROR(INDEX(Paramètres!$B$7:$B$13,MATCH(J34,Paramètres!$A$7:$A$13,0)),"") | L34: 51600 | M34: =IF(OR(L34="",K34=""),"",L34*K34) | N34: =IFERROR(INDEX(Paramètres!$C$7:$C$13,MATCH(J34,Paramètres!$A$7:$A$13,0)),"") | O34: Nouvelle affaire | P34: P010 | Q34: =IFERROR(INDEX(Produits!$C$2:$C$3000,MATCH(P34,Produits!$A$2:$A$3000,0)),"") | R34: 45719 | S34: 45820 | T34: 45820
A35: T034 | B35: Sanofi - Sérialisation site supplémentaire | C35: E022 | D35: =IFERROR(INDEX(Entreprises!$B$2:$B$3000,MATCH(C35,Entreprises!$A$2:$A$3000,0)),"") | E35: C036 | F35: =IFERROR(INDEX(Contacts!$E$2:$E$3000,MATCH(E35,Contacts!$A$2:$A$3000,0)),"") | G35: U006 | H35: =IFERROR(INDEX(Commerciaux!$D$2:$D$3000,MATCH(G35,Commerciaux!$A$2:$A$3000,0)),"") | I35: Ventes terrain | J35: Décideur impliqué | K35: =IFERROR(INDEX(Paramètres!$B$7:$B$13,MATCH(J35,Paramètres!$A$7:$A$13,0)),"") | L35: 340000 | M35: =IF(OR(L35="",K35=""),"",L35*K35) | N35: =IFERROR(INDEX(Paramètres!$C$7:$C$13,MATCH(J35,Paramètres!$A$7:$A$13,0)),"") | O35: Nouvelle affaire | P35: P009 | Q35: =IFERROR(INDEX(Produits!$C$2:$C$3000,MATCH(P35,Produits!$A$2:$A$3000,0)),"") | R35: 46055 | S35: 46371 | U35: Comité de pilotage mi-octobre | V35: Kartéa Pharma Pack
A36: T035 | B36: Sanofi - Renouvellement accord-cadre étuis et notices 2027 | C36: E022 | D36: =IFERROR(INDEX(Entreprises!$B$2:$B$3000,MATCH(C36,Entreprises!$A$2:$A$3000,0)),"") | E36: C035 | F36: =IFERROR(INDEX(Contacts!$E$2:$E$3000,MATCH(E36,Contacts!$A$2:$A$3000,0)),"") | G36: U006 | H36: =IFERROR(INDEX(Commerciaux!$D$2:$D$3000,MATCH(G36,Commerciaux!$A$2:$A$3000,0)),"") | I36: Ventes terrain | J36: Qualifié pour achat | K36: =IFERROR(INDEX(Paramètres!$B$7:$B$13,MATCH(J36,Paramètres!$A$7:$A$13,0)),"") | L36: 1150000 | M36: =IF(OR(L36="",K36=""),"",L36*K36) | N36: =IFERROR(INDEX(Paramètres!$C$7:$C$13,MATCH(J36,Paramètres!$A$7:$A$13,0)),"") | O36: Renouvellement | P36: P001 | Q36: =IFERROR(INDEX(Produits!$C$2:$C$3000,MATCH(P36,Produits!$A$2:$A$3000,0)),"") | R36: 46279 | S36: 46477 | U36: Préparer le dossier de candidature | V36: Kartéa Pharma Pack
A37: T036 | B37: Sanofi - Notices pharmaceutiques 2026 | C37: E022 | D37: =IFERROR(INDEX(Entreprises!$B$2:$B$3000,MATCH(C37,Entreprises!$A$2:$A$3000,0)),"") | E37: C035 | F37: =IFERROR(INDEX(Contacts!$E$2:$E$3000,MATCH(E37,Contacts!$A$2:$A$3000,0)),"") | G37: U006 | H37: =IFERROR(INDEX(Commerciaux!$D$2:$D$3000,MATCH(G37,Commerciaux!$A$2:$A$3000,0)),"") | I37: Ventes terrain | J37: Conclu gagné | K37: =IFERROR(INDEX(Paramètres!$B$7:$B$13,MATCH(J37,Paramètres!$A$7:$A$13,0)),"") | L37: 420000 | M37: =IF(OR(L37="",K37=""),"",L37*K37) | N37: =IFERROR(INDEX(Paramètres!$C$7:$C$13,MATCH(J37,Paramètres!$A$7:$A$13,0)),"") | O37: Renouvellement | P37: P002 | Q37: =IFERROR(INDEX(Produits!$C$2:$C$3000,MATCH(P37,Produits!$A$2:$A$3000,0)),"") | R37: 45901 | S37: 45989 | T37: 45989
A38: T037 | B38: Ipsen - Étiquettes d'inviolabilité gamme complète | C38: E023 | D38: =IFERROR(INDEX(Entreprises!$B$2:$B$3000,MATCH(C38,Entreprises!$A$2:$A$3000,0)),"") | E38: C037 | F38: =IFERROR(INDEX(Contacts!$E$2:$E$3000,MATCH(E38,Contacts!$A$2:$A$3000,0)),"") | G38: U006 | H38: =IFERROR(INDEX(Commerciaux!$D$2:$D$3000,MATCH(G38,Commerciaux!$A$2:$A$3000,0)),"") | I38: Ventes terrain | J38: Contrat envoyé | K38: =IFERROR(INDEX(Paramètres!$B$7:$B$13,MATCH(J38,Paramètres!$A$7:$A$13,0)),"") | L38: 125000 | M38: =IF(OR(L38="",K38=""),"",L38*K38) | N38: =IFERROR(INDEX(Paramètres!$C$7:$C$13,MATCH(J38,Paramètres!$A$7:$A$13,0)),"") | O38: Affaire existante | P38: P004 | Q38: =IFERROR(INDEX(Produits!$C$2:$C$3000,MATCH(P38,Produits!$A$2:$A$3000,0)),"") | R38: 46132 | S38: 46339 | U38: Revue du contrat avec le service juridique
A39: T038 | B39: Servier - Appel d'offres notices et étuis | C39: E024 | D39: =IFERROR(INDEX(Entreprises!$B$2:$B$3000,MATCH(C39,Entreprises!$A$2:$A$3000,0)),"") | E39: C039 | F39: =IFERROR(INDEX(Contacts!$E$2:$E$3000,MATCH(E39,Contacts!$A$2:$A$3000,0)),"") | G39: U006 | H39: =IFERROR(INDEX(Commerciaux!$D$2:$D$3000,MATCH(G39,Commerciaux!$A$2:$A$3000,0)),"") | I39: Ventes terrain | J39: Présentation planifiée | K39: =IFERROR(INDEX(Paramètres!$B$7:$B$13,MATCH(J39,Paramètres!$A$7:$A$13,0)),"") | L39: 480000 | M39: =IF(OR(L39="",K39=""),"",L39*K39) | N39: =IFERROR(INDEX(Paramètres!$C$7:$C$13,MATCH(J39,Paramètres!$A$7:$A$13,0)),"") | O39: Nouvelle affaire | P39: P002 | Q39: =IFERROR(INDEX(Produits!$C$2:$C$3000,MATCH(P39,Produits!$A$2:$A$3000,0)),"") | R39: 45944 | S39: 46444 | U39: Préparer la soutenance du 28/10 | V39: Kartéa Pharma Pack
A40: T039 | B40: Pernod Ricard - Éco-conception des coffrets 2027 | C40: E025 | D40: =IFERROR(INDEX(Entreprises!$B$2:$B$3000,MATCH(C40,Entreprises!$A$2:$A$3000,0)),"") | E40: C041 | F40: =IFERROR(INDEX(Contacts!$E$2:$E$3000,MATCH(E40,Contacts!$A$2:$A$3000,0)),"") | G40: U007 | H40: =IFERROR(INDEX(Commerciaux!$D$2:$D$3000,MATCH(G40,Commerciaux!$A$2:$A$3000,0)),"") | I40: Ventes terrain | J40: Décideur impliqué | K40: =IFERROR(INDEX(Paramètres!$B$7:$B$13,MATCH(J40,Paramètres!$A$7:$A$13,0)),"") | L40: 420000 | M40: =IF(OR(L40="",K40=""),"",L40*K40) | N40: =IFERROR(INDEX(Paramètres!$C$7:$C$13,MATCH(J40,Paramètres!$A$7:$A$13,0)),"") | O40: Affaire existante | P40: P005 | Q40: =IFERROR(INDEX(Produits!$C$2:$C$3000,MATCH(P40,Produits!$A$2:$A$3000,0)),"") | R40: 46146 | S40: 46374 | U40: Transmettre les analyses de cycle de vie | V40: Kartéa Luxe
A41: T040 | B41: Pernod Ricard - Étuis spiritueux 2026 | C41: E025 | D41: =IFERROR(INDEX(Entreprises!$B$2:$B$3000,MATCH(C41,Entreprises!$A$2:$A$3000,0)),"") | E41: C040 | F41: =IFERROR(INDEX(Contacts!$E$2:$E$3000,MATCH(E41,Contacts!$A$2:$A$3000,0)),"") | G41: U007 | H41: =IFERROR(INDEX(Commerciaux!$D$2:$D$3000,MATCH(G41,Commerciaux!$A$2:$A$3000,0)),"") | I41: Ventes terrain | J41: Conclu gagné | K41: =IFERROR(INDEX(Paramètres!$B$7:$B$13,MATCH(J41,Paramètres!$A$7:$A$13,0)),"") | L41: 610000 | M41: =IF(OR(L41="",K41=""),"",L41*K41) | N41: =IFERROR(INDEX(Paramètres!$C$7:$C$13,MATCH(J41,Paramètres!$A$7:$A$13,0)),"") | O41: Renouvellement | P41: P006 | Q41: =IFERROR(INDEX(Produits!$C$2:$C$3000,MATCH(P41,Produits!$A$2:$A$3000,0)),"") | R41: 45887 | S41: 45960 | T41: 45960
A42: T041 | B42: Danone - Caisses carton recyclé | C42: E026 | D42: =IFERROR(INDEX(Entreprises!$B$2:$B$3000,MATCH(C42,Entreprises!$A$2:$A$3000,0)),"") | E42: C042 | F42: =IFERROR(INDEX(Contacts!$E$2:$E$3000,MATCH(E42,Contacts!$A$2:$A$3000,0)),"") | G42: U007 | H42: =IFERROR(INDEX(Commerciaux!$D$2:$D$3000,MATCH(G42,Commerciaux!$A$2:$A$3000,0)),"") | I42: Ventes terrain | J42: Qualifié pour achat | K42: =IFERROR(INDEX(Paramètres!$B$7:$B$13,MATCH(J42,Paramètres!$A$7:$A$13,0)),"") | L42: 380000 | M42: =IF(OR(L42="",K42=""),"",L42*K42) | N42: =IFERROR(INDEX(Paramètres!$C$7:$C$13,MATCH(J42,Paramètres!$A$7:$A$13,0)),"") | O42: Affaire existante | P42: P007 | Q42: =IFERROR(INDEX(Produits!$C$2:$C$3000,MATCH(P42,Produits!$A$2:$A$3000,0)),"") | R42: 46237 | S42: 46430 | U42: Atelier technique en octobre | V42: Emballor Industries
A43: T042 | B43: L'Oréal - Coffrets de fêtes 2027 | C43: E027 | D43: =IFERROR(INDEX(Entreprises!$B$2:$B$3000,MATCH(C43,Entreprises!$A$2:$A$3000,0)),"") | E43: C044 | F43: =IFERROR(INDEX(Contacts!$E$2:$E$3000,MATCH(E43,Contacts!$A$2:$A$3000,0)),"") | G43: U007 | H43: =IFERROR(INDEX(Commerciaux!$D$2:$D$3000,MATCH(G43,Commerciaux!$A$2:$A$3000,0)),"") | I43: Ventes terrain | J43: Présentation planifiée | K43: =IFERROR(INDEX(Paramètres!$B$7:$B$13,MATCH(J43,Paramètres!$A$7:$A$13,0)),"") | L43: 520000 | M43: =IF(OR(L43="",K43=""),"",L43*K43) | N43: =IFERROR(INDEX(Paramètres!$C$7:$C$13,MATCH(J43,Paramètres!$A$7:$A$13,0)),"") | O43: Affaire existante | P43: P005 | Q43: =IFERROR(INDEX(Produits!$C$2:$C$3000,MATCH(P43,Produits!$A$2:$A$3000,0)),"") | R43: 46218 | S43: 46409 | U43: Présenter les concepts le 26/10 | V43: Cartonnages Vauclair
A44: T043 | B44: L'Oréal - Coffrets de fêtes 2026 | C44: E027 | D44: =IFERROR(INDEX(Entreprises!$B$2:$B$3000,MATCH(C44,Entreprises!$A$2:$A$3000,0)),"") | E44: C044 | F44: =IFERROR(INDEX(Contacts!$E$2:$E$3000,MATCH(E44,Contacts!$A$2:$A$3000,0)),"") | G44: U007 | H44: =IFERROR(INDEX(Commerciaux!$D$2:$D$3000,MATCH(G44,Commerciaux!$A$2:$A$3000,0)),"") | I44: Ventes terrain | J44: Conclu gagné | K44: =IFERROR(INDEX(Paramètres!$B$7:$B$13,MATCH(J44,Paramètres!$A$7:$A$13,0)),"") | L44: 495000 | M44: =IF(OR(L44="",K44=""),"",L44*K44) | N44: =IFERROR(INDEX(Paramètres!$C$7:$C$13,MATCH(J44,Paramètres!$A$7:$A$13,0)),"") | O44: Affaire existante | P44: P005 | Q44: =IFERROR(INDEX(Produits!$C$2:$C$3000,MATCH(P44,Produits!$A$2:$A$3000,0)),"") | R44: 45950 | S44: 46063 | T44: 46063
A45: T044 | B45: Savencia - Étiquettes gamme export | C45: E028 | D45: =IFERROR(INDEX(Entreprises!$B$2:$B$3000,MATCH(C45,Entreprises!$A$2:$A$3000,0)),"") | E45: C047 | F45: =IFERROR(INDEX(Contacts!$E$2:$E$3000,MATCH(E45,Contacts!$A$2:$A$3000,0)),"") | G45: U007 | H45: =IFERROR(INDEX(Commerciaux!$D$2:$D$3000,MATCH(G45,Commerciaux!$A$2:$A$3000,0)),"") | I45: Ventes terrain | J45: Contrat envoyé | K45: =IFERROR(INDEX(Paramètres!$B$7:$B$13,MATCH(J45,Paramètres!$A$7:$A$13,0)),"") | L45: 68000 | M45: =IF(OR(L45="",K45=""),"",L45*K45) | N45: =IFERROR(INDEX(Paramètres!$C$7:$C$13,MATCH(J45,Paramètres!$A$7:$A$13,0)),"") | O45: Nouvelle affaire | P45: P003 | Q45: =IFERROR(INDEX(Produits!$C$2:$C$3000,MATCH(P45,Produits!$A$2:$A$3000,0)),"") | R45: 46181 | S45: 46325 | U45: Finaliser le contrat (délais de paiement)
A46: T045 | B46: Saint-Gobain - Emballages de transport distribution | C46: E029 | D46: =IFERROR(INDEX(Entreprises!$B$2:$B$3000,MATCH(C46,Entreprises!$A$2:$A$3000,0)),"") | E46: C048 | F46: =IFERROR(INDEX(Contacts!$E$2:$E$3000,MATCH(E46,Contacts!$A$2:$A$3000,0)),"") | G46: U007 | H46: =IFERROR(INDEX(Commerciaux!$D$2:$D$3000,MATCH(G46,Commerciaux!$A$2:$A$3000,0)),"") | I46: Ventes terrain | J46: Rendez-vous programmé | K46: =IFERROR(INDEX(Paramètres!$B$7:$B$13,MATCH(J46,Paramètres!$A$7:$A$13,0)),"") | L46: 250000 | M46: =IF(OR(L46="",K46=""),"",L46*K46) | N46: =IFERROR(INDEX(Paramètres!$C$7:$C$13,MATCH(J46,Paramètres!$A$7:$A$13,0)),"") | O46: Nouvelle affaire | P46: P007 | Q46: =IFERROR(INDEX(Produits!$C$2:$C$3000,MATCH(P46,Produits!$A$2:$A$3000,0)),"") | R46: 46209 | S46: 46535 | U46: Rendez-vous de découverte le 03/11
A47: T046 | B47: Schneider Electric - Emballages sans plastique distribution | C47: E030 | D47: =IFERROR(INDEX(Entreprises!$B$2:$B$3000,MATCH(C47,Entreprises!$A$2:$A$3000,0)),"") | E47: C049 | F47: =IFERROR(INDEX(Contacts!$E$2:$E$3000,MATCH(E47,Contacts!$A$2:$A$3000,0)),"") | G47: U007 | H47: =IFERROR(INDEX(Commerciaux!$D$2:$D$3000,MATCH(G47,Commerciaux!$A$2:$A$3000,0)),"") | I47: Ventes terrain | J47: Décideur impliqué | K47: =IFERROR(INDEX(Paramètres!$B$7:$B$13,MATCH(J47,Paramètres!$A$7:$A$13,0)),"") | L47: 290000 | M47: =IF(OR(L47="",K47=""),"",L47*K47) | N47: =IFERROR(INDEX(Paramètres!$C$7:$C$13,MATCH(J47,Paramètres!$A$7:$A$13,0)),"") | O47: Nouvelle affaire | P47: P008 | Q47: =IFERROR(INDEX(Produits!$C$2:$C$3000,MATCH(P47,Produits!$A$2:$A$3000,0)),"") | R47: 46119 | S47: 46367 | U47: Comité de sélection le 30/10 | V47: Emballor Industries
A48: T047 | B48: Schneider Electric - Audit lignes de conditionnement | C48: E030 | D48: =IFERROR(INDEX(Entreprises!$B$2:$B$3000,MATCH(C48,Entreprises!$A$2:$A$3000,0)),"") | E48: C050 | F48: =IFERROR(INDEX(Contacts!$E$2:$E$3000,MATCH(E48,Contacts!$A$2:$A$3000,0)),"") | G48: U007 | H48: =IFERROR(INDEX(Commerciaux!$D$2:$D$3000,MATCH(G48,Commerciaux!$A$2:$A$3000,0)),"") | I48: Ventes terrain | J48: Conclu perdu | K48: =IFERROR(INDEX(Paramètres!$B$7:$B$13,MATCH(J48,Paramètres!$A$7:$A$13,0)),"") | L48: 14400 | M48: =IF(OR(L48="",K48=""),"",L48*K48) | N48: =IFERROR(INDEX(Paramètres!$C$7:$C$13,MATCH(J48,Paramètres!$A$7:$A$13,0)),"") | O48: Nouvelle affaire | P48: P013 | Q48: =IFERROR(INDEX(Produits!$C$2:$C$3000,MATCH(P48,Produits!$A$2:$A$3000,0)),"") | R48: 45810 | S48: 45918 | T48: 45918 | W48: Projet reporté par le client
A49: T048 | B49: Danone - Étiquettes promotionnelles 2025 | C49: E026 | D49: =IFERROR(INDEX(Entreprises!$B$2:$B$3000,MATCH(C49,Entreprises!$A$2:$A$3000,0)),"") | E49: C042 | F49: =IFERROR(INDEX(Contacts!$E$2:$E$3000,MATCH(E49,Contacts!$A$2:$A$3000,0)),"") | G49: U007 | H49: =IFERROR(INDEX(Commerciaux!$D$2:$D$3000,MATCH(G49,Commerciaux!$A$2:$A$3000,0)),"") | I49: Ventes terrain | J49: Conclu perdu | K49: =IFERROR(INDEX(Paramètres!$B$7:$B$13,MATCH(J49,Paramètres!$A$7:$A$13,0)),"") | L49: 85000 | M49: =IF(OR(L49="",K49=""),"",L49*K49) | N49: =IFERROR(INDEX(Paramètres!$C$7:$C$13,MATCH(J49,Paramètres!$A$7:$A$13,0)),"") | O49: Nouvelle affaire | P49: P003 | Q49: =IFERROR(INDEX(Produits!$C$2:$C$3000,MATCH(P49,Produits!$A$2:$A$3000,0)),"") | R49: 45698 | S49: 45799 | T49: 45799 | V49: Labelis Group | W49: Prix
A50: T049 | B50: Boiron - Notices 2025 | C50: E013 | D50: =IFERROR(INDEX(Entreprises!$B$2:$B$3000,MATCH(C50,Entreprises!$A$2:$A$3000,0)),"") | E50: C021 | F50: =IFERROR(INDEX(Contacts!$E$2:$E$3000,MATCH(E50,Contacts!$A$2:$A$3000,0)),"") | G50: U004 | H50: =IFERROR(INDEX(Commerciaux!$D$2:$D$3000,MATCH(G50,Commerciaux!$A$2:$A$3000,0)),"") | I50: Ventes terrain | J50: Conclu gagné | K50: =IFERROR(INDEX(Paramètres!$B$7:$B$13,MATCH(J50,Paramètres!$A$7:$A$13,0)),"") | L50: 58000 | M50: =IF(OR(L50="",K50=""),"",L50*K50) | N50: =IFERROR(INDEX(Paramètres!$C$7:$C$13,MATCH(J50,Paramètres!$A$7:$A$13,0)),"") | O50: Renouvellement | P50: P002 | Q50: =IFERROR(INDEX(Produits!$C$2:$C$3000,MATCH(P50,Produits!$A$2:$A$3000,0)),"") | R50: 45614 | S50: 45693 | T50: 45693
A51: T050 | B51: Laurent-Perrier - Caisses export 2026 | C51: E009 | D51: =IFERROR(INDEX(Entreprises!$B$2:$B$3000,MATCH(C51,Entreprises!$A$2:$A$3000,0)),"") | E51: C014 | F51: =IFERROR(INDEX(Contacts!$E$2:$E$3000,MATCH(E51,Contacts!$A$2:$A$3000,0)),"") | G51: U003 | H51: =IFERROR(INDEX(Commerciaux!$D$2:$D$3000,MATCH(G51,Commerciaux!$A$2:$A$3000,0)),"") | I51: Ventes terrain | J51: Conclu gagné | K51: =IFERROR(INDEX(Paramètres!$B$7:$B$13,MATCH(J51,Paramètres!$A$7:$A$13,0)),"") | L51: 46000 | M51: =IF(OR(L51="",K51=""),"",L51*K51) | N51: =IFERROR(INDEX(Paramètres!$C$7:$C$13,MATCH(J51,Paramètres!$A$7:$A$13,0)),"") | O51: Affaire existante | P51: P007 | Q51: =IFERROR(INDEX(Produits!$C$2:$C$3000,MATCH(P51,Produits!$A$2:$A$3000,0)),"") | R51: 45971 | S51: 46034 | T51: 46034

Sheet Activités
A1: ID activité | B1: Date | C1: Type d'activité | D1: ID entreprise | E1: Entreprise | F1: ID contact | G1: Contact | H1: ID commercial | I1: Commercial | J1: Objet | K1: Compte rendu / contenu | L1: Résultat | M1: ID transaction associée | N1: Prochaine action | O1: Échéance prochaine action | P1: Durée (min) | Q1: Autres participants client
A2: A0001 | B2: 45664 | C2: Visite terrain | D2: E009 | E2: =IFERROR(INDEX(Entreprises!$B$2:$B$3000,MATCH(D2,Entreprises!$A$2:$A$3000,0)),"") | F2: C014 | G2: =IFERROR(INDEX(Contacts!$E$2:$E$3000,MATCH(F2,Contacts!$A$2:$A$3000,0)),"") | H2: U003 | I2: =IFERROR(INDEX(Commerciaux!$D$2:$D$3000,MATCH(H2,Commerciaux!$A$2:$A$3000,0)),"") | J2: Visite de la ligne de conditionnement | K2: Visite du site avec Jean-Marc Lambert et l'équipe de production. Observation de la ligne de conditionnement ; points d'amélioration identifiés sur les changements de format. Intérêt exprimé pour le renouvellement des étuis de la gamme rosé. | L2: Positif | N2: Planifier une visite de site | O2: 45671 | P2: 75
A3: A0002 | B3: 45664 | C3: Note | D3: E011 | E3: =IFERROR(INDEX(Entreprises!$B$2:$B$3000,MATCH(D3,Entreprises!$A$2:$A$3000,0)),"") | F3: C018 | G3: =IFERROR(INDEX(Contacts!$E$2:$E$3000,MATCH(F3,Contacts!$A$2:$A$3000,0)),"") | H3: U003 | I3: =IFERROR(INDEX(Commerciaux!$D$2:$D$3000,MATCH(H3,Commerciaux!$A$2:$A$3000,0)),"") | J3: Préparation négociation | K3: Note interne : préparer un comparatif de prix face à Emballor Industries avant la prochaine négociation. | L3: Neutre
A4: A0003 | B4: 45667 | C4: Visite terrain | D4: E023 | E4: =IFERROR(INDEX(Entreprises!$B$2:$B$3000,MATCH(D4,Entreprises!$A$2:$A$3000,0)),"") | F4: C037 | G4: =IFERROR(INDEX(Contacts!$E$2:$E$3000,MATCH(F4,Contacts!$A$2:$A$3000,0)),"") | H4: U006 | I4: =IFERROR(INDEX(Commerciaux!$D$2:$D$3000,MATCH(H4,Commerciaux!$A$2:$A$3000,0)),"") | J4: Revue d'activité semestrielle | K4: Revue d'activité semestrielle avec Caroline Lefèvre. Satisfaction globale sur la qualité ; demande de visibilité sur l'évolution des prix des matières. Échange sur les étiquettes d'inviolabilité sur toute la gamme. | L4: Négatif | N4: Envoyer le devis | O4: 45678 | P4: 120
A5: A0004 | B5: 45672 | C5: Visite terrain | D5: E004 | E5: =IFERROR(INDEX(Entreprises!$B$2:$B$3000,MATCH(D5,Entreprises!$A$2:$A$3000,0)),"") | F5: C008 | G5: =IFERROR(INDEX(Contacts!$E$2:$E$3000,MATCH(F5,Contacts!$A$2:$A$3000,0)),"") | H5: U002 | I5: =IFERROR(INDEX(Commerciaux!$D$2:$D$3000,MATCH(H5,Commerciaux!$A$2:$A$3000,0)),"") | J5: Présentation des nouveautés 2025 | K5: Présentation des nouveautés 2025 à Hugo Perrin, notamment les emballages éco-conçus mono-matériau. Accueil favorable et demande d'échantillons. | L5: Positif | N5: Envoyer le devis | O5: 45684 | P5: 60
A6: A0005 | B6: 45678 | C6: Visite terrain | D6: E028 | E6: =IFERROR(INDEX(Entreprises!$B$2:$B$3000,MATCH(D6,Entreprises!$A$2:$A$3000,0)),"") | F6: C047 | G6: =IFERROR(INDEX(Contacts!$E$2:$E$3000,MATCH(F6,Contacts!$A$2:$A$3000,0)),"") | H6: U007 | I6: =IFERROR(INDEX(Commerciaux!$D$2:$D$3000,MATCH(H6,Commerciaux!$A$2:$A$3000,0)),"") | J6: Visite de suivi | K6: Visite de suivi avec Chloé Muller. Revue des commandes en cours et des prévisions du trimestre sur les étiquettes adhésives haute définition. Pas de difficulté particulière signalée. Chloé Muller évoque les étiquettes de la gamme export. | L6: Neutre | N6: Relancer pour obtenir un retour | O6: 45699 | P6: 75
A7: A0006 | B7: 45681 | C7: Visite terrain | D7: E028 | E7: =IFERROR(INDEX(Entreprises!$B$2:$B$3000,MATCH(D7,Entreprises!$A$2:$A$3000,0)),"") | F7: C047 | G7: =IFERROR(INDEX(Contacts!$E$2:$E$3000,MATCH(F7,Contacts!$A$2:$A$3000,0)),"") | H7: U007 | I7: =IFERROR(INDEX(Commerciaux!$D$2:$D$3000,MATCH(H7,Commerciaux!$A$2:$A$3000,0)),"") | J7: Présentation des nouveautés 2025 | K7: Présentation des nouveautés 2025 à Chloé Muller, notamment les caisses carton ondulé personnalisées. Accueil favorable et demande d'échantillons. | L7: Positif | P7: 90
A8: A0007 | B8: 45688 | C8: E-mail | D8: E002 | E8: =IFERROR(INDEX(Entreprises!$B$2:$B$3000,MATCH(D8,Entreprises!$A$2:$A$3000,0)),"") | F8: C003 | G8: =IFERROR(INDEX(Contacts!$E$2:$E$3000,MATCH(F8,Contacts!$A$2:$A$3000,0)),"") | H8: U002 | I8: =IFERROR(INDEX(Commerciaux!$D$2:$D$3000,MATCH(H8,Commerciaux!$A$2:$A$3000,0)),"") | J8: Envoi de fiche technique | K8: Envoi à Aurélie Vasseur de la fiche technique et des certificats des étiquettes adhésives haute définition. | L8: Neutre
A9: A0008 | B9: 45693 | C9: Appel | D9: E018 | E9: =IFERROR(INDEX(Entreprises!$B$2:$B$3000,MATCH(D9,Entreprises!$A$2:$A$3000,0)),"") | F9: C029 | G9: =IFERROR(INDEX(Contacts!$E$2:$E$3000,MATCH(F9,Contacts!$A$2:$A$3000,0)),"") | H9: U005 | I9: =IFERROR(INDEX(Commerciaux!$D$2:$D$3000,MATCH(H9,Commerciaux!$A$2:$A$3000,0)),"") | J9: Ajustement de commande | K9: Appel de Guillaume Petit pour ajuster les quantités de la prochaine commande d'étuis spiritueux luxe. Modification prise en compte. | L9: À relancer | P9: 20
A10: A0009 | B10: 45695 | C10: Appel | D10: E002 | E10: =IFERROR(INDEX(Entreprises!$B$2:$B$3000,MATCH(D10,Entreprises!$A$2:$A$3000,0)),"") | F10: C003 | G10: =IFERROR(INDEX(Contacts!$E$2:$E$3000,MATCH(F10,Contacts!$A$2:$A$3000,0)),"") | H10: U002 | I10: =IFERROR(INDEX(Commerciaux!$D$2:$D$3000,MATCH(H10,Commerciaux!$A$2:$A$3000,0)),"") | J10: Suivi de livraison | K10: Appel de suivi après la dernière livraison. Aurélie Vasseur confirme la conformité des lots reçus. | L10: À relancer | N10: Planifier une visite de site | O10: 45712 | P10: 30
A11: A0010 | B11: 45698 | C11: Réunion visio | D11: E008 | E11: =IFERROR(INDEX(Entreprises!$B$2:$B$3000,MATCH(D11,Entreprises!$A$2:$A$3000,0)),"") | F11: C012 | G11: =IFERROR(INDEX(Contacts!$E$2:$E$3000,MATCH(F11,Contacts!$A$2:$A$3000,0)),"") | H11: U003 | I11: =IFERROR(INDEX(Commerciaux!$D$2:$D$3000,MATCH(H11,Commerciaux!$A$2:$A$3000,0)),"") | J11: Cadrage du besoin | K11: Réunion Teams avec Marie-Laure Rivière pour cadrer le besoin concernant la consultation sur les étuis allégés 2027. Liste des prérequis techniques partagée. | L11: Neutre | N11: Planifier une visite de site | O11: 45712 | P11: 60
A12: A0011 | B12: 45701 | C12: Note | D12: E013 | E12: =IFERROR(INDEX(Entreprises!$B$2:$B$3000,MATCH(D12,Entreprises!$A$2:$A$3000,0)),"") | F12: C022 | G12: =IFERROR(INDEX(Contacts!$E$2:$E$3000,MATCH(F12,Contacts!$A$2:$A$3000,0)),"") | H12: U004 | I12: =IFERROR(INDEX(Commerciaux!$D$2:$D$3000,MATCH(H12,Commerciaux!$A$2:$A$3000,0)),"") | J12: Préparation négociation | K12: Note interne : préparer un comparatif de prix face à Kartéa Pharma Pack avant la prochaine négociation. | L12: Neutre
A13: A0012 | B13: 45702 | C13: Appel | D13: E019 | E13: =IFERROR(INDEX(Entreprises!$B$2:$B$3000,MATCH(D13,Entreprises!$A$2:$A$3000,0)),"") | F13: C030 | G13: =IFERROR(INDEX(Contacts!$E$2:$E$3000,MATCH(F13,Contacts!$A$2:$A$3000,0)),"") | H13: U005 | I13: =IFERROR(INDEX(Commerciaux!$D$2:$D$3000,MATCH(H13,Commerciaux!$A$2:$A$3000,0)),"") | J13: Suivi de livraison | K13: Appel de suivi après la dernière livraison. Sandrine Delmas confirme la conformité des lots reçus. | L13: Neutre | N13: Envoyer le devis | O13: 45723 | P13: 30
A14: A0013 | B14: 45715 | C14: Appel | D14: E018 | E14: =IFERROR(INDEX(Entreprises!$B$2:$B$3000,MATCH(D14,Entreprises!$A$2:$A$3000,0)),"") | F14: C029 | G14: =IFERROR(INDEX(Contacts!$E$2:$E$3000,MATCH(F14,Contacts!$A$2:$A$3000,0)),"") | H14: U005 | I14: =IFERROR(INDEX(Commerciaux!$D$2:$D$3000,MATCH(H14,Commerciaux!$A$2:$A$3000,0)),"") | J14: Suivi de livraison | K14: Appel de suivi après la dernière livraison. Guillaume Petit confirme la conformité des lots reçus. | L14: Neutre | P14: 30
A15: A0014 | B15: 45716 | C15: Réunion visio | D15: E017 | E15: =IFERROR(INDEX(Entreprises!$B$2:$B$3000,MATCH(D15,Entreprises!$A$2:$A$3000,0)),"") | F15: C028 | G15: =IFERROR(INDEX(Contacts!$E$2:$E$3000,MATCH(F15,Contacts!$A$2:$A$3000,0)),"") | H15: U005 | I15: =IFERROR(INDEX(Commerciaux!$D$2:$D$3000,MATCH(H15,Commerciaux!$A$2:$A$3000,0)),"") | J15: Cadrage du besoin | K15: Réunion Teams avec Romain Arnaud pour cadrer le besoin concernant le coffret réutilisable de la gamme premium. Liste des prérequis techniques partagée. | L15: Positif | N15: Transmettre des échantillons | O15: 45733 | P15: 45
A16: A0015 | B16: 45719 | C16: Visite terrain | D16: E004 | E16: =IFERROR(INDEX(Entreprises!$B$2:$B$3000,MATCH(D16,Entreprises!$A$2:$A$3000,0)),"") | F16: C008 | G16: =IFERROR(INDEX(Contacts!$E$2:$E$3000,MATCH(F16,Contacts!$A$2:$A$3000,0)),"") | H16: U002 | I16: =IFERROR(INDEX(Commerciaux!$D$2:$D$3000,MATCH(H16,Commerciaux!$A$2:$A$3000,0)),"") | J16: Visite de suivi | K16: Visite de suivi avec Hugo Perrin. Revue des commandes en cours et des prévisions du trimestre sur les coffrets rigides premium. Pas de difficulté particulière signalée. Hugo Perrin évoque les coffrets des éditions limitées 2027. | L16: Neutre | N16: Envoyer la documentation technique | O16: 45733 | P16: 75
A17: A0016 | B17: 45719 | C17: Appel | D17: E004 | E17: =IFERROR(INDEX(Entreprises!$B$2:$B$3000,MATCH(D17,Entreprises!$A$2:$A$3000,0)),"") | F17: C008 | G17: =IFERROR(INDEX(Contacts!$E$2:$E$3000,MATCH(F17,Contacts!$A$2:$A$3000,0)),"") | H17: U002 | I17: =IFERROR(INDEX(Commerciaux!$D$2:$D$3000,MATCH(H17,Commerciaux!$A$2:$A$3000,0)),"") | J17: Relance proposition | K17: Appel de relance sur la dernière proposition. Hugo Perrin demande quelques jours pour consolider les retours internes. | L17: Neutre | P17: 15
A18: A0017 | B18: 45719 | C18: Visite terrain | D18: E008 | E18: =IFERROR(INDEX(Entreprises!$B$2:$B$3000,MATCH(D18,Entreprises!$A$2:$A$3000,0)),"") | F18: C012 | G18: =IFERROR(INDEX(Contacts!$E$2:$E$3000,MATCH(F18,Contacts!$A$2:$A$3000,0)),"") | H18: U003 | I18: =IFERROR(INDEX(Commerciaux!$D$2:$D$3000,MATCH(H18,Commerciaux!$A$2:$A$3000,0)),"") | J18: Visite de suivi | K18: Visite de suivi avec Marie-Laure Rivière. Revue des commandes en cours et des prévisions du trimestre sur les étuis spiritueux luxe. Pas de difficulté particulière signalée. Marie-Laure Rivière évoque la consultation sur les étuis allégés 2027. | L18: Positif | N18: Relancer pour obtenir un retour | O18: 45736 | P18: 120
A19: A0018 | B19: 45722 | C19: Visite terrain | D19: E011 | E19: =IFERROR(INDEX(Entreprises!$B$2:$B$3000,MATCH(D19,Entreprises!$A$2:$A$3000,0)),"") | F19: C017 | G19: =IFERROR(INDEX(Contacts!$E$2:$E$3000,MATCH(F19,Contacts!$A$2:$A$3000,0)),"") | H19: U003 | I19: =IFERROR(INDEX(Commerciaux!$D$2:$D$3000,MATCH(H19,Commerciaux!$A$2:$A$3000,0)),"") | J19: Présentation des nouveautés 2025 | K19: Présentation des nouveautés 2025 à Stéphane Klein, notamment les caisses carton ondulé personnalisées. Accueil favorable et demande d'échantillons. | L19: Positif | N19: Transmettre des échantillons | O19: 45733 | P19: 75
A20: A0019 | B20: 45728 | C20: E-mail | D20: E019 | E20: =IFERROR(INDEX(Entreprises!$B$2:$B$3000,MATCH(D20,Entreprises!$A$2:$A$3000,0)),"") | F20: C031 | G20: =IFERROR(INDEX(Contacts!$E$2:$E$3000,MATCH(F20,Contacts!$A$2:$A$3000,0)),"") | H20: U005 | I20: =IFERROR(INDEX(Commerciaux!$D$2:$D$3000,MATCH(H20,Commerciaux!$A$2:$A$3000,0)),"") | J20: Envoi de la grille tarifaire | K20: Envoi à Benoît Carrière de la grille tarifaire actualisée, avec rappel des conditions de paiement (60 jours). | L20: Neutre
A21: A0020 | B21: 45730 | C21: Appel | D21: E008 | E21: =IFERROR(INDEX(Entreprises!$B$2:$B$3000,MATCH(D21,Entreprises!$A$2:$A$3000,0)),"") | F21: C013 | G21: =IFERROR(INDEX(Contacts!$E$2:$E$3000,MATCH(F21,Contacts!$A$2:$A$3000,0)),"") | H21: U003 | I21: =IFERROR(INDEX(Commerciaux!$D$2:$D$3000,MATCH(H21,Commerciaux!$A$2:$A$3000,0)),"") | J21: Relance proposition | K21: Appel de relance sur la dernière proposition. Bastien Collet demande quelques jours pour consolider les retours internes. | L21: Neutre | N21: Envoyer la documentation technique | O21: 45747 | P21: 20
A22: A0021 | B22: 45730 | C22: Appel | D22: E025 | E22: =IFERROR(INDEX(Entreprises!$B$2:$B$3000,MATCH(D22,Entreprises!$A$2:$A$3000,0)),"") | F22: C041 | G22: =IFERROR(INDEX(Contacts!$E$2:$E$3000,MATCH(F22,Contacts!$A$2:$A$3000,0)),"") | H22: U007 | I22: =IFERROR(INDEX(Commerciaux!$D$2:$D$3000,MATCH(H22,Commerciaux!$A$2:$A$3000,0)),"") | J22: Relance proposition | K22: Appel de relance sur la dernière proposition. Manon Leclerc demande quelques jours pour consolider les retours internes. | L22: À relancer | N22: Planifier une visite de site | O22: 45740 | P22: 10
A23: A0022 | B23: 45740 | C23: E-mail | D23: E022 | E23: =IFERROR(INDEX(Entreprises!$B$2:$B$3000,MATCH(D23,Entreprises!$A$2:$A$3000,0)),"") | F23: C036 | G23: =IFERROR(INDEX(Contacts!$E$2:$E$3000,MATCH(F23,Contacts!$A$2:$A$3000,0)),"") | H23: U006 | I23: =IFERROR(INDEX(Commerciaux!$D$2:$D$3000,MATCH(H23,Commerciaux!$A$2:$A$3000,0)),"") | J23: Envoi de fiche technique | K23: Envoi à Patrick Renaud de la fiche technique et des certificats des notices pharmaceutiques pliées. | L23: Neutre
A24: A0023 | B24: 45742 | C24: Note | D24: E023 | E24: =IFERROR(INDEX(Entreprises!$B$2:$B$3000,MATCH(D24,Entreprises!$A$2:$A$3000,0)),"") | F24: C038 | G24: =IFERROR(INDEX(Contacts!$E$2:$E$3000,MATCH(F24,Contacts!$A$2:$A$3000,0)),"") | H24: U006 | I24: =IFERROR(INDEX(Commerciaux!$D$2:$D$3000,MATCH(H24,Commerciaux!$A$2:$A$3000,0)),"") | J24: Préparation négociation | K24: Note interne : préparer un comparatif de prix face à Kartéa Pharma Pack avant la prochaine négociation. | L24: Neutre
A25: A0024 | B25: 45742 | C25: Note | D25: E025 | E25: =IFERROR(INDEX(Entreprises!$B$2:$B$3000,MATCH(D25,Entreprises!$A$2:$A$3000,0)),"") | F25: C041 | G25: =IFERROR(INDEX(Contacts!$E$2:$E$3000,MATCH(F25,Contacts!$A$2:$A$3000,0)),"") | H25: U007 | I25: =IFERROR(INDEX(Commerciaux!$D$2:$D$3000,MATCH(H25,Commerciaux!$A$2:$A$3000,0)),"") | J25: Préparation négociation | K25: Note interne : préparer un comparatif de prix face à Kartéa Luxe avant la prochaine négociation. | L25: Neutre
A26: A0025 | B26: 45743 | C26: Réunion visio | D26: E023 | E26: =IFERROR(INDEX(Entreprises!$B$2:$B$3000,MATCH(D26,Entreprises!$A$2:$A$3000,0)),"") | F26: C037 | G26: =IFERROR(INDEX(Contacts!$E$2:$E$3000,MATCH(F26,Contacts!$A$2:$A$3000,0)),"") | H26: U006 | I26: =IFERROR(INDEX(Commerciaux!$D$2:$D$3000,MATCH(H26,Commerciaux!$A$2:$A$3000,0)),"") | J26: Revue des prévisions | K26: Visio de revue des prévisions de volumes avec Caroline Lefèvre et la supply chain du client. | L26: Neutre | P26: 45
A27: A0026 | B27: 45751 | C27: Visite terrain | D27: E025 | E27: =IFERROR(INDEX(Entreprises!$B$2:$B$3000,MATCH(D27,Entreprises!$A$2:$A$3000,0)),"") | F27: C041 | G27: =IFERROR(INDEX(Contacts!$E$2:$E$3000,MATCH(F27,Contacts!$A$2:$A$3000,0)),"") | H27: U007 | I27: =IFERROR(INDEX(Commerciaux!$D$2:$D$3000,MATCH(H27,Commerciaux!$A$2:$A$3000,0)),"") | J27: Visite de la ligne de conditionnement | K27: Visite du site avec Manon Leclerc et l'équipe de production. Observation de la ligne de conditionnement ; points d'amélioration identifiés sur les changements de format. Intérêt exprimé pour le programme d'éco-conception des coffrets. | L27: Neutre | P27: 90
A28: A0027 | B28: 45751 | C28: E-mail | D28: E027 | E28: =IFERROR(INDEX(Entreprises!$B$2:$B$3000,MATCH(D28,Entreprises!$A$2:$A$3000,0)),"") | F28: C045 | G28: =IFERROR(INDEX(Contacts!$E$2:$E$3000,MATCH(F28,Contacts!$A$2:$A$3000,0)),"") | H28: U007 | I28: =IFERROR(INDEX(Commerciaux!$D$2:$D$3000,MATCH(H28,Commerciaux!$A$2:$A$3000,0)),"") | J28: Envoi du planning | K28: Envoi à Alexandre Colin du planning prévisionnel et des points ouverts concernant les coffrets de fêtes 2027. | L28: Neutre
A29: A0028 | B29: 45751 | C29: Visite terrain | D29: E030 | E29: =IFERROR(INDEX(Entreprises!$B$2:$B$3000,MATCH(D29,Entreprises!$A$2:$A$3000,0)),"") | F29: C050 | G29: =IFERROR(INDEX(Contacts!$E$2:$E$3000,MATCH(F29,Contacts!$A$2:$A$3000,0)),"") | H29: U007 | I29: =IFERROR(INDEX(Commerciaux!$D$2:$D$3000,MATCH(H29,Commerciaux!$A$2:$A$3000,0)),"") | J29: Visite de la ligne de conditionnement | K29: Visite du site avec Pierre-Yves Guérin et l'équipe de production. Observation de la ligne de conditionnement ; points d'amélioration identifiés sur les changements de format. Intérêt exprimé pour les emballages sans plastique de la distribution électrique. | L29: Positif | N29: Envoyer la documentation technique | O29: 45761 | P29: 90
A30: A0029 | B30: 45756 | C30: E-mail | D30: E001 | E30: =IFERROR(INDEX(Entreprises!$B$2:$B$3000,MATCH(D30,Entreprises!$A$2:$A$3000,0)),"") | F30: C001 | G30: =IFERROR(INDEX(Contacts!$E$2:$E$3000,MATCH(F30,Contacts!$A$2:$A$3000,0)),"") | H30: U002 | I30: =IFERROR(INDEX(Commerciaux!$D$2:$D$3000,MATCH(H30,Commerciaux!$A$2:$A$3000,0)),"") | J30: Demande de devis | K30: Nathalie Dubreuil demande un devis complémentaire pour une série courte de caisses carton ondulé personnalisées. | L30: Neutre
A31: A0030 | B31: 45758 | C31: Visite terrain | D31: E021 | E31: =IFERROR(INDEX(Entreprises!$B$2:$B$3000,MATCH(D31,Entreprises!$A$2:$A$3000,0)),"") | F31: C033 | G31: =IFERROR(INDEX(Contacts!$E$2:$E$3000,MATCH(F31,Contacts!$A$2:$A$3000,0)),"") | H31: U005 | I31: =IFERROR(INDEX(Commerciaux!$D$2:$D$3000,MATCH(H31,Commerciaux!$A$2:$A$3000,0)),"") | J31: Présentation des nouveautés 2025 | K31: Présentation des nouveautés 2025 à Valérie Dumas, notamment les caisses carton ondulé personnalisées. Accueil favorable et demande d'échantillons. | L31: Négatif | N31: Planifier une visite de site | O31: 45775 | P31: 90
A32: A0031 | B32: 45758 | C32: Réunion visio | D32: E025 | E32: =IFERROR(INDEX(Entreprises!$B$2:$B$3000,MATCH(D32,Entreprises!$A$2:$A$3000,0)),"") | F32: C041 | G32: =IFERROR(INDEX(Contacts!$E$2:$E$3000,MATCH(F32,Contacts!$A$2:$A$3000,0)),"") | H32: U007 | I32: =IFERROR(INDEX(Commerciaux!$D$2:$D$3000,MATCH(H32,Commerciaux!$A$2:$A$3000,0)),"") | J32: Revue des prévisions | K32: Visio de revue des prévisions de volumes avec Manon Leclerc et la supply chain du client. | L32: Positif | N32: Envoyer le devis | O32: 45778 | P32: 45
A33: A0032 | B33: 45761 | C33: Visite terrain | D33: E003 | E33: =IFERROR(INDEX(Entreprises!$B$2:$B$3000,MATCH(D33,Entreprises!$A$2:$A$3000,0)),"") | F33: C006 | G33: =IFERROR(INDEX(Contacts!$E$2:$E$3000,MATCH(F33,Contacts!$A$2:$A$3000,0)),"") | H33: U002 | I33: =IFERROR(INDEX(Commerciaux!$D$2:$D$3000,MATCH(H33,Commerciaux!$A$2:$A$3000,0)),"") | J33: Visite de la ligne de conditionnement | K33: Visite du site avec Olivier Chen et l'équipe de production. Observation de la ligne de conditionnement ; points d'amélioration identifiés sur les changements de format. Intérêt exprimé pour la refonte des notices multilingues. | L33: À relancer | N33: Envoyer la documentation technique | O33: 45770 | P33: 90
A34: A0033 | B34: 45762 | C34: Appel | D34: E012 | E34: =IFERROR(INDEX(Entreprises!$B$2:$B$3000,MATCH(D34,Entreprises!$A$2:$A$3000,0)),"") | F34: C020 | G34: =IFERROR(INDEX(Contacts!$E$2:$E$3000,MATCH(F34,Contacts!$A$2:$A$3000,0)),"") | H34: U004 | I34: =IFERROR(INDEX(Commerciaux!$D$2:$D$3000,MATCH(H34,Commerciaux!$A$2:$A$3000,0)),"") | J34: Suivi de livraison | K34: Appel de suivi après la dernière livraison. Mathieu Faure confirme la conformité des lots reçus. | L34: À relancer | N34: Envoyer la documentation technique | O34: 45779 | P34: 20
A35: A0034 | B35: 45764 | C35: Visite terrain | D35: E014 | E35: =IFERROR(INDEX(Entreprises!$B$2:$B$3000,MATCH(D35,Entreprises!$A$2:$A$3000,0)),"") | F35: C024 | G35: =IFERROR(INDEX(Contacts!$E$2:$E$3000,MATCH(F35,Contacts!$A$2:$A$3000,0)),"") | H35: U004 | I35: =IFERROR(INDEX(Commerciaux!$D$2:$D$3000,MATCH(H35,Commerciaux!$A$2:$A$3000,0)),"") | J35: Présentation des nouveautés 2025 | K35: Présentation des nouveautés 2025 à Laurent Mercier, notamment les caisses carton ondulé personnalisées. Accueil favorable et demande d'échantillons. | L35: Positif | N35: Planifier une visite de site | O35: 45783 | P35: 120
A36: A0035 | B36: 45768 | C36: Appel | D36: E003 | E36: =IFERROR(INDEX(Entreprises!$B$2:$B$3000,MATCH(D36,Entreprises!$A$2:$A$3000,0)),"") | F36: C005 | G36: =IFERROR(INDEX(Contacts!$E$2:$E$3000,MATCH(F36,Contacts!$A$2:$A$3000,0)),"") | H36: U002 | I36: =IFERROR(INDEX(Commerciaux!$D$2:$D$3000,MATCH(H36,Commerciaux!$A$2:$A$3000,0)),"") | J36: Relance proposition | K36: Appel de relance sur la dernière proposition. Sophie Marchand demande quelques jours pour consolider les retours internes. | L36: À relancer | P36: 15
A37: A0036 | B37: 45768 | C37: E-mail | D37: E019 | E37: =IFERROR(INDEX(Entreprises!$B$2:$B$3000,MATCH(D37,Entreprises!$A$2:$A$3000,0)),"") | F37: C030 | G37: =IFERROR(INDEX(Contacts!$E$2:$E$3000,MATCH(F37,Contacts!$A$2:$A$3000,0)),"") | H37: U005 | I37: =IFERROR(INDEX(Commerciaux!$D$2:$D$3000,MATCH(H37,Commerciaux!$A$2:$A$3000,0)),"") | J37: Envoi du planning | K37: Envoi à Sandrine Delmas du planning prévisionnel et des points ouverts concernant le renouvellement du contrat étuis 2027. | L37: À relancer
A38: A0037 | B38: 45772 | C38: Appel | D38: E019 | E38: =IFERROR(INDEX(Entreprises!$B$2:$B$3000,MATCH(D38,Entreprises!$A$2:$A$3000,0)),"") | F38: C030 | G38: =IFERROR(INDEX(Contacts!$E$2:$E$3000,MATCH(F38,Contacts!$A$2:$A$3000,0)),"") | H38: U005 | I38: =IFERROR(INDEX(Commerciaux!$D$2:$D$3000,MATCH(H38,Commerciaux!$A$2:$A$3000,0)),"") | J38: Ajustement de commande | K38: Appel de Sandrine Delmas pour ajuster les quantités de la prochaine commande de notices pharmaceutiques pliées. Modification prise en compte. | L38: À relancer | P38: 10
A39: A0038 | B39: 45772 | C39: Visite terrain | D39: E021 | E39: =IFERROR(INDEX(Entreprises!$B$2:$B$3000,MATCH(D39,Entreprises!$A$2:$A$3000,0)),"") | F39: C034 | G39: =IFERROR(INDEX(Contacts!$E$2:$E$3000,MATCH(F39,Contacts!$A$2:$A$3000,0)),"") | H39: U005 | I39: =IFERROR(INDEX(Commerciaux!$D$2:$D$3000,MATCH(H39,Commerciaux!$A$2:$A$3000,0)),"") | J39: Revue d'activité semestrielle | K39: Revue d'activité semestrielle avec Thierry Lacroix. Satisfaction globale sur la qualité ; demande de visibilité sur l'évolution des prix des matières. Échange sur le déploiement des emballages éco-conçus sur deux usines. | L39: Positif | N39: Envoyer la documentation technique | O39: 45789 | P39: 75
A40: A0039 | B40: 45775 | C40: E-mail | D40: E019 | E40: =IFERROR(INDEX(Entreprises!$B$2:$B$3000,MATCH(D40,Entreprises!$A$2:$A$3000,0)),"") | F40: C030 | G40: =IFERROR(INDEX(Contacts!$E$2:$E$3000,MATCH(F40,Contacts!$A$2:$A$3000,0)),"") | H40: U005 | I40: =IFERROR(INDEX(Commerciaux!$D$2:$D$3000,MATCH(H40,Commerciaux!$A$2:$A$3000,0)),"") | J40: Envoi de fiche technique | K40: Envoi à Sandrine Delmas de la fiche technique et des certificats des notices pharmaceutiques pliées. | L40: Neutre
A41: A0040 | B41: 45786 | C41: Réunion visio | D41: E028 | E41: =IFERROR(INDEX(Entreprises!$B$2:$B$3000,MATCH(D41,Entreprises!$A$2:$A$3000,0)),"") | F41: C047 | G41: =IFERROR(INDEX(Contacts!$E$2:$E$3000,MATCH(F41,Contacts!$A$2:$A$3000,0)),"") | H41: U007 | I41: =IFERROR(INDEX(Commerciaux!$D$2:$D$3000,MATCH(H41,Commerciaux!$A$2:$A$3000,0)),"") | J41: Revue des prévisions | K41: Visio de revue des prévisions de volumes avec Chloé Muller et la supply chain du client. | L41: Positif | P41: 45
A42: A0041 | B42: 45792 | C42: Réunion visio | D42: E012 | E42: =IFERROR(INDEX(Entreprises!$B$2:$B$3000,MATCH(D42,Entreprises!$A$2:$A$3000,0)),"") | F42: C020 | G42: =IFERROR(INDEX(Contacts!$E$2:$E$3000,MATCH(F42,Contacts!$A$2:$A$3000,0)),"") | H42: U004 | I42: =IFERROR(INDEX(Commerciaux!$D$2:$D$3000,MATCH(H42,Commerciaux!$A$2:$A$3000,0)),"") | J42: Revue des prévisions | K42: Visio de revue des prévisions de volumes avec Mathieu Faure et la supply chain du client. | L42: Positif | P42: 60
A43: A0042 | B43: 45796 | C43: Visite terrain | D43: E014 | E43: =IFERROR(INDEX(Entreprises!$B$2:$B$3000,MATCH(D43,Entreprises!$A$2:$A$3000,0)),"") | F43: C024 | G43: =IFERROR(INDEX(Contacts!$E$2:$E$3000,MATCH(F43,Contacts!$A$2:$A$3000,0)),"") | H43: U004 | I43: =IFERROR(INDEX(Commerciaux!$D$2:$D$3000,MATCH(H43,Commerciaux!$A$2:$A$3000,0)),"") | J43: Revue d'activité semestrielle | K43: Revue d'activité semestrielle avec Laurent Mercier. Satisfaction globale sur la qualité ; demande de visibilité sur l'évolution des prix des matières. Échange sur la suppression du polystyrène dans les calages. | L43: À relancer | N43: Planifier une visite de site | O43: 45810 | P43: 75
A44: A0043 | B44: 45797 | C44: Réunion visio | D44: E003 | E44: =IFERROR(INDEX(Entreprises!$B$2:$B$3000,MATCH(D44,Entreprises!$A$2:$A$3000,0)),"") | F44: C005 | G44: =IFERROR(INDEX(Contacts!$E$2:$E$3000,MATCH(F44,Contacts!$A$2:$A$3000,0)),"") | H44: U002 | I44: =IFERROR(INDEX(Commerciaux!$D$2:$D$3000,MATCH(H44,Commerciaux!$A$2:$A$3000,0)),"") | J44: Revue des prévisions | K44: Visio de revue des prévisions de volumes avec Sophie Marchand et la supply chain du client. | L44: Positif | N44: Envoyer le devis | O44: 45807 | P44: 45
A45: A0044 | B45: 45807 | C45: E-mail | D45: E023 | E45: =IFERROR(INDEX(Entreprises!$B$2:$B$3000,MATCH(D45,Entreprises!$A$2:$A$3000,0)),"") | F45: C038 | G45: =IFERROR(INDEX(Contacts!$E$2:$E$3000,MATCH(F45,Contacts!$A$2:$A$3000,0)),"") | H45: U006 | I45: =IFERROR(INDEX(Commerciaux!$D$2:$D$3000,MATCH(H45,Commerciaux!$A$2:$A$3000,0)),"") | J45: Envoi de fiche technique | K45: Envoi à David Nguyen de la fiche technique et des certificats des étuis carton pharmaceutiques imprimés. | L45: Neutre
A46: A0045 | B46: 45818 | C46: Appel | D46: E021 | E46: =IFERROR(INDEX(Entreprises!$B$2:$B$3000,MATCH(D46,Entreprises!$A$2:$A$3000,0)),"") | F46: C033 | G46: =IFERROR(INDEX(Contacts!$E$2:$E$3000,MATCH(F46,Contacts!$A$2:$A$3000,0)),"") | H46: U005 | I46: =IFERROR(INDEX(Commerciaux!$D$2:$D$3000,MATCH(H46,Commerciaux!$A$2:$A$3000,0)),"") | J46: Point d'avancement projet | K46: Échange téléphonique avec Valérie Dumas sur le calendrier concernant le déploiement des emballages éco-conçus sur deux usines. Décision interne attendue dans les prochaines semaines. | L46: Positif | P46: 15
A47: A0046 | B47: 45820 | C47: E-mail | D47: E022 | E47: =IFERROR(INDEX(Entreprises!$B$2:$B$3000,MATCH(D47,Entreprises!$A$2:$A$3000,0)),"") | F47: C035 | G47: =IFERROR(INDEX(Contacts!$E$2:$E$3000,MATCH(F47,Contacts!$A$2:$A$3000,0)),"") | H47: U006 | I47: =IFERROR(INDEX(Commerciaux!$D$2:$D$3000,MATCH(H47,Commerciaux!$A$2:$A$3000,0)),"") | J47: Envoi de la grille tarifaire | K47: Envoi à Hélène Bouvier de la grille tarifaire actualisée, avec rappel des conditions de paiement (60 jours). | L47: Neutre
A48: A0047 | B48: 45821 | C48: Visite terrain | D48: E008 | E48: =IFERROR(INDEX(Entreprises!$B$2:$B$3000,MATCH(D48,Entreprises!$A$2:$A$3000,0)),"") | F48: C013 | G48: =IFERROR(INDEX(Contacts!$E$2:$E$3000,MATCH(F48,Contacts!$A$2:$A$3000,0)),"") | H48: U003 | I48: =IFERROR(INDEX(Commerciaux!$D$2:$D$3000,MATCH(H48,Commerciaux!$A$2:$A$3000,0)),"") | J48: Présentation des nouveautés 2025 | K48: Présentation des nouveautés 2025 à Bastien Collet, notamment les étuis spiritueux luxe. Accueil favorable et demande d'échantillons. | L48: Positif | N48: Envoyer la documentation technique | O48: 45831 | P48: 90
A49: A0048 | B49: 45825 | C49: E-mail | D49: E009 | E49: =IFERROR(INDEX(Entreprises!$B$2:$B$3000,MATCH(D49,Entreprises!$A$2:$A$3000,0)),"") | F49: C015 | G49: =IFERROR(INDEX(Contacts!$E$2:$E$3000,MATCH(F49,Contacts!$A$2:$A$3000,0)),"") | H49: U003 | I49: =IFERROR(INDEX(Commerciaux!$D$2:$D$3000,MATCH(H49,Commerciaux!$A$2:$A$3000,0)),"") | J49: Demande de devis | K49: Pauline Henry demande un devis complémentaire pour une série courte de caisses carton ondulé personnalisées. | L49: Neutre
A50: A0049 | B50: 45828 | C50: E-mail | D50: E027 | E50: =IFERROR(INDEX(Entreprises!$B$2:$B$3000,MATCH(D50,Entreprises!$A$2:$A$3000,0)),"") | F50: C044 | G50: =IFERROR(INDEX(Contacts!$E$2:$E$3000,MATCH(F50,Contacts!$A$2:$A$3000,0)),"") | H50: U007 | I50: =IFERROR(INDEX(Commerciaux!$D$2:$D$3000,MATCH(H50,Commerciaux!$A$2:$A$3000,0)),"") | J50: Envoi de la grille tarifaire | K50: Envoi à Laetitia Fournier de la grille tarifaire actualisée, avec rappel des conditions de paiement (60 jours). | L50: Neutre
A51: A0050 | B51: 45832 | C51: Réunion visio | D51: E003 | E51: =IFERROR(INDEX(Entreprises!$B$2:$B$3000,MATCH(D51,Entreprises!$A$2:$A$3000,0)),"") | F51: C005 | G51: =IFERROR(INDEX(Contacts!$E$2:$E$3000,MATCH(F51,Contacts!$A$2:$A$3000,0)),"") | H51: U002 | I51: =IFERROR(INDEX(Commerciaux!$D$2:$D$3000,MATCH(H51,Commerciaux!$A$2:$A$3000,0)),"") | J51: Cadrage du besoin | K51: Réunion Teams avec Sophie Marchand pour cadrer le besoin concernant la refonte des notices multilingues. Liste des prérequis techniques partagée. | L51: Positif | P51: 30
A52: A0051 | B52: 45840 | C52: Note | D52: E012 | E52: =IFERROR(INDEX(Entreprises!$B$2:$B$3000,MATCH(D52,Entreprises!$A$2:$A$3000,0)),"") | F52: C020 | G52: =IFERROR(INDEX(Contacts!$E$2:$E$3000,MATCH(F52,Contacts!$A$2:$A$3000,0)),"") | H52: U004 | I52: =IFERROR(INDEX(Commerciaux!$D$2:$D$3000,MATCH(H52,Commerciaux!$A$2:$A$3000,0)),"") | J52: Préparation négociation | K52: Note interne : préparer un comparatif de prix face à Kartéa Pharma Pack avant la prochaine négociation. | L52: Neutre
A53: A0052 | B53: 45840 | C53: Visite terrain | D53: E027 | E53: =IFERROR(INDEX(Entreprises!$B$2:$B$3000,MATCH(D53,Entreprises!$A$2:$A$3000,0)),"") | F53: C044 | G53: =IFERROR(INDEX(Contacts!$E$2:$E$3000,MATCH(F53,Contacts!$A$2:$A$3000,0)),"") | H53: U007 | I53: =IFERROR(INDEX(Commerciaux!$D$2:$D$3000,MATCH(H53,Commerciaux!$A$2:$A$3000,0)),"") | J53: Présentation des nouveautés 2025 | K53: Présentation des nouveautés 2025 à Laetitia Fournier, notamment les emballages éco-conçus mono-matériau. Accueil favorable et demande d'échantillons. | L53: Neutre | N53: Transmettre des échantillons | O53: 45855 | P53: 75
A54: A0053 | B54: 45849 | C54: Visite terrain | D54: E026 | E54: =IFERROR(INDEX(Entreprises!$B$2:$B$3000,MATCH(D54,Entreprises!$A$2:$A$3000,0)),"") | F54: C043 | G54: =IFERROR(INDEX(Contacts!$E$2:$E$3000,MATCH(F54,Contacts!$A$2:$A$3000,0)),"") | H54: U007 | I54: =IFERROR(INDEX(Commerciaux!$D$2:$D$3000,MATCH(H54,Commerciaux!$A$2:$A$3000,0)),"") | J54: Visite de suivi | K54: Visite de suivi avec Samuel Robin. Revue des commandes en cours et des prévisions du trimestre sur les caisses carton ondulé personnalisées. Pas de difficulté particulière signalée. Samuel Robin évoque la réduction des emballages secondaires. | L54: À relancer | N54: Planifier une visite de site | O54: 45866 | P54: 60
A55: A0054 | B55: 45852 | C55: Visite terrain | D55: E018 | E55: =IFERROR(INDEX(Entreprises!$B$2:$B$3000,MATCH(D55,Entreprises!$A$2:$A$3000,0)),"") | F55: C029 | G55: =IFERROR(INDEX(Contacts!$E$2:$E$3000,MATCH(F55,Contacts!$A$2:$A$3000,0)),"") | H55: U005 | I55: =IFERROR(INDEX(Commerciaux!$D$2:$D$3000,MATCH(H55,Commerciaux!$A$2:$A$3000,0)),"") | J55: Présentation des nouveautés 2025 | K55: Présentation des nouveautés 2025 à Guillaume Petit, notamment les étuis spiritueux luxe. Accueil favorable et demande d'échantillons. | L55: Positif | N55: Envoyer la documentation technique | O55: 45868 | P55: 90
A56: A0055 | B56: 45852 | C56: E-mail | D56: E027 | E56: =IFERROR(INDEX(Entreprises!$B$2:$B$3000,MATCH(D56,Entreprises!$A$2:$A$3000,0)),"") | F56: C044 | G56: =IFERROR(INDEX(Contacts!$E$2:$E$3000,MATCH(F56,Contacts!$A$2:$A$3000,0)),"") | H56: U007 | I56: =IFERROR(INDEX(Commerciaux!$D$2:$D$3000,MATCH(H56,Commerciaux!$A$2:$A$3000,0)),"") | J56: Envoi de fiche technique | K56: Envoi à Laetitia Fournier de la fiche technique et des certificats des coffrets rigides premium. | L56: Neutre
A57: A0056 | B57: 45856 | C57: Appel | D57: E001 | E57: =IFERROR(INDEX(Entreprises!$B$2:$B$3000,MATCH(D57,Entreprises!$A$2:$A$3000,0)),"") | F57: C002 | G57: =IFERROR(INDEX(Contacts!$E$2:$E$3000,MATCH(F57,Contacts!$A$2:$A$3000,0)),"") | H57: U002 | I57: =IFERROR(INDEX(Commerciaux!$D$2:$D$3000,MATCH(H57,Commerciaux!$A$2:$A$3000,0)),"") | J57: Ajustement de commande | K57: Appel de Kevin Lemaire pour ajuster les quantités de la prochaine commande d'étiquettes adhésives haute définition. Modification prise en compte. | L57: Positif | N57: Planifier une visite de site | O57: 45873 | P57: 5
A58: A0057 | B58: 45861 | C58: Visite terrain | D58: E007 | E58: =IFERROR(INDEX(Entreprises!$B$2:$B$3000,MATCH(D58,Entreprises!$A$2:$A$3000,0)),"") | F58: C011 | G58: =IFERROR(INDEX(Contacts!$E$2:$E$3000,MATCH(F58,Contacts!$A$2:$A$3000,0)),"") | H58: U002 | I58: =IFERROR(INDEX(Commerciaux!$D$2:$D$3000,MATCH(H58,Commerciaux!$A$2:$A$3000,0)),"") | J58: Présentation des nouveautés 2025 | K58: Présentation des nouveautés 2025 à François Girard, notamment les caisses carton ondulé personnalisées. Accueil favorable et demande d'échantillons. | L58: Positif | N58: Planifier une visite de site | O58: 45882 | P58: 120
A59: A0058 | B59: 45863 | C59: Appel | D59: E023 | E59: =IFERROR(INDEX(Entreprises!$B$2:$B$3000,MATCH(D59,Entreprises!$A$2:$A$3000,0)),"") | F59: C037 | G59: =IFERROR(INDEX(Contacts!$E$2:$E$3000,MATCH(F59,Contacts!$A$2:$A$3000,0)),"") | H59: U006 | I59: =IFERROR(INDEX(Commerciaux!$D$2:$D$3000,MATCH(H59,Commerciaux!$A$2:$A$3000,0)),"") | J59: Suivi de livraison | K59: Appel de suivi après la dernière livraison. Caroline Lefèvre confirme la conformité des lots reçus. | L59: Neutre | N59: Envoyer la documentation technique | O59: 45877 | P59: 10
A60: A0059 | B60: 45867 | C60: Réunion visio | D60: E019 | E60: =IFERROR(INDEX(Entreprises!$B$2:$B$3000,MATCH(D60,Entreprises!$A$2:$A$3000,0)),"") | F60: C030 | G60: =IFERROR(INDEX(Contacts!$E$2:$E$3000,MATCH(F60,Contacts!$A$2:$A$3000,0)),"") | H60: U005 | I60: =IFERROR(INDEX(Commerciaux!$D$2:$D$3000,MATCH(H60,Commerciaux!$A$2:$A$3000,0)),"") | J60: Cadrage du besoin | K60: Réunion Teams avec Sandrine Delmas pour cadrer le besoin concernant le renouvellement du contrat étuis 2027. Liste des prérequis techniques partagée. | L60: Positif | P60: 60
A61: A0060 | B61: 45870 | C61: Réunion visio | D61: E014 | E61: =IFERROR(INDEX(Entreprises!$B$2:$B$3000,MATCH(D61,Entreprises!$A$2:$A$3000,0)),"") | F61: C024 | G61: =IFERROR(INDEX(Contacts!$E$2:$E$3000,MATCH(F61,Contacts!$A$2:$A$3000,0)),"") | H61: U004 | I61: =IFERROR(INDEX(Commerciaux!$D$2:$D$3000,MATCH(H61,Commerciaux!$A$2:$A$3000,0)),"") | J61: Revue des prévisions | K61: Visio de revue des prévisions de volumes avec Laurent Mercier et la supply chain du client. | L61: Positif | N61: Envoyer le devis | O61: 45887 | P61: 30
A62: A0061 | B62: 45877 | C62: Appel | D62: E009 | E62: =IFERROR(INDEX(Entreprises!$B$2:$B$3000,MATCH(D62,Entreprises!$A$2:$A$3000,0)),"") | F62: C015 | G62: =IFERROR(INDEX(Contacts!$E$2:$E$3000,MATCH(F62,Contacts!$A$2:$A$3000,0)),"") | H62: U003 | I62: =IFERROR(INDEX(Commerciaux!$D$2:$D$3000,MATCH(H62,Commerciaux!$A$2:$A$3000,0)),"") | J62: Point d'avancement projet | K62: Échange téléphonique avec Pauline Henry sur le calendrier concernant le renouvellement des étuis de la gamme rosé. Décision interne attendue dans les prochaines semaines. | L62: Neutre | P62: 20
A63: A0062 | B63: 45880 | C63: Visite terrain | D63: E019 | E63: =IFERROR(INDEX(Entreprises!$B$2:$B$3000,MATCH(D63,Entreprises!$A$2:$A$3000,0)),"") | F63: C031 | G63: =IFERROR(INDEX(Contacts!$E$2:$E$3000,MATCH(F63,Contacts!$A$2:$A$3000,0)),"") | H63: U005 | I63: =IFERROR(INDEX(Commerciaux!$D$2:$D$3000,MATCH(H63,Commerciaux!$A$2:$A$3000,0)),"") | J63: Visite de la ligne de conditionnement | K63: Visite du site avec Benoît Carrière et l'équipe de production. Observation de la ligne de conditionnement ; points d'amélioration identifiés sur les changements de format. Intérêt exprimé pour le renouvellement du contrat étuis 2027. | L63: Neutre | N63: Envoyer le devis | O63: 45891 | P63: 90
A64: A0063 | B64: 45882 | C64: Appel | D64: E003 | E64: =IFERROR(INDEX(Entreprises!$B$2:$B$3000,MATCH(D64,Entreprises!$A$2:$A$3000,0)),"") | F64: C006 | G64: =IFERROR(INDEX(Contacts!$E$2:$E$3000,MATCH(F64,Contacts!$A$2:$A$3000,0)),"") | H64: U002 | I64: =IFERROR(INDEX(Commerciaux!$D$2:$D$3000,MATCH(H64,Commerciaux!$A$2:$A$3000,0)),"") | J64: Point d'avancement projet | K64: Échange téléphonique avec Olivier Chen sur le calendrier concernant la refonte des notices multilingues. Décision interne attendue dans les prochaines semaines. | L64: Neutre | P64: 15
A65: A0064 | B65: 45884 | C65: E-mail | D65: E007 | E65: =IFERROR(INDEX(Entreprises!$B$2:$B$3000,MATCH(D65,Entreprises!$A$2:$A$3000,0)),"") | F65: C011 | G65: =IFERROR(INDEX(Contacts!$E$2:$E$3000,MATCH(F65,Contacts!$A$2:$A$3000,0)),"") | H65: U002 | I65: =IFERROR(INDEX(Commerciaux!$D$2:$D$3000,MATCH(H65,Commerciaux!$A$2:$A$3000,0)),"") | J65: Envoi du planning | K65: Envoi à François Girard du planning prévisionnel et des points ouverts concernant l'harmonisation des étiquettes logistiques entre sites. | L65: Neutre
A66: A0065 | B66: 45887 | C66: Appel | D66: E012 | E66: =IFERROR(INDEX(Entreprises!$B$2:$B$3000,MATCH(D66,Entreprises!$A$2:$A$3000,0)),"") | F66: C019 | G66: =IFERROR(INDEX(Contacts!$E$2:$E$3000,MATCH(F66,Contacts!$A$2:$A$3000,0)),"") | H66: U004 | I66: =IFERROR(INDEX(Commerciaux!$D$2:$D$3000,MATCH(H66,Commerciaux!$A$2:$A$3000,0)),"") | J66: Ajustement de commande | K66: Appel de Isabelle Roche pour ajuster les quantités de la prochaine commande d'étuis carton pharmaceutiques imprimés. Modification prise en compte. | L66: Positif | P66: 20
A67: A0066 | B67: 45888 | C67: Visite terrain | D67: E017 | E67: =IFERROR(INDEX(Entreprises!$B$2:$B$3000,MATCH(D67,Entreprises!$A$2:$A$3000,0)),"") | F67: C027 | G67: =IFERROR(INDEX(Contacts!$E$2:$E$3000,MATCH(F67,Contacts!$A$2:$A$3000,0)),"") | H67: U005 | I67: =IFERROR(INDEX(Commerciaux!$D$2:$D$3000,MATCH(H67,Commerciaux!$A$2:$A$3000,0)),"") | J67: Visite de suivi | K67: Visite de suivi avec Céline Barbier. Revue des commandes en cours et des prévisions du trimestre sur les coffrets rigides premium. Pas de difficulté particulière signalée. Céline Barbier évoque le coffret réutilisable de la gamme premium. | L67: Neutre | N67: Transmettre des échantillons | O67: 45901 | P67: 120
A68: A0067 | B68: 45888 | C68: E-mail | D68: E027 | E68: =IFERROR(INDEX(Entreprises!$B$2:$B$3000,MATCH(D68,Entreprises!$A$2:$A$3000,0)),"") | F68: C044 | G68: =IFERROR(INDEX(Contacts!$E$2:$E$3000,MATCH(F68,Contacts!$A$2:$A$3000,0)),"") | H68: U007 | I68: =IFERROR(INDEX(Commerciaux!$D$2:$D$3000,MATCH(H68,Commerciaux!$A$2:$A$3000,0)),"") | J68: Demande de devis | K68: Laetitia Fournier demande un devis complémentaire pour une série courte de coffrets rigides premium. | L68: Neutre
A69: A0068 | B69: 45888 | C69: E-mail | D69: E030 | E69: =IFERROR(INDEX(Entreprises!$B$2:$B$3000,MATCH(D69,Entreprises!$A$2:$A$3000,0)),"") | F69: C050 | G69: =IFERROR(INDEX(Contacts!$E$2:$E$3000,MATCH(F69,Contacts!$A$2:$A$3000,0)),"") | H69: U007 | I69: =IFERROR(INDEX(Commerciaux!$D$2:$D$3000,MATCH(H69,Commerciaux!$A$2:$A$3000,0)),"") | J69: Demande de devis | K69: Pierre-Yves Guérin demande un devis complémentaire pour une série courte de caisses carton ondulé personnalisées. | L69: Neutre
A70: A0069 | B70: 45918 | C70: Note | D70: E022 | E70: =IFERROR(INDEX(Entreprises!$B$2:$B$3000,MATCH(D70,Entreprises!$A$2:$A$3000,0)),"") | F70: C036 | G70: =IFERROR(INDEX(Contacts!$E$2:$E$3000,MATCH(F70,Contacts!$A$2:$A$3000,0)),"") | H70: U006 | I70: =IFERROR(INDEX(Commerciaux!$D$2:$D$3000,MATCH(H70,Commerciaux!$A$2:$A$3000,0)),"") | J70: Préparation négociation | K70: Note interne : préparer un comparatif de prix face à Kartéa Pharma Pack avant la prochaine négociation. | L70: Neutre
A71: A0070 | B71: 45926 | C71: Visite terrain | D71: E017 | E71: =IFERROR(INDEX(Entreprises!$B$2:$B$3000,MATCH(D71,Entreprises!$A$2:$A$3000,0)),"") | F71: C028 | G71: =IFERROR(INDEX(Contacts!$E$2:$E$3000,MATCH(F71,Contacts!$A$2:$A$3000,0)),"") | H71: U005 | I71: =IFERROR(INDEX(Commerciaux!$D$2:$D$3000,MATCH(H71,Commerciaux!$A$2:$A$3000,0)),"") | J71: Présentation des nouveautés 2025 | K71: Présentation des nouveautés 2025 à Romain Arnaud, notamment les étuis spiritueux luxe. Accueil favorable et demande d'échantillons. | L71: Négatif | N71: Envoyer le devis | O71: 45946 | P71: 120
A72: A0071 | B72: 45926 | C72: Appel | D72: E018 | E72: =IFERROR(INDEX(Entreprises!$B$2:$B$3000,MATCH(D72,Entreprises!$A$2:$A$3000,0)),"") | F72: C029 | G72: =IFERROR(INDEX(Contacts!$E$2:$E$3000,MATCH(F72,Contacts!$A$2:$A$3000,0)),"") | H72: U005 | I72: =IFERROR(INDEX(Commerciaux!$D$2:$D$3000,MATCH(H72,Commerciaux!$A$2:$A$3000,0)),"") | J72: Relance proposition | K72: Appel de relance sur la dernière proposition. Guillaume Petit demande quelques jours pour consolider les retours internes. | L72: Neutre | P72: 10
A73: A0072 | B73: 45929 | C73: Appel | D73: E021 | E73: =IFERROR(INDEX(Entreprises!$B$2:$B$3000,MATCH(D73,Entreprises!$A$2:$A$3000,0)),"") | F73: C034 | G73: =IFERROR(INDEX(Contacts!$E$2:$E$3000,MATCH(F73,Contacts!$A$2:$A$3000,0)),"") | H73: U005 | I73: =IFERROR(INDEX(Commerciaux!$D$2:$D$3000,MATCH(H73,Commerciaux!$A$2:$A$3000,0)),"") | J73: Suivi de livraison | K73: Appel de suivi après la dernière livraison. Thierry Lacroix confirme la conformité des lots reçus. | L73: Neutre | P73: 15
A74: A0073 | B74: 45930 | C74: Visite terrain | D74: E028 | E74: =IFERROR(INDEX(Entreprises!$B$2:$B$3000,MATCH(D74,Entreprises!$A$2:$A$3000,0)),"") | F74: C046 | G74: =IFERROR(INDEX(Contacts!$E$2:$E$3000,MATCH(F74,Contacts!$A$2:$A$3000,0)),"") | H74: U007 | I74: =IFERROR(INDEX(Commerciaux!$D$2:$D$3000,MATCH(H74,Commerciaux!$A$2:$A$3000,0)),"") | J74: Revue d'activité semestrielle | K74: Revue d'activité semestrielle avec Éric Lemoine. Satisfaction globale sur la qualité ; demande de visibilité sur l'évolution des prix des matières. Échange sur les étiquettes de la gamme export. | L74: À relancer | P74: 60
A75: A0074 | B75: 45933 | C75: Note | D75: E010 | E75: =IFERROR(INDEX(Entreprises!$B$2:$B$3000,MATCH(D75,Entreprises!$A$2:$A$3000,0)),"") | F75: C016 | G75: =IFERROR(INDEX(Contacts!$E$2:$E$3000,MATCH(F75,Contacts!$A$2:$A$3000,0)),"") | H75: U003 | I75: =IFERROR(INDEX(Commerciaux!$D$2:$D$3000,MATCH(H75,Commerciaux!$A$2:$A$3000,0)),"") | J75: Préparation négociation | K75: Note interne : préparer un comparatif de prix face à Kartéa Luxe avant la prochaine négociation. | L75: Neutre
A76: A0075 | B76: 45936 | C76: E-mail | D76: E008 | E76: =IFERROR(INDEX(Entreprises!$B$2:$B$3000,MATCH(D76,Entreprises!$A$2:$A$3000,0)),"") | F76: C013 | G76: =IFERROR(INDEX(Contacts!$E$2:$E$3000,MATCH(F76,Contacts!$A$2:$A$3000,0)),"") | H76: U003 | I76: =IFERROR(INDEX(Commerciaux!$D$2:$D$3000,MATCH(H76,Commerciaux!$A$2:$A$3000,0)),"") | J76: Envoi de fiche technique | K76: Envoi à Bastien Collet de la fiche technique et des certificats des étuis spiritueux luxe. | L76: Neutre
A77: A0076 | B77: 45939 | C77: Visite terrain | D77: E014 | E77: =IFERROR(INDEX(Entreprises!$B$2:$B$3000,MATCH(D77,Entreprises!$A$2:$A$3000,0)),"") | F77: C023 | G77: =IFERROR(INDEX(Contacts!$E$2:$E$3000,MATCH(F77,Contacts!$A$2:$A$3000,0)),"") | H77: U004 | I77: =IFERROR(INDEX(Commerciaux!$D$2:$D$3000,MATCH(H77,Commerciaux!$A$2:$A$3000,0)),"") | J77: Visite de la ligne de conditionnement | K77: Visite du site avec Émilie Gauthier et l'équipe de production. Observation de la ligne de conditionnement ; points d'amélioration identifiés sur les changements de format. Intérêt exprimé pour la suppression du polystyrène dans les calages. | L77: À relancer | N77: Envoyer la documentation technique | O77: 45950 | P77: 60
A78: A0077 | B78: 45940 | C78: Appel | D78: E009 | E78: =IFERROR(INDEX(Entreprises!$B$2:$B$3000,MATCH(D78,Entreprises!$A$2:$A$3000,0)),"") | F78: C015 | G78: =IFERROR(INDEX(Contacts!$E$2:$E$3000,MATCH(F78,Contacts!$A$2:$A$3000,0)),"") | H78: U003 | I78: =IFERROR(INDEX(Commerciaux!$D$2:$D$3000,MATCH(H78,Commerciaux!$A$2:$A$3000,0)),"") | J78: Ajustement de commande | K78: Appel de Pauline Henry pour ajuster les quantités de la prochaine commande d'étuis spiritueux luxe. Modification prise en compte. | L78: Positif | P78: 5
A79: A0078 | B79: 45940 | C79: Réunion visio | D79: E010 | E79: =IFERROR(INDEX(Entreprises!$B$2:$B$3000,MATCH(D79,Entreprises!$A$2:$A$3000,0)),"") | F79: C016 | G79: =IFERROR(INDEX(Contacts!$E$2:$E$3000,MATCH(F79,Contacts!$A$2:$A$3000,0)),"") | H79: U003 | I79: =IFERROR(INDEX(Commerciaux!$D$2:$D$3000,MATCH(H79,Commerciaux!$A$2:$A$3000,0)),"") | J79: Cadrage du besoin | K79: Réunion Teams avec Damien Royer pour cadrer le besoin concernant les coffrets premium 2027. Liste des prérequis techniques partagée. | L79: Neutre | M79: T016 | P79: 60
A80: A0079 | B80: 45943 | C80: E-mail | D80: E008 | E80: =IFERROR(INDEX(Entreprises!$B$2:$B$3000,MATCH(D80,Entreprises!$A$2:$A$3000,0)),"") | F80: C012 | G80: =IFERROR(INDEX(Contacts!$E$2:$E$3000,MATCH(F80,Contacts!$A$2:$A$3000,0)),"") | H80: U003 | I80: =IFERROR(INDEX(Commerciaux!$D$2:$D$3000,MATCH(H80,Commerciaux!$A$2:$A$3000,0)),"") | J80: Envoi de la grille tarifaire | K80: Envoi à Marie-Laure Rivière de la grille tarifaire actualisée, avec rappel des conditions de paiement (60 jours). | L80: Neutre
A81: A0080 | B81: 45947 | C81: Appel | D81: E018 | E81: =IFERROR(INDEX(Entreprises!$B$2:$B$3000,MATCH(D81,Entreprises!$A$2:$A$3000,0)),"") | F81: C029 | G81: =IFERROR(INDEX(Contacts!$E$2:$E$3000,MATCH(F81,Contacts!$A$2:$A$3000,0)),"") | H81: U005 | I81: =IFERROR(INDEX(Commerciaux!$D$2:$D$3000,MATCH(H81,Commerciaux!$A$2:$A$3000,0)),"") | J81: Point d'avancement projet | K81: Échange téléphonique avec Guillaume Petit sur le calendrier concernant les étuis de l'édition limitée. Décision interne attendue dans les prochaines semaines. | L81: À relancer | P81: 20
A82: A0081 | B82: 45950 | C82: E-mail | D82: E007 | E82: =IFERROR(INDEX(Entreprises!$B$2:$B$3000,MATCH(D82,Entreprises!$A$2:$A$3000,0)),"") | F82: C011 | G82: =IFERROR(INDEX(Contacts!$E$2:$E$3000,MATCH(F82,Contacts!$A$2:$A$3000,0)),"") | H82: U002 | I82: =IFERROR(INDEX(Commerciaux!$D$2:$D$3000,MATCH(H82,Commerciaux!$A$2:$A$3000,0)),"") | J82: Envoi de la grille tarifaire | K82: Envoi à François Girard de la grille tarifaire actualisée, avec rappel des conditions de paiement (60 jours). | L82: Neutre
A83: A0082 | B83: 45951 | C83: Appel | D83: E003 | E83: =IFERROR(INDEX(Entreprises!$B$2:$B$3000,MATCH(D83,Entreprises!$A$2:$A$3000,0)),"") | F83: C006 | G83: =IFERROR(INDEX(Contacts!$E$2:$E$3000,MATCH(F83,Contacts!$A$2:$A$3000,0)),"") | H83: U002 | I83: =IFERROR(INDEX(Commerciaux!$D$2:$D$3000,MATCH(H83,Commerciaux!$A$2:$A$3000,0)),"") | J83: Ajustement de commande | K83: Appel de Olivier Chen pour ajuster les quantités de la prochaine commande de notices pharmaceutiques pliées. Modification prise en compte. | L83: À relancer | N83: Planifier une visite de site | O83: 45967 | P83: 30
A84: A0083 | B84: 45953 | C84: Note | D84: E004 | E84: =IFERROR(INDEX(Entreprises!$B$2:$B$3000,MATCH(D84,Entreprises!$A$2:$A$3000,0)),"") | F84: C007 | G84: =IFERROR(INDEX(Contacts!$E$2:$E$3000,MATCH(F84,Contacts!$A$2:$A$3000,0)),"") | H84: U002 | I84: =IFERROR(INDEX(Commerciaux!$D$2:$D$3000,MATCH(H84,Commerciaux!$A$2:$A$3000,0)),"") | J84: Information organisation | K84: Note interne : Claire Fontaine a mentionné une réorganisation du service achats ; à surveiller. | L84: Neutre
A85: A0084 | B85: 45960 | C85: E-mail | D85: E030 | E85: =IFERROR(INDEX(Entreprises!$B$2:$B$3000,MATCH(D85,Entreprises!$A$2:$A$3000,0)),"") | F85: C049 | G85: =IFERROR(INDEX(Contacts!$E$2:$E$3000,MATCH(F85,Contacts!$A$2:$A$3000,0)),"") | H85: U007 | I85: =IFERROR(INDEX(Commerciaux!$D$2:$D$3000,MATCH(H85,Commerciaux!$A$2:$A$3000,0)),"") | J85: Envoi du planning | K85: Envoi à Nadia Haddad du planning prévisionnel et des points ouverts concernant les emballages sans plastique de la distribution électrique. | L85: Neutre
A86: A0085 | B86: 45961 | C86: Appel | D86: E024 | E86: =IFERROR(INDEX(Entreprises!$B$2:$B$3000,MATCH(D86,Entreprises!$A$2:$A$3000,0)),"") | F86: C039 | G86: =IFERROR(INDEX(Contacts!$E$2:$E$3000,MATCH(F86,Contacts!$A$2:$A$3000,0)),"") | H86: U006 | I86: =IFERROR(INDEX(Commerciaux!$D$2:$D$3000,MATCH(H86,Commerciaux!$A$2:$A$3000,0)),"") | J86: Relance proposition | K86: Appel de relance sur la dernière proposition. Agnès Picard demande quelques jours pour consolider les retours internes. | L86: Neutre | N86: Transmettre des échantillons | O86: 45973 | P86: 30
A87: A0086 | B87: 45975 | C87: Visite terrain | D87: E018 | E87: =IFERROR(INDEX(Entreprises!$B$2:$B$3000,MATCH(D87,Entreprises!$A$2:$A$3000,0)),"") | F87: C029 | G87: =IFERROR(INDEX(Contacts!$E$2:$E$3000,MATCH(F87,Contacts!$A$2:$A$3000,0)),"") | H87: U005 | I87: =IFERROR(INDEX(Commerciaux!$D$2:$D$3000,MATCH(H87,Commerciaux!$A$2:$A$3000,0)),"") | J87: Revue d'activité semestrielle | K87: Revue d'activité semestrielle avec Guillaume Petit. Satisfaction globale sur la qualité ; demande de visibilité sur l'évolution des prix des matières. Échange sur les étuis de l'édition limitée. | L87: Positif | P87: 60
A88: A0087 | B88: 45978 | C88: Visite terrain | D88: E026 | E88: =IFERROR(INDEX(Entreprises!$B$2:$B$3000,MATCH(D88,Entreprises!$A$2:$A$3000,0)),"") | F88: C042 | G88: =IFERROR(INDEX(Contacts!$E$2:$E$3000,MATCH(F88,Contacts!$A$2:$A$3000,0)),"") | H88: U007 | I88: =IFERROR(INDEX(Commerciaux!$D$2:$D$3000,MATCH(H88,Commerciaux!$A$2:$A$3000,0)),"") | J88: Présentation des nouveautés 2025 | K88: Présentation des nouveautés 2025 à Véronique Bertin, notamment les étiquettes adhésives haute définition. Accueil favorable et demande d'échantillons. | L88: Négatif | N88: Envoyer la documentation technique | O88: 45999 | P88: 90
A89: A0088 | B89: 45979 | C89: Appel | D89: E026 | E89: =IFERROR(INDEX(Entreprises!$B$2:$B$3000,MATCH(D89,Entreprises!$A$2:$A$3000,0)),"") | F89: C043 | G89: =IFERROR(INDEX(Contacts!$E$2:$E$3000,MATCH(F89,Contacts!$A$2:$A$3000,0)),"") | H89: U007 | I89: =IFERROR(INDEX(Commerciaux!$D$2:$D$3000,MATCH(H89,Commerciaux!$A$2:$A$3000,0)),"") | J89: Point d'avancement projet | K89: Échange téléphonique avec Samuel Robin sur le calendrier concernant la réduction des emballages secondaires. Décision interne attendue dans les prochaines semaines. | L89: Neutre | P89: 10
A90: A0089 | B90: 45986 | C90: Appel | D90: E024 | E90: =IFERROR(INDEX(Entreprises!$B$2:$B$3000,MATCH(D90,Entreprises!$A$2:$A$3000,0)),"") | F90: C039 | G90: =IFERROR(INDEX(Contacts!$E$2:$E$3000,MATCH(F90,Contacts!$A$2:$A$3000,0)),"") | H90: U006 | I90: =IFERROR(INDEX(Commerciaux!$D$2:$D$3000,MATCH(H90,Commerciaux!$A$2:$A$3000,0)),"") | J90: Point d'avancement projet | K90: Échange téléphonique avec Agnès Picard sur le calendrier concernant l'appel d'offres notices et étuis. Décision interne attendue dans les prochaines semaines. | L90: Positif | M90: T038 | P90: 5
A91: A0090 | B91: 45988 | C91: Appel | D91: E019 | E91: =IFERROR(INDEX(Entreprises!$B$2:$B$3000,MATCH(D91,Entreprises!$A$2:$A$3000,0)),"") | F91: C031 | G91: =IFERROR(INDEX(Contacts!$E$2:$E$3000,MATCH(F91,Contacts!$A$2:$A$3000,0)),"") | H91: U005 | I91: =IFERROR(INDEX(Commerciaux!$D$2:$D$3000,MATCH(H91,Commerciaux!$A$2:$A$3000,0)),"") | J91: Relance proposition | K91: Appel de relance sur la dernière proposition. Benoît Carrière demande quelques jours pour consolider les retours internes. | L91: À relancer | P91: 20
A92: A0091 | B92: 45989 | C92: Visite terrain | D92: E023 | E92: =IFERROR(INDEX(Entreprises!$B$2:$B$3000,MATCH(D92,Entreprises!$A$2:$A$3000,0)),"") | F92: C038 | G92: =IFERROR(INDEX(Contacts!$E$2:$E$3000,MATCH(F92,Contacts!$A$2:$A$3000,0)),"") | H92: U006 | I92: =IFERROR(INDEX(Commerciaux!$D$2:$D$3000,MATCH(H92,Commerciaux!$A$2:$A$3000,0)),"") | J92: Visite de suivi | K92: Visite de suivi avec David Nguyen. Revue des commandes en cours et des prévisions du trimestre sur les étuis carton pharmaceutiques imprimés. Pas de difficulté particulière signalée. David Nguyen évoque les étiquettes d'inviolabilité sur toute la gamme. | L92: Positif | P92: 60
A93: A0092 | B93: 45992 | C93: Réunion visio | D93: E018 | E93: =IFERROR(INDEX(Entreprises!$B$2:$B$3000,MATCH(D93,Entreprises!$A$2:$A$3000,0)),"") | F93: C029 | G93: =IFERROR(INDEX(Contacts!$E$2:$E$3000,MATCH(F93,Contacts!$A$2:$A$3000,0)),"") | H93: U005 | I93: =IFERROR(INDEX(Commerciaux!$D$2:$D$3000,MATCH(H93,Commerciaux!$A$2:$A$3000,0)),"") | J93: Cadrage du besoin | K93: Réunion Teams avec Guillaume Petit pour cadrer le besoin concernant les étuis de l'édition limitée. Liste des prérequis techniques partagée. | L93: Positif | N93: Transmettre des échantillons | O93: 46006 | P93: 45
A94: A0093 | B94: 45996 | C94: E-mail | D94: E013 | E94: =IFERROR(INDEX(Entreprises!$B$2:$B$3000,MATCH(D94,Entreprises!$A$2:$A$3000,0)),"") | F94: C022 | G94: =IFERROR(INDEX(Contacts!$E$2:$E$3000,MATCH(F94,Contacts!$A$2:$A$3000,0)),"") | H94: U004 | I94: =IFERROR(INDEX(Commerciaux!$D$2:$D$3000,MATCH(H94,Commerciaux!$A$2:$A$3000,0)),"") | J94: Envoi du planning | K94: Envoi à Yannick Morin du planning prévisionnel et des points ouverts concernant le passage à des étuis en carton recyclé. | L94: Neutre
A95: A0094 | B95: 46006 | C95: Visite terrain | D95: E007 | E95: =IFERROR(INDEX(Entreprises!$B$2:$B$3000,MATCH(D95,Entreprises!$A$2:$A$3000,0)),"") | F95: C011 | G95: =IFERROR(INDEX(Contacts!$E$2:$E$3000,MATCH(F95,Contacts!$A$2:$A$3000,0)),"") | H95: U002 | I95: =IFERROR(INDEX(Commerciaux!$D$2:$D$3000,MATCH(H95,Commerciaux!$A$2:$A$3000,0)),"") | J95: Visite de suivi | K95: Visite de suivi avec François Girard. Revue des commandes en cours et des prévisions du trimestre sur les étiquettes adhésives haute définition. Pas de difficulté particulière signalée. François Girard évoque l'harmonisation des étiquettes logistiques entre sites. | L95: Neutre | N95: Relancer pour obtenir un retour | O95: 46024 | P95: 60
A96: A0095 | B96: 46006 | C96: E-mail | D96: E013 | E96: =IFERROR(INDEX(Entreprises!$B$2:$B$3000,MATCH(D96,Entreprises!$A$2:$A$3000,0)),"") | F96: C021 | G96: =IFERROR(INDEX(Contacts!$E$2:$E$3000,MATCH(F96,Contacts!$A$2:$A$3000,0)),"") | H96: U004 | I96: =IFERROR(INDEX(Commerciaux!$D$2:$D$3000,MATCH(H96,Commerciaux!$A$2:$A$3000,0)),"") | J96: Envoi de fiche technique | K96: Envoi à Christine Blanc de la fiche technique et des certificats des notices pharmaceutiques pliées. | L96: À relancer
A97: A0096 | B97: 46006 | C97: E-mail | D97: E025 | E97: =IFERROR(INDEX(Entreprises!$B$2:$B$3000,MATCH(D97,Entreprises!$A$2:$A$3000,0)),"") | F97: C040 | G97: =IFERROR(INDEX(Contacts!$E$2:$E$3000,MATCH(F97,Contacts!$A$2:$A$3000,0)),"") | H97: U007 | I97: =IFERROR(INDEX(Commerciaux!$D$2:$D$3000,MATCH(H97,Commerciaux!$A$2:$A$3000,0)),"") | J97: Envoi de la grille tarifaire | K97: Envoi à Frédéric Masson de la grille tarifaire actualisée, avec rappel des conditions de paiement (60 jours). | L97: À relancer
A98: A0097 | B98: 46008 | C98: Réunion visio | D98: E011 | E98: =IFERROR(INDEX(Entreprises!$B$2:$B$3000,MATCH(D98,Entreprises!$A$2:$A$3000,0)),"") | F98: C018 | G98: =IFERROR(INDEX(Contacts!$E$2:$E$3000,MATCH(F98,Contacts!$A$2:$A$3000,0)),"") | H98: U003 | I98: =IFERROR(INDEX(Commerciaux!$D$2:$D$3000,MATCH(H98,Commerciaux!$A$2:$A$3000,0)),"") | J98: Revue des prévisions | K98: Visio de revue des prévisions de volumes avec Julie Schmitt et la supply chain du client. | L98: Neutre | P98: 45
A99: A0098 | B99: 46008 | C99: E-mail | D99: E022 | E99: =IFERROR(INDEX(Entreprises!$B$2:$B$3000,MATCH(D99,Entreprises!$A$2:$A$3000,0)),"") | F99: C035 | G99: =IFERROR(INDEX(Contacts!$E$2:$E$3000,MATCH(F99,Contacts!$A$2:$A$3000,0)),"") | H99: U006 | I99: =IFERROR(INDEX(Commerciaux!$D$2:$D$3000,MATCH(H99,Commerciaux!$A$2:$A$3000,0)),"") | J99: Envoi du planning | K99: Envoi à Hélène Bouvier du planning prévisionnel et des points ouverts concernant le déploiement de la sérialisation sur un site supplémentaire. | L99: À relancer
A100: A0099 | B100: 46024 | C100: Visite terrain | D100: E001 | E100: =IFERROR(INDEX(Entreprises!$B$2:$B$3000,MATCH(D100,Entreprises!$A$2:$A$3000,0)),"") | F100: C001 | G100: =IFERROR(INDEX(Contacts!$E$2:$E$3000,MATCH(F100,Contacts!$A$2:$A$3000,0)),"") | H100: U002 | I100: =IFERROR(INDEX(Commerciaux!$D$2:$D$3000,MATCH(H100,Commerciaux!$A$2:$A$3000,0)),"") | J100: Revue d'activité semestrielle | K100: Revue d'activité semestrielle avec Nathalie Dubreuil. Satisfaction globale sur la qualité ; demande de visibilité sur l'évolution des prix des matières. Échange sur le renouvellement de l'accord-cadre étiquettes 2027. | L100: Neutre | N100: Planifier une visite de site | O100: 46031 | P100: 60
...

Sheet Rendez-vous
A1: ID rendez-vous | B1: Date | C1: Heure de début | D1: Heure de fin | E1: Type de rendez-vous | F1: ID entreprise | G1: Entreprise | H1: ID contact | I1: Contact | J1: Fonction du contact | K1: ID commercial | L1: Commercial | M1: Lieu | N1: Objet du rendez-vous | O1: ID transaction associée | P1: Statut | Q1: Brief préparé | R1: Compte rendu de visite
A2: R001 | B2: 46307 | C2: 0.39583333 | D2: 0.45833333 | E2: Visite sur site | F2: E001 | G2: =IFERROR(INDEX(Entreprises!$B$2:$B$3000,MATCH(F2,Entreprises!$A$2:$A$3000,0)),"") | H2: C001 | I2: =IFERROR(INDEX(Contacts!$E$2:$E$3000,MATCH(H2,Contacts!$A$2:$A$3000,0)),"") | J2: =IFERROR(INDEX(Contacts!$I$2:$I$3000,MATCH(H2,Contacts!$A$2:$A$3000,0)),"") | K2: U002 | L2: =IFERROR(INDEX(Commerciaux!$D$2:$D$3000,MATCH(K2,Commerciaux!$A$2:$A$3000,0)),"") | M2: Bonduelle - Villeneuve-d'Ascq | N2: Revue de la proposition de renouvellement de l'accord-cadre étiquettes 2027 | O2: T001 | P2: Confirmé | Q2: Oui
A3: R002 | B3: 46307 | C3: 0.58333333 | D3: 0.66666667 | E3: Visite sur site | F3: E002 | G3: =IFERROR(INDEX(Entreprises!$B$2:$B$3000,MATCH(F3,Entreprises!$A$2:$A$3000,0)),"") | H3: C004 | I3: =IFERROR(INDEX(Contacts!$E$2:$E$3000,MATCH(H3,Contacts!$A$2:$A$3000,0)),"") | J3: =IFERROR(INDEX(Contacts!$I$2:$I$3000,MATCH(H3,Contacts!$A$2:$A$3000,0)),"") | K3: U002 | L3: =IFERROR(INDEX(Commerciaux!$D$2:$D$3000,MATCH(K3,Commerciaux!$A$2:$A$3000,0)),"") | M3: Lesaffre - Marcq-en-Barœul | N3: Démonstration de l'encartonneuse EC-200 et échange sur le chiffrage | O3: T004 | P3: Confirmé | Q3: Oui
A4: R003 | B4: 46307 | C4: 0.70833333 | D4: 0.73958333 | E4: Visio | F4: E003 | G4: =IFERROR(INDEX(Entreprises!$B$2:$B$3000,MATCH(F4,Entreprises!$A$2:$A$3000,0)),"") | H4: C005 | I4: =IFERROR(INDEX(Contacts!$E$2:$E$3000,MATCH(H4,Contacts!$A$2:$A$3000,0)),"") | J4: =IFERROR(INDEX(Contacts!$I$2:$I$3000,MATCH(H4,Contacts!$A$2:$A$3000,0)),"") | K4: U002 | L4: =IFERROR(INDEX(Commerciaux!$D$2:$D$3000,MATCH(K4,Commerciaux!$A$2:$A$3000,0)),"") | M4: Microsoft Teams | N4: Préparation de l'audit fournisseur de novembre | O4: T006 | P4: Confirmé | Q4: Oui
A5: R004 | B5: 46308 | C5: 0.41666667 | D5: 0.5 | E5: Visite sur site | F5: E012 | G5: =IFERROR(INDEX(Entreprises!$B$2:$B$3000,MATCH(F5,Entreprises!$A$2:$A$3000,0)),"") | H5: C020 | I5: =IFERROR(INDEX(Contacts!$E$2:$E$3000,MATCH(H5,Contacts!$A$2:$A$3000,0)),"") | J5: =IFERROR(INDEX(Contacts!$I$2:$I$3000,MATCH(H5,Contacts!$A$2:$A$3000,0)),"") | K5: U004 | L5: =IFERROR(INDEX(Commerciaux!$D$2:$D$3000,MATCH(K5,Commerciaux!$A$2:$A$3000,0)),"") | M5: bioMérieux - Marcy-l'Étoile | N5: Démonstration DataMatrix sur ligne pilote | O5: T020 | P5: Confirmé | Q5: Non
A6: R005 | B6: 46308 | C6: 0.60416667 | D6: 0.66666667 | E6: Visite sur site | F6: E008 | G6: =IFERROR(INDEX(Entreprises!$B$2:$B$3000,MATCH(F6,Entreprises!$A$2:$A$3000,0)),"") | H6: C013 | I6: =IFERROR(INDEX(Contacts!$E$2:$E$3000,MATCH(H6,Contacts!$A$2:$A$3000,0)),"") | J6: =IFERROR(INDEX(Contacts!$I$2:$I$3000,MATCH(H6,Contacts!$A$2:$A$3000,0)),"") | K6: U003 | L6: =IFERROR(INDEX(Commerciaux!$D$2:$D$3000,MATCH(K6,Commerciaux!$A$2:$A$3000,0)),"") | M6: Moët & Chandon - Épernay | N6: Présentation des prototypes d'étuis allégés | O6: T013 | P6: Confirmé | Q6: Non
A7: R006 | B7: 46309 | C7: 0.375 | D7: 0.4375 | E7: Visite sur site | F7: E022 | G7: =IFERROR(INDEX(Entreprises!$B$2:$B$3000,MATCH(F7,Entreprises!$A$2:$A$3000,0)),"") | H7: C036 | I7: =IFERROR(INDEX(Contacts!$E$2:$E$3000,MATCH(H7,Contacts!$A$2:$A$3000,0)),"") | J7: =IFERROR(INDEX(Contacts!$I$2:$I$3000,MATCH(H7,Contacts!$A$2:$A$3000,0)),"") | K7: U006 | L7: =IFERROR(INDEX(Commerciaux!$D$2:$D$3000,MATCH(K7,Commerciaux!$A$2:$A$3000,0)),"") | M7: Sanofi - Paris | N7: Comité de pilotage sérialisation | O7: T034 | P7: Planifié | Q7: Non
A8: R007 | B8: 46309 | C8: 0.45833333 | D8: 0.48958333 | E8: Visio | F8: E005 | G8: =IFERROR(INDEX(Entreprises!$B$2:$B$3000,MATCH(F8,Entreprises!$A$2:$A$3000,0)),"") | H8: C009 | I8: =IFERROR(INDEX(Contacts!$E$2:$E$3000,MATCH(H8,Contacts!$A$2:$A$3000,0)),"") | J8: =IFERROR(INDEX(Contacts!$I$2:$I$3000,MATCH(H8,Contacts!$A$2:$A$3000,0)),"") | K8: U002 | L8: =IFERROR(INDEX(Commerciaux!$D$2:$D$3000,MATCH(K8,Commerciaux!$A$2:$A$3000,0)),"") | M8: Microsoft Teams | N8: Revue des échantillons et de la fiche RSE | O8: T010 | P8: Planifié | Q8: Oui
A9: R008 | B9: 46310 | C9: 0.41666667 | D9: 0.47916667 | E9: Visite sur site | F9: E017 | G9: =IFERROR(INDEX(Entreprises!$B$2:$B$3000,MATCH(F9,Entreprises!$A$2:$A$3000,0)),"") | H9: C027 | I9: =IFERROR(INDEX(Contacts!$E$2:$E$3000,MATCH(H9,Contacts!$A$2:$A$3000,0)),"") | J9: =IFERROR(INDEX(Contacts!$I$2:$I$3000,MATCH(H9,Contacts!$A$2:$A$3000,0)),"") | K9: U005 | L9: =IFERROR(INDEX(Commerciaux!$D$2:$D$3000,MATCH(K9,Commerciaux!$A$2:$A$3000,0)),"") | M9: Rémy Cointreau - Cognac | N9: Capacités saison 2027 et concept de coffret réutilisable | O9: T027 | P9: Confirmé | Q9: Non
A10: R009 | B10: 46310 | C10: 0.625 | D10: 0.6875 | E10: Visite sur site | F10: E014 | G10: =IFERROR(INDEX(Entreprises!$B$2:$B$3000,MATCH(F10,Entreprises!$A$2:$A$3000,0)),"") | H10: C024 | I10: =IFERROR(INDEX(Contacts!$E$2:$E$3000,MATCH(H10,Contacts!$A$2:$A$3000,0)),"") | J10: =IFERROR(INDEX(Contacts!$I$2:$I$3000,MATCH(H10,Contacts!$A$2:$A$3000,0)),"") | K10: U004 | L10: =IFERROR(INDEX(Commerciaux!$D$2:$D$3000,MATCH(K10,Commerciaux!$A$2:$A$3000,0)),"") | M10: SEB - Écully | N10: Négociation du devis d'industrialisation | O10: T023 | P10: Confirmé | Q10: Non
A11: R010 | B11: 46311 | C11: 0.39583333 | D11: 0.45833333 | E11: Visite sur site | F11: E010 | G11: =IFERROR(INDEX(Entreprises!$B$2:$B$3000,MATCH(F11,Entreprises!$A$2:$A$3000,0)),"") | H11: C016 | I11: =IFERROR(INDEX(Contacts!$E$2:$E$3000,MATCH(H11,Contacts!$A$2:$A$3000,0)),"") | J11: =IFERROR(INDEX(Contacts!$I$2:$I$3000,MATCH(H11,Contacts!$A$2:$A$3000,0)),"") | K11: U003 | L11: =IFERROR(INDEX(Commerciaux!$D$2:$D$3000,MATCH(K11,Commerciaux!$A$2:$A$3000,0)),"") | M11: Vranken-Pommery - Reims | N11: Remise de la proposition chiffrée coffrets premium | O11: T016 | P11: Planifié | Q11: Non
A12: R011 | B12: 46311 | C12: 0.52083333 | D12: 0.60416667 | E12: Déjeuner d'affaires | F12: E025 | G12: =IFERROR(INDEX(Entreprises!$B$2:$B$3000,MATCH(F12,Entreprises!$A$2:$A$3000,0)),"") | H12: C040 | I12: =IFERROR(INDEX(Contacts!$E$2:$E$3000,MATCH(H12,Contacts!$A$2:$A$3000,0)),"") | J12: =IFERROR(INDEX(Contacts!$I$2:$I$3000,MATCH(H12,Contacts!$A$2:$A$3000,0)),"") | K12: U007 | L12: =IFERROR(INDEX(Commerciaux!$D$2:$D$3000,MATCH(K12,Commerciaux!$A$2:$A$3000,0)),"") | M12: Paris 8e | N12: Point annuel et programme d'éco-conception des coffrets | O12: T039 | P12: Confirmé | Q12: Non
A13: R012 | B13: 46314 | C13: 0.41666667 | D13: 0.47916667 | E13: Visite sur site | F13: E004 | G13: =IFERROR(INDEX(Entreprises!$B$2:$B$3000,MATCH(F13,Entreprises!$A$2:$A$3000,0)),"") | H13: C007 | I13: =IFERROR(INDEX(Contacts!$E$2:$E$3000,MATCH(H13,Contacts!$A$2:$A$3000,0)),"") | J13: =IFERROR(INDEX(Contacts!$I$2:$I$3000,MATCH(H13,Contacts!$A$2:$A$3000,0)),"") | K13: U002 | L13: =IFERROR(INDEX(Commerciaux!$D$2:$D$3000,MATCH(K13,Commerciaux!$A$2:$A$3000,0)),"") | M13: Interparfums - Paris | N13: Présentation des maquettes de coffrets éco-conçus | O13: T008 | P13: Planifié | Q13: Non
... A32: R031 | B32: 46329 | C32: 0.41666667 | D32: 0.45833333 | E32: Visite sur site | F32: E029 | G32: =IFERROR(INDEX(Entreprises!$B$2:$B$3000,MATCH(F32,Entreprises!$A$2:$A$3000,0)),"") | H32: C048 | I32: =IFERROR(INDEX(Contacts!$E$2:$E$3000,MATCH(H32,Contacts!$A$2:$A$3000,0)),"") | J32: =IFERROR(INDEX(Contacts!$I$2:$I$3000,MATCH(H32,Contacts!$A$2:$A$3000,0)),"") | K32: U007 | L32: =IFERROR(INDEX(Commerciaux!$D$2:$D$3000,MATCH(K32,Commerciaux!$A$2:$A$3000,0)),"") | M32: Saint-Gobain - Courbevoie | N32: Rendez-vous de découverte du besoin distribution | O32: T045 | P32: Confirmé | Q32: Non
A33: R032 | B33: 46330 | C33: 0.39583333 | D33: 0.45833333 | E33: Visite sur site | F33: E012 | G33: =IFERROR(INDEX(Entreprises!$B$2:$B$3000,MATCH(F33,Entreprises!$A$2:$A$3000,0)),"") | H33: C019 | I33: =IFERROR(INDEX(Contacts!$E$2:$E$3000,MATCH(H33,Contacts!$A$2:$A$3000,0)),"") | J33: =IFERROR(INDEX(Contacts!$I$2:$I$3000,MATCH(H33,Contacts!$A$2:$A$3000,0)),"") | K33: U004 | L33: =IFERROR(INDEX(Commerciaux!$D$2:$D$3000,MATCH(K33,Commerciaux!$A$2:$A$3000,0)),"") | M33: bioMérieux - Marcy-l'Étoile | N33: Point achats annuel | P33: Planifié | Q33: Non
A34: R033 | B34: 46331 | C34: 0.41666667 | D34: 0.47916667 | E34: Visite sur site | F34: E002 | G34: =IFERROR(INDEX(Entreprises!$B$2:$B$3000,MATCH(F34,Entreprises!$A$2:$A$3000,0)),"") | H34: C003 | I34: =IFERROR(INDEX(Contacts!$E$2:$E$3000,MATCH(H34,Contacts!$A$2:$A$3000,0)),"") | J34: =IFERROR(INDEX(Contacts!$I$2:$I$3000,MATCH(H34,Contacts!$A$2:$A$3000,0)),"") | K34: U002 | L34: =IFERROR(INDEX(Commerciaux!$D$2:$D$3000,MATCH(K34,Commerciaux!$A$2:$A$3000,0)),"") | M34: Lesaffre - Marcq-en-Barœul | N34: Revue annuelle achats | P34: Planifié | Q34: Non
A35: R034 | B35: 46331 | C35: 0.60416667 | D35: 0.66666667 | E35: Visite sur site | F35: E022 | G35: =IFERROR(INDEX(Entreprises!$B$2:$B$3000,MATCH(F35,Entreprises!$A$2:$A$3000,0)),"") | H35: C035 | I35: =IFERROR(INDEX(Contacts!$E$2:$E$3000,MATCH(H35,Contacts!$A$2:$A$3000,0)),"") | J35: =IFERROR(INDEX(Contacts!$I$2:$I$3000,MATCH(H35,Contacts!$A$2:$A$3000,0)),"") | K35: U006 | L35: =IFERROR(INDEX(Commerciaux!$D$2:$D$3000,MATCH(K35,Commerciaux!$A$2:$A$3000,0)),"") | M35: Sanofi - Paris | N35: Lancement de la consultation accord-cadre 2027 | O35: T035 | P35: Planifié | Q35: Non
A36: R035 | B36: 46332 | C36: 0.41666667 | D36: 0.5 | E36: Visite sur site | F36: E003 | G36: =IFERROR(INDEX(Entreprises!$B$2:$B$3000,MATCH(F36,Entreprises!$A$2:$A$3000,0)),"") | H36: C006 | I36: =IFERROR(INDEX(Contacts!$E$2:$E$3000,MATCH(H36,Contacts!$A$2:$A$3000,0)),"") | J36: =IFERROR(INDEX(Contacts!$I$2:$I$3000,MATCH(H36,Contacts!$A$2:$A$3000,0)),"") | K36: U002 | L36: =IFERROR(INDEX(Commerciaux!$D$2:$D$3000,MATCH(K36,Commerciaux!$A$2:$A$3000,0)),"") | M36: Guerbet - Villepinte | N36: Atelier notices multilingues | O36: T006 | P36: Planifié | Q36: Non
A37: R036 | B37: 46335 | C37: 0.41666667 | D37: 0.47916667 | E37: Visite sur site | F37: E017 | G37: =IFERROR(INDEX(Entreprises!$B$2:$B$3000,MATCH(F37,Entreprises!$A$2:$A$3000,0)),"") | H37: C028 | I37: =IFERROR(INDEX(Contacts!$E$2:$E$3000,MATCH(H37,Contacts!$A$2:$A$3000,0)),"") | J37: =IFERROR(INDEX(Contacts!$I$2:$I$3000,MATCH(H37,Contacts!$A$2:$A$3000,0)),"") | K37: U005 | L37: =IFERROR(INDEX(Commerciaux!$D$2:$D$3000,MATCH(K37,Commerciaux!$A$2:$A$3000,0)),"") | M37: Rémy Cointreau - Cognac | N37: Présentation du prototype de coffret réutilisable | O37: T027 | P37: Planifié | Q37: Non
A38: R037 | B38: 46336 | C38: 0.41666667 | D38: 0.47916667 | E38: Visite sur site | F38: E008 | G38: =IFERROR(INDEX(Entreprises!$B$2:$B$3000,MATCH(F38,Entreprises!$A$2:$A$3000,0)),"") | H38: C012 | I38: =IFERROR(INDEX(Contacts!$E$2:$E$3000,MATCH(H38,Contacts!$A$2:$A$3000,0)),"") | J38: =IFERROR(INDEX(Contacts!$I$2:$I$3000,MATCH(H38,Contacts!$A$2:$A$3000,0)),"") | K38: U003 | L38: =IFERROR(INDEX(Commerciaux!$D$2:$D$3000,MATCH(K38,Commerciaux!$A$2:$A$3000,0)),"") | M38: Moët & Chandon - Épernay | N38: Bilan de production des coffrets de fin d'année | P38: Planifié | Q38: Non
A39: R038 | B39: 46338 | C39: 0.58333333 | D39: 0.61458333 | E39: Visio | F39: E026 | G39: =IFERROR(INDEX(Entreprises!$B$2:$B$3000,MATCH(F39,Entreprises!$A$2:$A$3000,0)),"") | H39: C043 | I39: =IFERROR(INDEX(Contacts!$E$2:$E$3000,MATCH(H39,Contacts!$A$2:$A$3000,0)),"") | J39: =IFERROR(INDEX(Contacts!$I$2:$I$3000,MATCH(H39,Contacts!$A$2:$A$3000,0)),"") | K39: U007 | L39: =IFERROR(INDEX(Commerciaux!$D$2:$D$3000,MATCH(K39,Commerciaux!$A$2:$A$3000,0)),"") | M39: Microsoft Teams | N39: Prévisions de volumes 2027 | P39: Planifié | Q39: Non
A40: R039 | B40: 46339 | C40: 0.41666667 | D40: 0.5 | E40: Visite sur site | F40: E021 | G40: =IFERROR(INDEX(Entreprises!$B$2:$B$3000,MATCH(F40,Entreprises!$A$2:$A$3000,0)),"") | H40: C034 | I40: =IFERROR(INDEX(Contacts!$E$2:$E$3000,MATCH(H40,Contacts!$A$2:$A$3000,0)),"") | J40: =IFERROR(INDEX(Contacts!$I$2:$I$3000,MATCH(H40,Contacts!$A$2:$A$3000,0)),"") | K40: U005 | L40: =IFERROR(INDEX(Commerciaux!$D$2:$D$3000,MATCH(K40,Commerciaux!$A$2:$A$3000,0)),"") | M40: Volterra - Poitiers | N40: Visite d'industrialisation de la première usine | O40: T032 | P40: Planifié | Q40: Non

Sheet Tickets
A1: ID ticket | B1: Objet | C1: ID entreprise | D1: Entreprise | E1: ID contact | F1: Contact | G1: Catégorie | H1: Priorité | I1: Statut | J1: Date de création | K1: Date de clôture | L1: Délai de résolution (jours) | M1: Description | N1: Responsable du ticket
A2: K001 | B2: Retard de livraison étiquettes (commande de septembre) | C2: E001 | D2: =IFERROR(INDEX(Entreprises!$B$2:$B$3000,MATCH(C2,Entreprises!$A$2:$A$3000,0)),"") | E2: C001 | F2: =IFERROR(INDEX(Contacts!$E$2:$E$3000,MATCH(E2,Contacts!$A$2:$A$3000,0)),"") | G2: Livraison | H2: Haute | I2: En cours | J2: 46289 | L2: =IF(K2="","",K2-J2) | M2: Livraison prévue le 15/09, réceptionnée le 24/09. Impact client : décalage d'une production. Analyse de cause en cours côté logistique (saturation transporteur). | N2: Lucie Martin - Service client
A3: K002 | B3: Non-conformité d'impression du numéro de lot | C3: E003 | D3: =IFERROR(INDEX(Entreprises!$B$2:$B$3000,MATCH(C3,Entreprises!$A$2:$A$3000,0)),"") | E3: C005 | F3: =IFERROR(INDEX(Contacts!$E$2:$E$3000,MATCH(E3,Contacts!$A$2:$A$3000,0)),"") | G3: Qualité produit | H3: Critique | I3: Fermé | J3: 46191 | K3: 46233 | L3: =IF(K3="","",K3-J3) | M3: Numéro de lot illisible sur environ 2 % des étuis. Lot remplacé sous six jours. Rapport 8D transmis en version provisoire, version finale attendue par le client. | N3: Karim Haddou - Qualité
A4: K003 | B4: Défaut de pliage sur étuis dermo-cosmétiques | C4: E019 | D4: =IFERROR(INDEX(Entreprises!$B$2:$B$3000,MATCH(C4,Entreprises!$A$2:$A$3000,0)),"") | E4: C031 | F4: =IFERROR(INDEX(Contacts!$E$2:$E$3000,MATCH(E4,Contacts!$A$2:$A$3000,0)),"") | G4: Qualité produit | H4: Haute | I4: En cours | J4: 46279 | L4: =IF(K4="","",K4-J4) | M4: Rainage trop marqué sur une référence, provoquant des bourrages en encartonnage. Échantillons en analyse au laboratoire. | N4: Karim Haddou - Qualité
A5: K004 | B5: Panne étiqueteuse ligne 3 | C5: E011 | D5: =IFERROR(INDEX(Entreprises!$B$2:$B$3000,MATCH(C5,Entreprises!$A$2:$A$3000,0)),"") | E5: C018 | F5: =IFERROR(INDEX(Contacts!$E$2:$E$3000,MATCH(E5,Contacts!$A$2:$A$3000,0)),"") | G5: Technique équipement | H5: Haute | I5: Fermé | J5: 46148 | K5: 46150 | L5: =IF(K5="","",K5-J5) | M5: Intervention sur site sous 24 heures, remplacement du capteur de détection. | N5: Marc Olivier - Service technique
A6: K005 | B6: Remise non appliquée sur facture | C6: E002 | D6: =IFERROR(INDEX(Entreprises!$B$2:$B$3000,MATCH(C6,Entreprises!$A$2:$A$3000,0)),"") | E6: C003 | F6: =IFERROR(INDEX(Contacts!$E$2:$E$3000,MATCH(E6,Contacts!$A$2:$A$3000,0)),"") | G6: Facturation | H6: Normale | I6: Fermé | J6: 46092 | K6: 46100 | L6: =IF(K6="","",K6-J6) | M6: Remise contractuelle oubliée sur deux factures. Avoir émis. | N6: Lucie Martin - Service client
A7: K006 | B7: Demande de certificats de conformité matières | C7: E022 | D7: =IFERROR(INDEX(Entreprises!$B$2:$B$3000,MATCH(C7,Entreprises!$A$2:$A$3000,0)),"") | E7: C035 | F7: =IFERROR(INDEX(Contacts!$E$2:$E$3000,MATCH(E7,Contacts!$A$2:$A$3000,0)),"") | G7: Documentation | H7: Normale | I7: Fermé | J7: 46238 | K7: 46241 | L7: =IF(K7="","",K7-J7) | M7: Envoi des certificats de conformité et des déclarations matières pour trois références. | N7: Karim Haddou - Qualité
A8: K007 | B8: Écart de teinte de la dorure sur étuis | C8: E008 | D8: =IFERROR(INDEX(Entreprises!$B$2:$B$3000,MATCH(C8,Entreprises!$A$2:$A$3000,0)),"") | E8: C012 | F8: =IFERROR(INDEX(Contacts!$E$2:$E$3000,MATCH(E8,Contacts!$A$2:$A$3000,0)),"") | G8: Qualité produit | H8: Haute | I8: Fermé | J8: 45973 | K8: 45989 | L8: =IF(K8="","",K8-J8) | M8: Écart de teinte constaté sur un lot d'étuis. Réimpression partielle et ajustement du standard couleur. | N8: Karim Haddou - Qualité
A9: K008 | B9: Livraison incomplète (palette manquante) | C9: E014 | D9: =IFERROR(INDEX(Entreprises!$B$2:$B$3000,MATCH(C9,Entreprises!$A$2:$A$3000,0)),"") | E9: C024 | F9: =IFERROR(INDEX(Contacts!$E$2:$E$3000,MATCH(E9,Contacts!$A$2:$A$3000,0)),"") | G9: Livraison | H9: Normale | I9: Fermé | J9: 46195 | K9: 46198 | L9: =IF(K9="","",K9-J9) | M9: Une palette manquante sur la livraison, renvoyée en express. | N9: Lucie Martin - Service client
A10: K009 | B10: Ajustement du calendrier de livraison | C10: E026 | D10: =IFERROR(INDEX(Entreprises!$B$2:$B$3000,MATCH(C10,Entreprises!$A$2:$A$3000,0)),"") | E10: C043 | F10: =IFERROR(INDEX(Contacts!$E$2:$E$3000,MATCH(E10,Contacts!$A$2:$A$3000,0)),"") | G10: Livraison | H10: Basse | I10: Fermé | J10: 46204 | K10: 46205 | L10: =IF(K10="","",K10-J10) | M10: Décalage de deux livraisons à la demande du client pendant la période estivale. | N10: Lucie Martin - Service client
A11: K010 | B11: Étiquettes décollées après stockage à froid | C11: E012 | D11: =IFERROR(INDEX(Entreprises!$B$2:$B$3000,MATCH(C11,Entreprises!$A$2:$A$3000,0)),"") | E11: C019 | F11: =IFERROR(INDEX(Contacts!$E$2:$E$3000,MATCH(E11,Contacts!$A$2:$A$3000,0)),"") | G11: Qualité produit | H11: Haute | I11: En attente client | J11: 46293 | L11: =IF(K11="","",K11-J11) | M11: Décollement constaté après stockage à 4 °C. Tests de résistance lancés ; en attente des conditions exactes de stockage côté client. | N11: Karim Haddou - Qualité
A12: K011 | B12: Coffrets abîmés pendant le transport | C12: E027 | D12: =IFERROR(INDEX(Entreprises!$B$2:$B$3000,MATCH(C12,Entreprises!$A$2:$A$3000,0)),"") | E12: C045 | F12: =IFERROR(INDEX(Contacts!$E$2:$E$3000,MATCH(E12,Contacts!$A$2:$A$3000,0)),"") | G12: Livraison | H12: Normale | I12: Fermé | J12: 46037 | K12: 46044 | L12: =IF(K12="","",K12-J12) | M12: Coins enfoncés sur une partie des coffrets. Renforcement du calage palette. | N12: Lucie Martin - Service client
A13: K012 | B13: Réglage étiqueteuse ETQ-400 après maintenance | C13: E021 | D13: =IFERROR(INDEX(Entreprises!$B$2:$B$3000,MATCH(C13,Entreprises!$A$2:$A$3000,0)),"") | E13: C034 | F13: =IFERROR(INDEX(Contacts!$E$2:$E$3000,MATCH(E13,Contacts!$A$2:$A$3000,0)),"") | G13: Technique équipement | H13: Normale | I13: Fermé | J13: 46062 | K13: 46064 | L13: =IF(K13="","",K13-J13) | M13: Dérive de positionnement des étiquettes après la visite préventive. Réglage effectué. | N13: Marc Olivier - Service technique
A14: K013 | B14: Retard de validation BAT coffrets | C14: E017 | D14: =IFERROR(INDEX(Entreprises!$B$2:$B$3000,MATCH(C14,Entreprises!$A$2:$A$3000,0)),"") | E14: C027 | F14: =IFERROR(INDEX(Contacts!$E$2:$E$3000,MATCH(E14,Contacts!$A$2:$A$3000,0)),"") | G14: Livraison | H14: Normale | I14: Fermé | J14: 46084 | K14: 46087 | L14: =IF(K14="","",K14-J14) | M14: BAT envoyé avec trois jours de retard, planning de production réajusté sans impact sur la livraison. | N14: Lucie Martin - Service client
A15: K014 | B15: Question technique sur l'adhésif des étiquettes | C15: E023 | D15: =IFERROR(INDEX(Entreprises!$B$2:$B$3000,MATCH(C15,Entreprises!$A$2:$A$3000,0)),"") | E15: C038 | F15: =IFERROR(INDEX(Contacts!$E$2:$E$3000,MATCH(E15,Contacts!$A$2:$A$3000,0)),"") | G15: Technique équipement | H15: Basse | I15: Nouveau | J15: 46302 | L15: =IF(K15="","",K15-J15) | M15: Le client demande la compatibilité de l'adhésif avec un nouveau film de flacon. | N15: Marc Olivier - Service technique
A16: K015 | B16: Demande de fiches techniques papier certifié | C16: E001 | D16: =IFERROR(INDEX(Entreprises!$B$2:$B$3000,MATCH(C16,Entreprises!$A$2:$A$3000,0)),"") | E16: C002 | F16: =IFERROR(INDEX(Contacts!$E$2:$E$3000,MATCH(E16,Contacts!$A$2:$A$3000,0)),"") | G16: Documentation | H16: Basse | I16: Fermé | J16: 46206 | K16: 46213 | L16: =IF(K16="","",K16-J16) | M16: Envoi des fiches techniques et certificats du papier certifié pour le projet mono-matériau. | N16: Karim Haddou - Qualité
A17: K016 | B17: Écart de quantité facturée | C17: E025 | D17: =IFERROR(INDEX(Entreprises!$B$2:$B$3000,MATCH(C17,Entreprises!$A$2:$A$3000,0)),"") | E17: C040 | F17: =IFERROR(INDEX(Contacts!$E$2:$E$3000,MATCH(E17,Contacts!$A$2:$A$3000,0)),"") | G17: Facturation | H17: Normale | I17: Fermé | J17: 46129 | K17: 46136 | L17: =IF(K17="","",K17-J17) | M17: Quantité facturée supérieure à la quantité livrée sur une commande. Avoir émis. | N17: Lucie Martin - Service client
A18: K017 | B18: Étiquettes logistiques illisibles au scanner | C18: E007 | D18: =IFERROR(INDEX(Entreprises!$B$2:$B$3000,MATCH(C18,Entreprises!$A$2:$A$3000,0)),"") | E18: C011 | F18: =IFERROR(INDEX(Contacts!$E$2:$E$3000,MATCH(E18,Contacts!$A$2:$A$3000,0)),"") | G18: Qualité produit | H18: Haute | I18: Fermé | J18: 45993 | K18: 46000 | L18: =IF(K18="","",K18-J18) | M18: Contraste insuffisant des codes-barres sur un lot. Lot remplacé et paramètres d'impression corrigés. | N18: Karim Haddou - Qualité
A19: K018 | B19: Retard de livraison de caisses carton | C19: E028 | D19: =IFERROR(INDEX(Entreprises!$B$2:$B$3000,MATCH(C19,Entreprises!$A$2:$A$3000,0)),"") | E19: C046 | F19: =IFERROR(INDEX(Contacts!$E$2:$E$3000,MATCH(E19,Contacts!$A$2:$A$3000,0)),"") | G19: Livraison | H19: Normale | I19: En cours | J19: 46297 | L19: =IF(K19="","",K19-J19) | M19: Livraison décalée de quatre jours à cause d'un manque de matière. Nouvelle date communiquée au client. | N19: Lucie Martin - Service client

Sheet Commandes
A1: ID commande | B1: N° de commande client | C1: Date de commande | D1: ID entreprise | E1: Entreprise | F1: ID produit | G1: Produit | H1: Quantité | I1: Prix unitaire HT (€) | J1: Remise | K1: Montant HT (€) | L1: Date de livraison prévue | M1: Date de livraison effective | N1: Retard de livraison (jours) | O1: Statut | P1: ID commercial
A2: CMD-2024-0001 | B2: PO-INT-57459 | C2: 45566 | D2: E004 | E2: =IFERROR(INDEX(Entreprises!$B$2:$B$3000,MATCH(D2,Entreprises!$A$2:$A$3000,0)),"") | F2: P005 | G2: =IFERROR(INDEX(Produits!$C$2:$C$3000,MATCH(F2,Produits!$A$2:$A$3000,0)),"") | H2: 9 | I2: =IFERROR(INDEX(Produits!$G$2:$G$3000,MATCH(F2,Produits!$A$2:$A$3000,0)),"") | J2: 0.04 | K2: =IF(OR(H2="",I2=""),"",ROUND(H2*I2*(1-J2),2)) | L2: 45580 | M2: 45581 | N2: =IF(M2="","",MAX(0,M2-L2)) | O2: Facturée | P2: U002
